Workbook

Sheet Summary
E1: INR to USD
E2: INR to CAD
E3: Mileage
E4: Home Use %
F5: =G5+1 -> 2024 | G5: =H5+1 -> 2023 | H5: =I5+1 -> 2022 | I5: =J5+1 -> 2021 | J5: =K5+1 -> 2020 | K5: =L5+1 -> 2019 | L5: =M5+1 -> 2018 | M5: 2017
E6: W2 Wages | H6: 37995.76 | I6: 49793.32 | J6: 69549.66 | K6: 84444.89 | L6: 70399.57 | M6: 63132.46
E7: Taxes Withheld | H7: 4063.44 | I7: 5834.02 | J7: 10423.75 | K7: 12386.28 | L7: 7675.56 | M7: 7909.36
E10: Biz Income/Loss
C11: work in progress | E11: 1. Comfort Foods (dba Robertos Pizza) | M11: =Robertos!D3-Robertos!D4 -> -44581.92
E12: 2. CloudBaud LLC | F12: ='CB-24'!C6 -> 153952 | G12: ='CB-23'!C6 -> 38376 | H12: ='CB-22'!C6 -> 365772.34 | I12: ='CB-21'!C6 -> 67285.005 | J12: ='CB-20'!C6 -> -1569.8499 | K12: ='CB-19'!D6 -> 79825.513 | L12: ='CB-18'!C3 -> 485019.41 | M12: ='CB-17'!C6 -> 334565.42
C13: question for IRS or CPA | E13: 3. Teaching Income
E14: 4. Canada Condo Sale
C15: complete for CPA | E15: Rental Income
E16: 1. Olympic Court
C17: filed with CPA | E17: 2. Cherry Crest
E18: 3. Woodridge
C19: filed with IRS
E21: Jishnu Roth IRA | M21: 5500
E22: Deepika ROTH IRA | L22: 5500 | M22: 5500
E23: SEP IRA | L23: 43605.6 | M23: 5244.9
E24: 1099-R | L24: 4862.99 | M24: 0
E25: Child Education Fund | M25: 4000
E27: Itemized deductions
E28: Real Estate Interest Woodridge | I28: 10516.14 | J28: 16431.02 | K28: 18719.36 | L28: 13698.52 | M28: 17619.67
E29: Real Estate Interest Lake Hills
E30: Real Estate Interest Olympic Court
E32: Real Estate Taxes Woodridge | I32: 7271.09 | J32: 7191.32 | K32: 6633.65 | L32: 6191.31 | M32: 5009.22
E33: Real Estate Taxes Cherry Crest | I33: 4110.17 | J33: 3186.17 | K33: 2724.69 | L33: 2761.75
E34: Real Estate Taxes Lake Hills
E35: Real Estate Taxes Olympic Court
E36: Real Estate Taxes Rudins Lounge
E41: Capital Gains/Loss | M41: =-1*32307.82 -> -32307.82
E42: Investment Interest | M42: 115.94
E44: Gifts to Charity | G44: Rs. 50000 | H44: =51 -> 51 | M44: 500
E47: Medical/Dental HSA | L47: 5800 | M47: 4050
I75: 7

Sheet LH-23
C2: keys, packing
C3: grass cutting | D3: 250

Sheet WR-23

Sheet CB-24
B1: =Summary!F5 -> 2024 | G1: ="CLOUDBAUD CONSULTING "& Summary!F5 & " ONLY" -> CLOUDBAUD CONSULTING 2024 ONLY
F2: TOTAL | G2: Jan | H2: Feb | I2: Mar | J2: Apr | K2: May | L2: Jun | M2: Jul | N2: Aug | O2: Sep | P2: Oct | Q2: Nov | R2: Dec | T2: Check# | U2: Amount | V2: Date | W2: Payee
B3: ='CB-17'!B3 -> CONSULTING REVENUE | C3: =F3 -> 153952 | F3: =SUM(G3:R3) -> 153952 | G3: =8496 -> 8496 | H3: 0 | I3: =7168 -> 7168 | J3: =18816 -> 18816 | K3: 0 | L3: =6272+15840 -> 22112 | M3: =19712 -> 19712 | N3: =17600+1792 -> 19392 | O3: 38720 | P3: 19536 | Q3: 0 | R3: 0
F4: YTD | G4: =G3 -> 8496 | H4: =G4+H3 -> 8496 | I4: =H4+I3 -> 15664 | J4: =I4+J3 -> 34480 | K4: =J4+K3 -> 34480 | L4: =K4+L3 -> 56592 | M4: =L4+M3 -> 76304 | N4: =M4+N3 -> 95696 | O4: =N4+O3 -> 134416 | ... R4: =Q4+R3 -> 153952
B5: ='CB-17'!B5 -> TOTAL EXPENSES | C5: =C7+C20+C27+C76+C35+C59+C45+C62+C67+C71 -> 0
B6: ='CB-17'!B6 -> NET REVENUE | C6: =C3-C5 -> 153952
B7: UTILITIES | C7: =SUM(D8:D14) -> 0 | D7: Prorated | E7: Rate | F7: Annual | G7: =SUM(G8:G14) -> 0 | H7: =SUM(H8:H14) -> 0 | I7: =SUM(I8:I14) -> 0 | J7: =SUM(J8:J14) -> 0 | K7: =SUM(K8:K14) -> 0 | L7: =SUM(L8:L14) -> 0 | M7: =SUM(M8:M14) -> 0 | N7: =SUM(N8:N14) -> 0 | ... R7: =SUM(R8:R14) -> 0
B8: ELECTRICITY | D8: =E8*F8 -> 0 | E8: 0.17 | F8: =SUM(G8:R8) -> 0
B9: WASTE | D9: =E9*F9 -> 0 | E9: 0.17 | F9: =SUM(G9:R9) -> 0
B10: Water | D10: =E10*F10 -> 0 | E10: 0.17 | F10: =SUM(G10:R10) -> 0
B11: Security | D11: =E11*F11 -> 0 | E11: 0.17 | F11: =SUM(G11:R11) -> 0
B12: Landscaping | D12: =E12*F12 -> 0 | E12: 0.17 | F12: =SUM(G12:R12) -> 0
B13: Home Owners Insurance | D13: =E13*F13 -> 0 | E13: 0.17 | F13: =SUM(G13:R13) -> 0
B14: Appliance Maintenance | D14: =E14*F14 -> 0 | E14: 0.17 | F14: =SUM(G14:R14) -> 0
B16: Mobile | C16: =D16 -> 0 | D16: =F16*E16 -> 0 | E16: 0.5 | F16: =SUM(G16:R16) -> 0
B17: Mobile Device (samsung) | E17: 1
B19: Biz Registration | C19: =F19 -> 0 | E19: 1 | F19: =SUM(G19:R19) -> 0
B20: WA DOR | C20: =F20 -> 0 | E20: 1 | F20: =SUM(G20:R20) -> 0
B21: Garnishment Fee | C21: =F21 -> 0 | E21: 1 | F21: =SUM(G21:R21) -> 0
B22: LNI Insurance | C22: =F22 -> 0 | E22: 1 | F22: =SUM(G22:R22) -> 0
B23: WA Employment Security
B24: Commercial Insurance | C24: =F24 -> 0 | E24: 1
B25: Supplies | C25: =F25 -> 40.34 | E25: 1 | F25: =SUM(G25:R25) -> 40.34 | H25: 40.34
B26: STATIONARIES | C26: =F26 -> 0 | E26: 1 | F26: =SUM(G26:R26) -> 0
B27: PAYROLL | C27: =SUM(F28:F31) -> 0 | E27: Rate
D28: =F28*E28 -> 0 | E28: 1 | F28: =SUM(G28:R28) -> 0
D29: =F29*E29 -> 0 | E29: 1 | F29: =SUM(G29:R29) -> 0
D30: =F30*E30 -> 0 | E30: 1 | F30: =SUM(G30:R30) -> 0
D31: =F31*E31 -> 0 | E31: 1 | F31: =SUM(H31:R31) -> 0
A33: godaddy | B33: WEB HOSTING | F33: =SUM(G33:R33) -> 0
A34: xfiniti | B34: BROADBAND | E34: 0.5 | F34: =SUM(G34:R34) -> 0
A35: t-mobile | B35: Logo Services | F35: =SUM(G35:R35) -> 0
A36: logo | B36: Temp Services | F36: =SUM(G36:R36) -> 0
A37: misc. | B37: Professional Services | C37: =E37 -> 0 | E37: =SUM(G37:R37) -> 0
B38: Bank Fees | C38: =E38 -> 0 | E38: =SUM(G38:R38) -> 0
B39: RENOVATION | C39: =SUM(F40:F43) -> 800
B40: Flooring | F40: =SUM(G40:R40) -> 0 | T40: 3044 | U40: 330 | V40: 44766 | W40: Edilberto
B41: Paint | F41: =SUM(G41:R41) -> 0 | T41: 3583 | U41: 300 | V41: 44745 | W41: SEARS
B42: bathroom | F42: =SUM(G42:R42) -> 0 | T42: 9917 | U42: 200 | V42: 44760 | W42: BoA
B43: electrical work | F43: 800 | T43: 3022 | U43: 570 | V43: 44779 | W43: Edilberto
K44: 156.25 | T44: 3023 | U44: 350 | V44: 44779 | W44: Edilberto
B45: Auto Mileage (client visits) | T45: 3024 | U45: 151 | V45: 44794 | W45: Edilberto
B46: =B1 & " IRS rate" -> 2024 IRS rate | E46: 0.655 | F46: =SUM(G46:R46) -> 24.44 | J46: =20*$E$46+3.5+7.84 -> 24.44 | T46: 3025 | U46: 180 | V46: 44794 | W46: Edilberto
T47: 3584 | U47: 300 | V47: 44776 | W47: SEARS
B48: PROFESSIONAL SUBSCRIPTIONS | C48: =SUM(F49:F57) -> 0 | G48: =SUM(G49:G57) -> 0 | H48: =SUM(H49:H57) -> 0 | I48: =SUM(I49:I57) -> 0 | J48: =SUM(J49:J57) -> 0 | K48: =SUM(K49:K57) -> 0 | L48: =SUM(L49:L57) -> 0 | M48: =SUM(M49:M57) -> 0 | N48: =SUM(N49:N57) -> 0 | ... R48: =SUM(R49:R57) -> 0 | T48: 9918 | U48: 200 | V48: 44793 | W48: BoA
B49: Cloud Academy | C49: =E49*D49 -> 0 | D49: =E49*F49 -> 0 | E49: 1 | F49: =SUM(G49:R49) -> 0 | T49: 3045 | U49: 135 | V49: 44814 | W49: Edilberto
B50: Packt | C50: =E50*D50 -> 0 | D50: =E50*F50 -> 0 | E50: 1 | F50: =SUM(G50:R50) -> 0 | T50: 3046 | U50: 165 | V50: 44814 | W50: Edilberto
B51: Pluralsight | C51: =E51*D51 -> 0 | D51: =E51*F51 -> 0 | E51: 1 | F51: =SUM(G51:R51) -> 0 | T51: 3583 | U51: 300 | V51: 44808 | W51: SEARS
B52: Linux Academy | C52: =E52*D52 -> 0 | D52: =E52*F52 -> 0 | E52: 1 | F52: =SUM(G52:R52) -> 0 | T52: 9919 | U52: 200 | V52: 44822 | W52: BoA
B53: Adobe | C53: =E53*D53 -> 0 | D53: =E53*F53 -> 0 | E53: 1 | F53: =SUM(G53:R53) -> 0 | T53: 3586 | U53: 300 | V53: 44838 | W53: SEARS
B54: O365 | C54: =E54*D54 -> 0 | D54: =E54*F54 -> 0 | E54: 1 | F54: =SUM(G54:R54) -> 0 | T54: 9920 | U54: 200 | V54: 44852 | W54: BoA
B55: Microsoft Alumni | C55: =E55*D55 -> 0 | D55: =E55*F55 -> 0 | E55: 1 | F55: =SUM(G55:R55) -> 0 | T55: 101 | U55: 80 | V55: 44879 | W55: zach devita
B56: LinkedIn | C56: =E56*D56 -> 0 | D56: =E56*F56 -> 0 | E56: 1 | F56: =SUM(G56:R56) -> 0 | T56: 1004 | U56: 6000 | V56: 44890 | W56: self
B57: itunes | C57: =E57*D57 -> 0 | D57: =E57*F57 -> 0 | E57: 1 | F57: =SUM(G57:R57) -> 0 | T57: 3587 | U57: 238.18 | V57: 44870 | W57: SEARS
T58: 9921 | U58: 200 | V58: 44885 | W58: BoA
T59: 103 | U59: 1230.57 | V59: 44898 | W59: zach devita
T60: 3047 | U60: 1449.68 | V60: 44913 | W60: zach devita
T61: 9922 | U61: 200 | V61: 44913 | W61: BoA

Sheet CB-23
B1: =Summary!G5 -> 2023 | G1: ="CLOUDBAUD CONSULTING "& Summary!G5 & " ONLY" -> CLOUDBAUD CONSULTING 2023 ONLY
F2: TOTAL | G2: Jan | H2: Feb | I2: Mar | J2: Apr | K2: May | L2: Jun | M2: Jul | N2: Aug | O2: Sep | P2: Oct | Q2: Nov | R2: Dec | T2: Check# | U2: Amount | V2: Date | W2: Payee
B3: ='CB-17'!B3 -> CONSULTING REVENUE | C3: =F3 -> 39176 | F3: =SUM(G3:R3) -> 39176 | P3: 0 | Q3: =10384+1888 -> 12272 | R3: =10620+ 16284 -> 26904
F4: YTD | G4: =G3 -> 0 | H4: =G4+H3 -> 0 | I4: =H4+I3 -> 0 | J4: =I4+J3 -> 0 | K4: =J4+K3 -> 0 | L4: =K4+L3 -> 0 | M4: =L4+M3 -> 0 | N4: =M4+N3 -> 0 | O4: =N4+O3 -> 0 | ... R4: =Q4+R3 -> 39176
B5: ='CB-17'!B5 -> TOTAL EXPENSES | C5: =C7+C20+C27+C76+C35+C59+C45+C62+C67+C71 -> 800
B6: ='CB-17'!B6 -> NET REVENUE | C6: =C3-C5 -> 38376
B7: UTILITIES | C7: =SUM(D8:D14) -> 0 | D7: Prorated | E7: Rate | F7: Annual | G7: =SUM(G8:G14) -> 0 | H7: =SUM(H8:H14) -> 0 | I7: =SUM(I8:I14) -> 0 | J7: =SUM(J8:J14) -> 0 | K7: =SUM(K8:K14) -> 0 | L7: =SUM(L8:L14) -> 0 | M7: =SUM(M8:M14) -> 0 | N7: =SUM(N8:N14) -> 0 | ... R7: =SUM(R8:R14) -> 0
B8: ='CB-17'!B8 -> Electricity | C8: ='CB-17'!C8 -> 380.358 | D8: =E8*F8 -> 0 | E8: ='CB-17'!E8 -> 0.17 | F8: =SUM(G8:R8) -> 0
B9: ='CB-17'!B9 -> Waste & Recycle | C9: ='CB-17'!C9 -> 68.6137 | D9: =E9*F9 -> 0 | E9: ='CB-17'!E9 -> 0.17 | F9: =SUM(G9:R9) -> 0
B10: ='CB-17'!B10 -> Water & Sewer | C10: ='CB-17'!C10 -> 0 | D10: =E10*F10 -> 0 | E10: ='CB-17'!E10 -> 0.17 | F10: =SUM(G10:R10) -> 0
B11: ='CB-17'!B11 -> Security | C11: ='CB-17'!C11 -> 0 | D11: =E11*F11 -> 0 | E11: ='CB-17'!E11 -> 0.17 | F11: =SUM(G11:R11) -> 0
B12: ='CB-17'!B12 -> Landscaping | C12: ='CB-17'!C12 -> 0 | D12: =E12*F12 -> 0 | E12: ='CB-17'!E12 -> 0.17 | F12: =SUM(G12:R12) -> 0
B13: ='CB-17'!B13 -> Home Owners Insurance | C13: ='CB-17'!C13 -> 0 | D13: =E13*F13 -> 0 | E13: ='CB-17'!E13 -> 0.17 | F13: =SUM(G13:R13) -> 0
B14: ='CB-17'!B14 -> Appliance Maintenance | C14: ='CB-17'!C14 -> 0 | D14: =E14*F14 -> 0 | E14: ='CB-17'!E14 -> 0.5 | F14: =SUM(G14:R14) -> 0
B15: ='CB-17'!B15 -> Apple Warranty | C15: ='CB-17'!C15 -> 0 | D15: =E15*F15 -> 0 | E15: ='CB-17'!E15 -> 0.5 | F15: =SUM(G15:R15) -> 0
B16: ='CB-17'!B16 -> Computers Warranty | C16: ='CB-17'!C16 -> 0 | D16: =E16*F16 -> 0 | E16: ='CB-17'!E16 -> 0.5 | F16: =SUM(G16:R16) -> 0
B17: ='CB-17'!B17 -> Cellular Service | C17: ='CB-17'!C17 -> 0 | D17: =E17*F17 -> 0 | E17: ='CB-17'!E17 -> 0.5 | F17: =SUM(G17:R17) -> 0
B18: ='CB-17'!B18 -> Broadband | C18: ='CB-17'!C18 -> 0 | D18: =E18*F18 -> 0 | E18: ='CB-17'!E18 -> 0.5 | F18: =SUM(G18:R18) -> 0
B19: ='CB-17'!B19 -> TV Cable | C19: ='CB-17'!C19 -> 0 | D19: =E19*F19 -> 0 | E19: ='CB-17'!E19 -> 0.5 | F19: =SUM(G19:R19) -> 0
B20: ='CB-17'!B20 -> DEPRECIABLE ASSETS | G20: =SUM(G21:G26) -> 0 | H20: =SUM(H21:H26) -> 0 | I20: =SUM(I21:I26) -> 0 | J20: =SUM(J21:J26) -> 0 | K20: =SUM(K21:K26) -> 0 | L20: =SUM(L21:L26) -> 0 | M20: =SUM(M21:M26) -> 0 | N20: =SUM(N21:N26) -> 0 | ... R20: =SUM(R21:R26) -> 0
B27: Biz Registration | C27: =F27 -> 0 | E27: 1 | F27: =SUM(G27:R27) -> 0
B28: WA DOR | C28: =F28 -> 0 | E28: 1 | F28: =SUM(G28:R28) -> 0
B29: Garnishment Fee | C29: =F29 -> 0 | E29: 1 | F29: =SUM(G29:R29) -> 0
B30: LNI Insurance | C30: =F30 -> 0 | E30: 1 | F30: =SUM(G30:R30) -> 0
B31: WA Employment Security
B32: Commercial Insurance | C32: =F32 -> 0 | E32: 1
A33: godaddy | B33: Supplies | C33: =F33 -> 40.34 | E33: 1 | F33: =SUM(G33:R33) -> 40.34 | H33: 40.34
A34: xfiniti | B34: STATIONARIES | C34: =F34 -> 0 | E34: 1 | F34: =SUM(G34:R34) -> 0
A35: t-mobile | D35: =F35*E35 -> 0 | E35: 1 | F35: =SUM(G35:R35) -> 0
A36: logo | D36: =F36*E36 -> 0 | E36: 1 | F36: =SUM(G36:R36) -> 0
A37: misc. | D37: =F37*E37 -> 0 | E37: 1 | F37: =SUM(H37:R37) -> 0
B39: WEB HOSTING | F39: =SUM(G39:R39) -> 0
B40: BROADBAND | E40: 0.5 | F40: =SUM(G40:R40) -> 0 | T40: 3044 | U40: 330 | V40: 44766 | W40: Edilberto
B41: Logo Services | F41: =SUM(G41:R41) -> 0 | T41: 3583 | U41: 300 | V41: 44745 | W41: SEARS
B42: Temp Services | F42: =SUM(G42:R42) -> 0 | T42: 9917 | U42: 200 | V42: 44760 | W42: BoA
B43: Professional Services | C43: =E43 -> 0 | E43: =SUM(G43:R43) -> 0 | T43: 3022 | U43: 570 | V43: 44779 | W43: Edilberto
B44: Bank Fees | C44: =E44 -> 0 | E44: =SUM(G44:R44) -> 0 | T44: 3023 | U44: 350 | V44: 44779 | W44: Edilberto
B45: RENOVATION | C45: =SUM(F46:F49) -> 800 | T45: 3024 | U45: 151 | V45: 44794 | W45: Edilberto
B46: Flooring | F46: =SUM(G46:R46) -> 0 | T46: 3025 | U46: 180 | V46: 44794 | W46: Edilberto
B47: Paint | F47: =SUM(G47:R47) -> 0 | T47: 3584 | U47: 300 | V47: 44776 | W47: SEARS
B48: bathroom | F48: =SUM(G48:R48) -> 0 | T48: 9918 | U48: 200 | V48: 44793 | W48: BoA
B49: electrical work | F49: 800 | T49: 3045 | U49: 135 | V49: 44814 | W49: Edilberto
K50: 156.25 | T50: 3046 | U50: 165 | V50: 44814 | W50: Edilberto
B51: Auto Mileage (client visits) | T51: 3583 | U51: 300 | V51: 44808 | W51: SEARS
B52: 2023 IRS rate | E52: 0.655 | F52: =SUM(G52:R52) -> 24.44 | J52: =20*$E$52+3.5+7.84 -> 24.44 | T52: 9919 | U52: 200 | V52: 44822 | W52: BoA
T53: 3586 | U53: 300 | V53: 44838 | W53: SEARS
B54: PROFESSIONAL SUBSCRIPTIONS | C54: =SUM(F55:F63) -> 0 | G54: =SUM(G55:G63) -> 0 | H54: =SUM(H55:H63) -> 0 | I54: =SUM(I55:I63) -> 0 | J54: =SUM(J55:J63) -> 0 | K54: =SUM(K55:K63) -> 0 | L54: =SUM(L55:L63) -> 0 | M54: =SUM(M55:M63) -> 0 | N54: =SUM(N55:N63) -> 0 | ... R54: =SUM(R55:R63) -> 0 | T54: 9920 | U54: 200 | V54: 44852 | W54: BoA
B55: Cloud Academy | C55: =E55*D55 -> 0 | D55: =E55*F55 -> 0 | E55: 1 | F55: =SUM(G55:R55) -> 0 | T55: 101 | U55: 80 | V55: 44879 | W55: zach devita
B56: Packt | C56: =E56*D56 -> 0 | D56: =E56*F56 -> 0 | E56: 1 | F56: =SUM(G56:R56) -> 0 | T56: 1004 | U56: 6000 | V56: 44890 | W56: self
B57: Pluralsight | C57: =E57*D57 -> 0 | D57: =E57*F57 -> 0 | E57: 1 | F57: =SUM(G57:R57) -> 0 | T57: 3587 | U57: 238.18 | V57: 44870 | W57: SEARS
B58: Linux Academy | C58: =E58*D58 -> 0 | D58: =E58*F58 -> 0 | E58: 1 | F58: =SUM(G58:R58) -> 0 | T58: 9921 | U58: 200 | V58: 44885 | W58: BoA
B59: Adobe | C59: =E59*D59 -> 0 | D59: =E59*F59 -> 0 | E59: 1 | F59: =SUM(G59:R59) -> 0 | T59: 103 | U59: 1230.57 | V59: 44898 | W59: zach devita
B60: O365 | C60: =E60*D60 -> 0 | D60: =E60*F60 -> 0 | E60: 1 | F60: =SUM(G60:R60) -> 0 | T60: 3047 | U60: 1449.68 | V60: 44913 | W60: zach devita
B61: Microsoft Alumni | C61: =E61*D61 -> 0 | D61: =E61*F61 -> 0 | E61: 1 | F61: =SUM(G61:R61) -> 0 | T61: 9922 | U61: 200 | V61: 44913 | W61: BoA
B62: LinkedIn | C62: =E62*D62 -> 0 | D62: =E62*F62 -> 0 | E62: 1 | F62: =SUM(G62:R62) -> 0
B63: itunes | C63: =E63*D63 -> 0 | D63: =E63*F63 -> 0 | E63: 1 | F63: =SUM(G63:R63) -> 0

Sheet CB-22
B1: =Summary!H5 -> 2022 | G1: ="CLOUDBAUD CONSULTING "& Summary!H5 & " ONLY" -> CLOUDBAUD CONSULTING 2022 ONLY
F2: TOTAL | G2: Jan | H2: Feb | I2: Mar | J2: Apr | K2: May | L2: Jun | M2: Jul | N2: Aug | O2: Sep | P2: Oct | Q2: Nov | R2: Dec | T2: Check# | U2: Amount | V2: Date | W2: Payee
B3: ='CB-17'!B3 -> CONSULTING REVENUE | C3: =F3 -> 366830.49 | F3: =SUM(G3:R3) -> 366830.49 | G3: =24030 -> 24030 | H3: =15080+24030 -> 39110 | I3: =22815+8700 -> 31515 | J3: =14065+19035 -> 33100 | K3: 18560 | L3: =18270+41985 -> 60255 | M3: =6075+18270+22815 -> 47160 | N3: =25245+17835 -> 43080 | O3: 20010 | P3: =29010.49 -> 29010.49 | Q3: 0 | R3: =21000 -> 21000
F4: YTD | G4: =G3 -> 24030 | H4: =G4+H3 -> 63140 | I4: =H4+I3 -> 94655 | J4: =I4+J3 -> 127755 | K4: =J4+K3 -> 146315 | L4: =K4+L3 -> 206570 | M4: =L4+M3 -> 253730 | N4: =M4+N3 -> 296810 | O4: =N4+O3 -> 316820 | ... R4: =Q4+R3 -> 366830.49
B5: ='CB-17'!B5 -> TOTAL EXPENSES | C5: =C7+C20+C27+C76+C35+C59+C45+C62+C67+C71 -> 1058.1463
B6: ='CB-17'!B6 -> NET REVENUE | C6: =C3-C5 -> 365772.34
B7: UTILITIES | C7: =SUM(D8:D14) -> 1058.1463 | D7: Prorated | E7: Rate | F7: Annual | G7: =SUM(G8:G14) -> 1171.42 | H7: =SUM(H8:H14) -> 688.25 | I7: =SUM(I8:I14) -> 200.54 | J7: =SUM(J8:J14) -> 287.86 | K7: =SUM(K8:K14) -> 1300.54 | L7: =SUM(L8:L14) -> 473.27 | M7: =SUM(M8:M14) -> 528.96 | N7: =SUM(N8:N14) -> 328.28 | ... R7: =SUM(R8:R14) -> 200.54
B8: ='CB-17'!B8 -> Electricity | C8: =D8 -> 564.3405 | D8: =E8*F8 -> 564.3405 | E8: ='CB-17'!E8 -> 0.17 | F8: =SUM(G8:R8) -> 3319.65 | G8: 944.98 | H8: 366.63 | I8: 0 | J8: 0 | K8: 1100 | L8: 272.73 | M8: 151.78 | N8: 127.74 | O8: 177.71 | P8: 178.08 | Q8: 0 | R8: 0
B9: ='CB-17'!B9 -> Waste & Recycle | C9: =D9 -> 74.4124 | D9: =E9*F9 -> 74.4124 | E9: ='CB-17'!E9 -> 0.17 | F9: =SUM(G9:R9) -> 437.72 | G9: 86.44 | J9: 87.32 | M9: 176.64 | P9: 87.32
B10: ='CB-17'!B10 -> Water & Sewer | C10: =D10 -> 0 | D10: =E10*F10 -> 0 | E10: ='CB-17'!E10 -> 0.17 | F10: =SUM(G10:R10) -> 0
B11: ='CB-17'!B11 -> Security | C11: =D11 -> 133.7934 | D11: =E11*F11 -> 133.7934 | E11: ='CB-17'!E11 -> 0.17 | F11: =SUM(G11:R11) -> 787.02 | G11: 0 | H11: 181.62 | I11: 60.54 | J11: 60.54 | K11: 60.54 | L11: 60.54 | M11: 60.54 | N11: 60.54 | O11: 60.54 | P11: 60.54 | Q11: 60.54 | R11: 60.54
B12: ='CB-17'!B12 -> Landscaping | C12: =D12 -> 285.6 | D12: =E12*F12 -> 285.6 | E12: ='CB-17'!E12 -> 0.17 | F12: =SUM(G12:R12) -> 1680 | G12: 140 | H12: 140 | I12: 140 | J12: 140 | K12: 140 | L12: 140 | M12: 140 | N12: 140 | O12: 140 | P12: 140 | Q12: 140 | R12: 140
B13: ='CB-17'!B13 -> Home Owners Insurance | C13: =D13 -> 0 | D13: =E13*F13 -> 0 | E13: ='CB-17'!E13 -> 0.17 | F13: =SUM(G13:R13) -> 0
B14: ='CB-17'!B14 -> Appliance Maintenance | C14: =D14 -> 0 | D14: =E14*F14 -> 0 | E14: ='CB-17'!E14 -> 0.5 | F14: =SUM(G14:R14) -> 0
B15: ='CB-17'!B15 -> Apple Warranty | C15: =D15 -> 0 | D15: =E15*F15 -> 0 | E15: ='CB-17'!E15 -> 0.5 | F15: =SUM(G15:R15) -> 0
B16: ='CB-17'!B16 -> Computers Warranty | C16: =D16 -> 0 | D16: =E16*F16 -> 0 | E16: ='CB-17'!E16 -> 0.5 | F16: =SUM(G16:R16) -> 0
B17: ='CB-17'!B17 -> Cellular Service | C17: =D17 -> 0 | D17: =E17*F17 -> 0 | E17: ='CB-17'!E17 -> 0.5 | F17: =SUM(G17:R17) -> 0
B18: ='CB-17'!B18 -> Broadband | C18: =D18 -> 0 | D18: =E18*F18 -> 0 | E18: ='CB-17'!E18 -> 0.5 | F18: =SUM(G18:R18) -> 0
B19: ='CB-17'!B19 -> TV Cable | C19: =D19 -> 0 | D19: =E19*F19 -> 0 | E19: ='CB-17'!E19 -> 0.5 | F19: =SUM(G19:R19) -> 0
B20: ='CB-17'!B20 -> DEPRECIABLE ASSETS | C20: =SUM(C21:C26) -> 0 | D20: Prorated | E20: Rate | F20: Annual | G20: =SUM(G21:G26) -> 0 | H20: =SUM(H21:H26) -> 0 | I20: =SUM(I21:I26) -> 0 | J20: =SUM(J21:J26) -> 0 | K20: =SUM(K21:K26) -> 0 | L20: =SUM(L21:L26) -> 0 | M20: =SUM(M21:M26) -> 0 | N20: =SUM(N21:N26) -> 0 | ... R20: =SUM(R21:R26) -> 0
B21: ='CB-17'!B21 -> ASUS Laptop | C21: =D21 -> 0 | D21: =E21*F21 -> 0 | E21: ='CB-17'!E21 -> 0.5 | F21: =SUM(G21:R21) -> 0
B22: ='CB-17'!B22 -> Mobile Device (samsung) | C22: =D22 -> 0 | D22: =E22*F22 -> 0 | E22: ='CB-17'!E22 -> 0.5 | F22: =SUM(G22:R22) -> 0
B23: ='CB-17'!B23 -> Cellphone Device | C23: =D23 -> 0 | D23: =E23*F23 -> 0 | E23: ='CB-17'!E23 -> 0.5 | F23: =SUM(G23:R23) -> 0
B24: ='CB-17'!B24 -> Supplies | C24: =D24 -> 0 | D24: =E24*F24 -> 0 | E24: ='CB-17'!E24 -> 1 | F24: =SUM(G24:R24) -> 0
B25: ='CB-17'!B25 -> Stationaries | C25: =D25 -> 0 | D25: =E25*F25 -> 0 | E25: ='CB-17'!E25 -> 1 | F25: =SUM(G25:R25) -> 0
B26: ='CB-17'!B26 -> Books | C26: =D26 -> 0 | D26: =E26*F26 -> 0 | E26: ='CB-17'!E26 -> 1 | F26: =SUM(G26:R26) -> 0
B27: ='CB-17'!B27 -> GOVERNMENT FEES | C27: =SUM(C28:C34) -> 0 | D27: Prorated | E27: Rate | F27: Annual
B28: ='CB-17'!B28 -> Biz Registration | C28: =D28 -> 0 | D28: =E28*F28 -> 0 | E28: ='CB-17'!E28 -> 1 | F28: =SUM(G28:R28) -> 0
B29: ='CB-17'!B29 -> Licensing | C29: =D29 -> 0 | D29: =E29*F29 -> 0 | E29: ='CB-17'!E29 -> 1 | F29: =SUM(G29:R29) -> 0
B30: ='CB-17'!B30 -> WA DOR Excise Tax | C30: =D30 -> 0 | D30: =E30*F30 -> 0 | E30: ='CB-17'!E30 -> 1 | F30: =SUM(G30:R30) -> 0
B31: ='CB-17'!B31 -> Garnishment Fee | C31: =F31 -> 0 | D31: =E31*F31 -> 0 | E31: ='CB-17'!E31 -> 1 | F31: =SUM(G31:R31) -> 0
B32: ='CB-17'!B32 -> LNI Insurance | C32: =F32 -> 0 | D32: =E32*F32 -> 0 | E32: ='CB-17'!E32 -> 1 | F32: =SUM(G32:R32) -> 0
A33: godaddy | B33: ='CB-17'!B33 -> WA Employment Security | C33: =F33 -> 0 | D33: =E33*F33 -> 0 | E33: ='CB-17'!E33 -> 1 | F33: =SUM(G33:R33) -> 0
A34: xfiniti | B34: ='CB-17'!B34 -> Commercial Insurance | C34: =F34 -> 0 | D34: =E34*F34 -> 0 | E34: ='CB-17'!E34 -> 1 | F34: =SUM(G34:R34) -> 0
A35: misc. | B35: ='CB-17'!B35 -> PROFESSIONAL SERVICES | C35: =SUM(C36:C44) -> 0 | D35: Prorated | E35: Rate | F35: Annual
B36: ='CB-17'!B36 -> Web Domains | C36: =D36 -> 0 | D36: =F36*E36 -> 0 | E36: ='CB-17'!E36 -> 1 | F36: =SUM(G36:R36) -> 0
B37: ='CB-17'!B37 -> Web Hosting | C37: =D37 -> 0 | D37: =F37*E37 -> 0 | E37: ='CB-17'!E37 -> 1 | F37: =SUM(G37:R37) -> 0
B38: ='CB-17'!B38 -> Digital Ads | C38: =D38 -> 0 | D38: =F38*E38 -> 0 | E38: ='CB-17'!E38 -> 1 | F38: =SUM(G38:R38) -> 0 | T38: 3044 | U38: 330 | V38: 44766 | W38: Edilberto
B39: ='CB-17'!B39 -> Logo Services | C39: =D39 -> 0 | D39: =F39*E39 -> 0 | E39: ='CB-17'!E39 -> 1 | F39: =SUM(G39:R39) -> 0 | T39: 3583 | U39: 300 | V39: 44745 | W39: SEARS
B40: ='CB-17'!B40 -> Temp Services | C40: =D40 -> 0 | D40: =F40*E40 -> 0 | E40: ='CB-17'!E40 -> 1 | F40: =SUM(G40:R40) -> 0 | T40: 9917 | U40: 200 | V40: 44760 | W40: BoA
B41: ='CB-17'!B41 -> Professional Services | C41: =D41 -> 0 | D41: =F41*E41 -> 0 | E41: ='CB-17'!E41 -> 1 | F41: =SUM(H41:R41) -> 0 | T41: 3022 | U41: 570 | V41: 44779 | W41: Edilberto
B42: ='CB-17'!B42 -> Bank Fees | C42: =D42 -> 0 | D42: =F42*E42 -> 0 | E42: ='CB-17'!E42 -> 1 | F42: =SUM(G42:R42) -> 0 | T42: 3023 | U42: 350 | V42: 44779 | W42: Edilberto
B43: ='CB-17'!B43 -> Legal Membership | C43: =D43 -> 0 | D43: =F43*E43 -> 0 | E43: ='CB-17'!E43 -> 1 | F43: =SUM(G43:R43) -> 0 | T43: 3024 | U43: 151 | V43: 44794 | W43: Edilberto
B44: ='CB-17'!B44 -> Business Insurance | C44: =D44 -> 0 | D44: =F44*E44 -> 0 | E44: ='CB-17'!E44 -> 1 | F44: =SUM(G44:R44) -> 0 | T44: 3025 | U44: 180 | V44: 44794 | W44: Edilberto
B45: SUBSCRIPTIONS | C45: =SUM(C46:C58) -> 0 | D45: Prorated | E45: Rate | F45: Annual | G45: =SUM(G46:G58) -> 0 | H45: =SUM(H46:H58) -> 0 | I45: =SUM(I46:I58) -> 0 | J45: =SUM(J46:J58) -> 0 | K45: =SUM(K46:K58) -> 0 | L45: =SUM(L46:L58) -> 0 | M45: =SUM(M46:M58) -> 0 | N45: =SUM(N46:N58) -> 0 | ... R45: =SUM(R46:R58) -> 0 | T45: 3584 | U45: 300 | V45: 44776 | W45: SEARS
B46: ='CB-17'!B46 -> Apple.com | C46: =D46 -> 0 | D46: =F46*E46 -> 0 | E46: ='CB-17'!E46 -> 0.5 | F46: =SUM(G46:R46) -> 0 | T46: 9918 | U46: 200 | V46: 44793 | W46: BoA
B47: ='CB-17'!B47 -> Audible.com | C47: =D47 -> 0 | D47: =F47*E47 -> 0 | E47: ='CB-17'!E47 -> 1 | F47: =SUM(G47:R47) -> 0 | T47: 3045 | U47: 135 | V47: 44814 | W47: Edilberto
B48: ='CB-17'!B48 -> Amazon | C48: =D48 -> 0 | D48: =F48*E48 -> 0 | E48: ='CB-17'!E48 -> 0.5 | F48: =SUM(G48:R48) -> 0 | T48: 3046 | U48: 165 | V48: 44814 | W48: Edilberto
B49: ='CB-17'!B49 -> Cloud Academy | C49: =D49 -> 0 | D49: =F49*E49 -> 0 | E49: ='CB-17'!E49 -> 1 | F49: =SUM(G49:R49) -> 0 | T49: 3583 | U49: 300 | V49: 44808 | W49: SEARS
B50: ='CB-17'!B50 -> Packt | C50: =D50 -> 0 | D50: =F50*E50 -> 0 | E50: ='CB-17'!E50 -> 1 | F50: =SUM(G50:R50) -> 0 | T50: 9919 | U50: 200 | V50: 44822 | W50: BoA
B51: ='CB-17'!B51 -> Pluralsight | C51: =D51 -> 0 | D51: =F51*E51 -> 0 | E51: ='CB-17'!E51 -> 1 | F51: =SUM(G51:R51) -> 0 | T51: 3586 | U51: 300 | V51: 44838 | W51: SEARS
B52: ='CB-17'!B52 -> Linux Academy | C52: =D52 -> 0 | D52: =F52*E52 -> 0 | E52: ='CB-17'!E52 -> 1 | F52: =SUM(G52:R52) -> 0 | T52: 9920 | U52: 200 | V52: 44852 | W52: BoA
B53: ='CB-17'!B53 -> Adobe | C53: =D53 -> 0 | D53: =F53*E53 -> 0 | E53: ='CB-17'!E53 -> 1 | F53: =SUM(G53:R53) -> 0 | T53: 101 | U53: 80 | V53: 44879 | W53: zach devita
B54: ='CB-17'!B54 -> O365 | C54: =D54 -> 0 | D54: =F54*E54 -> 0 | E54: ='CB-17'!E54 -> 1 | F54: =SUM(G54:R54) -> 0 | T54: 1004 | U54: 6000 | V54: 44890 | W54: self
B55: ='CB-17'!B55 -> Microsoft Alumni | C55: =D55 -> 0 | D55: =F55*E55 -> 0 | E55: ='CB-17'!E55 -> 1 | F55: =SUM(G55:R55) -> 0 | T55: 3587 | U55: 238.18 | V55: 44870 | W55: SEARS
B56: ='CB-17'!B56 -> LinkedIn | C56: =D56 -> 0 | D56: =F56*E56 -> 0 | E56: ='CB-17'!E56 -> 1 | F56: =SUM(G56:R56) -> 0 | T56: 9921 | U56: 200 | V56: 44885 | W56: BoA
B57: ='CB-17'!B57 -> DOODLY | C57: =D57 -> 0 | D57: =F57*E57 -> 0 | E57: ='CB-17'!E57 -> 1 | F57: =SUM(G57:R57) -> 0 | T57: 103 | U57: 1230.57 | V57: 44898 | W57: zach devita
B58: ='CB-17'!B58 -> Whizlabs | C58: =D58 -> 0 | D58: =F58*E58 -> 0 | E58: ='CB-17'!E58 -> 1 | F58: =SUM(G58:R58) -> 0 | T58: 3047 | U58: 1449.68 | V58: 44913 | W58: zach devita
B59: ='CB-17'!B59 -> AUTO MILEAGE | C59: =C60 -> 0 | D59: Prorated | E59: Rate | F59: Annual | T59: 9922 | U59: 200 | V59: 44913 | W59: BoA
B60: =B1&" IRS rate:" -> 2022 IRS rate: | C60: =D60 -> 0 | D60: =E60*F60 -> 0 | E60: 0.56 | F60: =SUM(G60:R60) -> 0
B61: ='CB-17'!B61 -> SETUP EXPENSES
B62: ='CB-17'!B62 -> WOODRIDGE OFFICE RENOVATION | C62: ='CB-17'!C62 -> 0 | D62: Prorated | E62: Rate | F62: Annual
B63: ='CB-17'!B63 -> Flooring | C63: =D63 -> 0 | D63: =F63*E63 -> 0 | E63: ='CB-17'!E63 -> 1 | F63: =SUM(G63:R63) -> 0
B64: ='CB-17'!B64 -> Paint | C64: =D64 -> 0 | D64: =F64*E64 -> 0 | E64: ='CB-17'!E64 -> 1 | F64: =SUM(G64:R64) -> 0
B65: ='CB-17'!B65 -> bathroom | C65: =D65 -> 0 | D65: =F65*E65 -> 0 | E65: ='CB-17'!E65 -> 1 | F65: =SUM(G65:R65) -> 0
B66: ='CB-17'!B66 -> electrical work | C66: =D66 -> 0 | D66: =F66*E66 -> 0 | E66: ='CB-17'!E66 -> 1 | F66: =SUM(G66:R66) -> 0
B67: ='CB-17'!B67 -> INDIA OFFICE RENOVATION | C67: =SUM(C68:C70) -> 0 | D67: Prorated | E67: Rate | F67: Annual | G67: =SUM(G68:G70) -> 0 | H67: =SUM(H68:H70) -> 0 | I67: =SUM(I68:I70) -> 0 | J67: =SUM(J68:J70) -> 0 | K67: =SUM(K68:K70) -> 0 | L67: =SUM(L68:L70) -> 0 | M67: =SUM(M68:M70) -> 0 | N67: =SUM(N68:N70) -> 0 | ... R67: =SUM(R68:R70) -> 0
B68: ='CB-17'!B68 -> faucets | C68: =D68 -> 0 | D68: =F68*E68 -> 0 | E68: ='CB-17'!E68 -> 1 | F68: =SUM(G68:R68) -> 0
B69: ='CB-17'!B69 -> furniture | C69: =D69 -> 0 | D69: =F69*E69 -> 0 | E69: ='CB-17'!E69 -> 1 | F69: =SUM(G69:R69) -> 0
B70: ='CB-17'!B70 -> lights | C70: =D70 -> 0 | D70: =F70*E70 -> 0 | E70: ='CB-17'!E70 -> 1 | F70: =SUM(G70:R70) -> 0 | G70: =SUM(G71:G79) -> 0 | H70: =SUM(H71:H79) -> 0 | I70: =SUM(I71:I79) -> 0 | J70: =SUM(J71:J79) -> 0 | K70: =SUM(K71:K79) -> 0 | L70: =SUM(L71:L79) -> 0 | M70: =SUM(M71:M79) -> 0 | N70: =SUM(N71:N79) -> 0 | ... R70: =SUM(R71:R79) -> 0
B71: ='CB-17'!B71 -> INDIA OFFICE EXPENSES | C71: =SUM(C72:C75) -> 0 | D71: Prorated | E71: Rate | F71: Annual | G71: =SUM(G72:G75) -> 0 | H71: =SUM(H72:H75) -> 0 | I71: =SUM(I72:I75) -> 0 | J71: =SUM(J72:J75) -> 0 | K71: =SUM(K72:K75) -> 0 | L71: =SUM(L72:L75) -> 0 | M71: =SUM(M72:M75) -> 0 | N71: =SUM(N72:N75) -> 0 | ... R71: =SUM(R72:R75) -> 0
B72: ='CB-17'!B72 -> electricity | C72: =E72*D72 -> 0 | D72: =E72*F72 -> 0 | E72: 1 | F72: =SUM(G72:R72) -> 0
B73: ='CB-17'!B73 -> taxes | C73: =E73*D73 -> 0 | D73: =E73*F73 -> 0 | E73: 1 | F73: =SUM(G73:R73) -> 0
B74: ='CB-17'!B74 -> cleaning | C74: =E74*D74 -> 0 | D74: =E74*F74 -> 0 | E74: 1 | F74: =SUM(G74:R74) -> 0
B75: ='CB-17'!B75 -> Staff | C75: =E75*D75 -> 0 | D75: =E75*F75 -> 0 | E75: 1 | F75: =SUM(G75:R75) -> 0
B76: ='CB-17'!B76 -> PAYROLL | C76: =SUM(C77:C80) -> 0 | D76: Prorated | E76: Rate | F76: Annual | G76: =SUM(G77:G80) -> 0 | H76: =SUM(H77:H80) -> 0 | I76: =SUM(I77:I80) -> 0 | J76: =SUM(J77:J80) -> 0 | K76: =SUM(K77:K80) -> 0 | L76: =SUM(L77:L80) -> 0 | M76: =SUM(M77:M80) -> 0 | N76: =SUM(N77:N80) -> 0 | ... R76: =SUM(R77:R80) -> 0
C77: =E77*D77 -> 0 | D77: =E77*F77 -> 0 | E77: 1 | F77: =SUM(G77:R77) -> 0
C78: =E78*D78 -> 0 | D78: =E78*F78 -> 0 | E78: 1 | F78: =SUM(G78:R78) -> 0
C79: =E79*D79 -> 0 | D79: =E79*F79 -> 0 | E79: 1 | F79: =SUM(G79:R79) -> 0

Sheet CB-21
A1: =Summary!I5 -> 2021 | B1: =Summary!I5 -> 2021 | G1: ="CLOUDBAUD CONSULTING "& Summary!I5 & " ONLY" -> CLOUDBAUD CONSULTING 2021 ONLY
A2: ='CB-20'!A2 -> Sources | F2: TOTAL | G2: Jan | H2: Feb | I2: Mar | J2: Apr | K2: May | L2: Jun | M2: July | N2: Aug | O2: Sep | P2: Oct | Q2: Nov | R2: Dec
A3: ='CB-20'!A3 -> Various | B3: ='CB-17'!B3 -> CONSULTING REVENUE | C3: =F3 -> 74480 | F3: =SUM(G3:R3) -> 74480 | G3: 0 | H3: 0 | I3: 17600 | J3: 18000 | K3: 19200 | L3: 0 | M3: 0 | N3: 0 | O3: 0 | P3: 0 | Q3: 1320 | R3: 18360
F4: YTD | G4: =G3 -> 0 | H4: =G4+H3 -> 0 | I4: =H4+I3 -> 17600 | J4: =I4+J3 -> 35600 | K4: =J4+K3 -> 54800 | L4: =K4+L3 -> 54800 | M4: =L4+M3 -> 54800 | N4: =M4+N3 -> 54800 | O4: =N4+O3 -> 54800 | ... R4: =Q4+R3 -> 74480
B5: ='CB-17'!B5 -> TOTAL EXPENSES | C5: =C7+C20+C27+C76+C35+C59+C45+C62+C67+C71 -> 7194.995
B6: ='CB-17'!B6 -> NET REVENUE | C6: =C3-C5 -> 67285.005
B7: ='CB-17'!B7 -> UTILITIES | C7: =SUM(C8:C21) -> 3142.1283 | D7: Prorated | E7: Rate | F7: Annual | G7: =SUM(G8:G19) -> 816.92 | H7: =SUM(H8:H19) -> 913.95 | I7: =SUM(I8:I19) -> 841.71 | J7: =SUM(J8:J19) -> 993.07 | K7: =SUM(K8:K19) -> 400.57 | L7: =SUM(L8:L19) -> 891.77 | M7: =SUM(M8:M19) -> 1208.51 | N7: =SUM(N8:N19) -> 1203.18 | ... R7: =SUM(R8:R19) -> 1145.55
B8: ='CB-17'!B8 -> Electricity | C8: =D8 -> 650.8076 | D8: =E8*F8 -> 650.8076 | E8: ='CB-17'!E8 -> 0.17 | F8: =SUM(G8:R8) -> 3828.28 | G8: 525.55 | H8: 310.79 | I8: 631.72 | J8: 254.37 | K8: 190.58 | L8: 169.63 | M8: 142.85 | N8: 308.34 | O8: 146.34 | P8: 142.14 | Q8: 375.45 | R8: 630.52
B9: ='CB-17'!B9 -> Waste & Recycle | C9: =D9 -> 55.4812 | D9: =E9*F9 -> 55.4812 | E9: ='CB-17'!E9 -> 0.17 | F9: =SUM(G9:R9) -> 326.36 | G9: 81.38 | J9: 81.66 | M9: 81.66 | R9: 81.66
B10: ='CB-17'!B10 -> Water & Sewer | C10: =D10 -> 434.1154 | D10: =E10*F10 -> 434.1154 | E10: ='CB-17'!E10 -> 0.17 | F10: =SUM(G10:R10) -> 2553.62 | H10: 393.17 | J10: 447.05 | L10: 421.14 | N10: 436.48 | P10: 855.78
B11: ='CB-17'!B11 -> Security | C11: =D11 -> 130.4291 | D11: =E11*F11 -> 130.4291 | E11: ='CB-17'!E11 -> 0.17 | F11: =SUM(G11:R11) -> 767.23 | M11: =464.52+60.55 -> 525.07 | Q11: 242.16
B12: ='CB-17'!B12 -> Landscaping | C12: =D12 -> 285.6 | D12: =E12*F12 -> 285.6 | E12: ='CB-17'!E12 -> 0.17 | F12: =SUM(G12:R12) -> 1680 | G12: 140 | H12: 140 | I12: 140 | J12: 140 | K12: 140 | L12: 140 | M12: 140 | N12: 140 | O12: 140 | P12: 140 | Q12: 140 | R12: 140
B13: ='CB-17'!B13 -> Home Owners Insurance | C13: =D13 -> 283.39 | D13: =E13*F13 -> 283.39 | E13: ='CB-17'!E13 -> 0.17 | F13: ='Home Insurance'!H13 -> 1667
B14: ='CB-17'!B14 -> Appliance Maintenance | C14: =D14 -> 279.96 | D14: =E14*F14 -> 279.96 | E14: ='CB-17'!E14 -> 0.5 | F14: =SUM(G14:R14) -> 559.92 | G14: 69.99 | H14: 69.99 | I14: 69.99 | J14: 69.99 | K14: 69.99 | L14: 0 | M14: 69.99 | N14: 69.99 | O14: 69.99 | P14: 0 | Q14: 0 | R14: 0
B15: ='CB-17'!B15 -> Apple Warranty | C15: =D15 -> 0 | D15: =E15*F15 -> 0 | E15: ='CB-17'!E15 -> 0.5 | F15: =SUM(G15:R15) -> 0
B16: ='CB-17'!B16 -> Computers Warranty | C16: =D16 -> 0 | D16: =E16*F16 -> 0 | E16: ='CB-17'!E16 -> 0.5 | F16: =SUM(G16:R16) -> 0
B17: ='CB-17'!B17 -> Cellular Service | C17: =D17 -> 393 | D17: =E17*F17 -> 393 | E17: ='CB-17'!E17 -> 0.5 | F17: =SUM(G17:R17) -> 786 | L17: 161 | M17: 145 | N17: 145 | P17: 145 | R17: 190
B18: ='CB-17'!B18 -> Broadband | C18: =D18 -> 340.395 | D18: =E18*F18 -> 340.395 | E18: ='CB-17'!E18 -> 0.5 | F18: =SUM(G18:R18) -> 680.79 | M18: 103.94 | N18: 103.37 | O18: 163.37 | P18: 113.37 | Q18: 93.37 | R18: 103.37
B19: ='CB-17'!B19 -> TV Cable | C19: =D19 -> 0 | D19: =E19*F19 -> 0 | E19: ='CB-17'!E19 -> 0.5 | F19: =SUM(G19:R19) -> 0
B20: ='CB-17'!B20 -> DEPRECIABLE ASSETS | C20: =SUM(C21:C26) -> 288.95 | G20: =SUM(G21:G26) -> 19.8 | H20: =SUM(H21:H26) -> 0 | I20: =SUM(I21:I26) -> 27.12 | J20: =SUM(J21:J26) -> 72.3 | K20: =SUM(K21:K26) -> 0 | L20: =SUM(L21:L26) -> 0 | M20: =SUM(M21:M26) -> 38.48 | N20: =SUM(N21:N26) -> 0 | ... R20: =SUM(R21:R26) -> 23.16
B21: ='CB-17'!B21 -> ASUS Laptop | C21: =D21 -> 0 | D21: =E21*F21 -> 0 | E21: ='CB-17'!E21 -> 0.5 | F21: =SUM(G21:R21) -> 0
B22: ='CB-17'!B22 -> Mobile Device (samsung) | C22: =D22 -> 94.5 | D22: =E22*F22 -> 94.5 | E22: ='CB-17'!E22 -> 0.5 | F22: =SUM(G22:R22) -> 189 | Q22: =148.6+40.4 -> 189
B23: ='CB-17'!B23 -> Cellphone Device | C23: =D23 -> 0 | D23: =E23*F23 -> 0 | E23: ='CB-17'!E23 -> 0.5
B24: ='CB-17'!B24 -> Supplies | C24: =D24 -> 100.64 | D24: =E24*F24 -> 100.64 | E24: ='CB-17'!E24 -> 1 | F24: =SUM(G24:R24) -> 100.64 | I24: 27.12 | M24: 38.48 | P24: 11.88 | R24: 23.16
B25: ='CB-17'!B25 -> Stationaries | C25: =D25 -> 21.51 | D25: =E25*F25 -> 21.51 | E25: ='CB-17'!E25 -> 1 | F25: =SUM(G25:R25) -> 21.51 | G25: 19.8 | O25: 0.78 | P25: 0.93
B26: ='CB-17'!B26 -> Books | C26: =D26 -> 72.3 | D26: =E26*F26 -> 72.3 | E26: ='CB-17'!E26 -> 1 | F26: =SUM(G26:R26) -> 72.3 | J26: 72.3
B27: ='CB-17'!B27 -> GOVERNMENT FEES | C27: =SUM(C28:C34) -> 242.13 | D27: Prorated | E27: Rate | F27: Annual
B28: ='CB-17'!B28 -> Biz Registration | C28: =D28 -> 0 | D28: =E28*F28 -> 0 | E28: ='CB-17'!E28 -> 1 | F28: =SUM(G28:R28) -> 0
B29: ='CB-18'!B29 -> Licensing | C29: =D29 -> 0 | D29: =E29*F29 -> 0 | E29: ='CB-17'!E29 -> 1 | F29: =SUM(G29:R29) -> 0
B30: ='CB-17'!B30 -> WA DOR Excise Tax | C30: =D30 -> 104 | D30: =E30*F30 -> 104 | E30: ='CB-17'!E30 -> 1 | F30: =SUM(G30:R30) -> 104 | K30: 104
B31: ='CB-17'!B31 -> Garnishment Fee | C31: =D31 -> 0 | D31: =E31*F31 -> 0 | E31: ='CB-17'!E31 -> 1 | F31: =SUM(G31:R31) -> 0
B32: ='CB-17'!B32 -> LNI Insurance | C32: =D32 -> 138.13 | D32: =E32*F32 -> 138.13 | E32: ='CB-17'!E32 -> 1 | F32: =SUM(G32:R32) -> 138.13 | J32: =33.64+84.46 -> 118.1 | K32: 10.03 | P32: 10
B33: ='CB-17'!B33 -> WA Employment Security | C33: =D33 -> 0 | D33: =E33*F33 -> 0 | E33: ='CB-17'!E33 -> 1
B34: ='CB-17'!B34 -> Commercial Insurance | C34: =D34 -> 0 | D34: =E34*F34 -> 0 | E34: ='CB-17'!E34 -> 1
B35: ='CB-17'!B35 -> PROFESSIONAL SERVICES | C35: =SUM(C36:C44) -> 3521.7867
A36: Google | B36: ='CB-17'!B36 -> Web Domains | C36: =D36 -> 237.44 | D36: =E36*F36 -> 237.44 | E36: ='CB-17'!E36 -> 1 | F36: =SUM(G36:R36) -> 237.44 | G36: =33.03+33.03+22.02 -> 88.08 | H36: =13.21+56.88 -> 70.09 | I36: 13.21 | J36: 26.42 | P36: 39.64
A37: godaddy | B37: ='CB-17'!B37 -> Web Hosting | C37: =D37 -> 123.1 | D37: =E37*F37 -> 123.1 | E37: ='CB-17'!E37 -> 1 | F37: =SUM(G37:R37) -> 123.1 | G37: 20.01 | M37: 14.93 | P37: 88.16
A38: google/fb | B38: Digital Ads | C38: =D38 -> 0 | D38: =E38*F38 -> 0 | E38: ='CB-17'!E38 -> 1 | F38: =SUM(G38:R38) -> 0
A39: logo | B39: Logo Services | C39: =D39 -> 0 | D39: =E39*F39 -> 0 | E39: ='CB-17'!E39 -> 1 | F39: =SUM(G39:R39) -> 0
A40: misc. | B40: Temp Services | C40: =D40 -> 2426.6667 | D40: =E40*F40 -> 2426.6667 | E40: ='CB-17'!E40 -> 1 | F40: =(52/3)*140 -> 2426.6667
B41: Professional Services | C41: =D41 -> 52.93 | D41: =E41*F41 -> 52.93 | E41: ='CB-17'!E41 -> 1 | F41: =SUM(G41:R41) -> 52.93 | R41: 52.93
B42: Bank Fees | C42: =D42 -> 103.65 | D42: =E42*F42 -> 103.65 | E42: ='CB-17'!E42 -> 1 | F42: =SUM(G42:R42) -> 103.65 | G42: 3.75 | J42: =8.4+51 -> 59.4 | M42: 7 | N42: 7 | O42: 7 | P42: 7 | Q42: 7 | R42: 5.5
B43: Legal Membership | C43: =D43 -> 468 | D43: =E43*F43 -> 468 | E43: ='CB-17'!E43 -> 1 | F43: =SUM(G43:R43) -> 468 | H43: 39 | I43: =39+39 -> 78 | J43: 39 | L43: =39+39 -> 78 | M43: 39 | N43: 39 | O43: 39 | Q43: =39+39 -> 78 | R43: 39
B44: Business Insurance | C44: =D44 -> 110 | D44: =E44*F44 -> 110 | E44: ='CB-17'!E44 -> 1 | F44: =SUM(G44:R44) -> 110 | P44: 55 | Q44: 27.5 | R44: 27.5
B45: ='CB-17'!B45 -> SUBSCRIPTIONS
B46: Apple.com | D46: =E46*F46 -> 72.085 | E46: ='CB-17'!E46 -> 0.5 | F46: =SUM(G46:R46) -> 144.17 | L46: 8.8 | M46: =9.9+18.7 -> 28.6 | N46: 18.7 | O46: 0 | P46: 0 | Q46: 0 | R46: 88.07
B47: Audible.com | D47: =E47*F47 -> 197.52 | E47: ='CB-17'!E47 -> 1 | F47: =SUM(G47:R47) -> 197.52 | G47: 16.46 | H47: 16.46 | I47: 16.46 | J47: 16.46 | K47: 16.46 | L47: 16.46 | M47: 16.46 | N47: 16.46 | O47: 16.46 | P47: 16.46 | Q47: 16.46 | R47: 16.46
B48: Amazon | D48: =E48*F48 -> 26.34 | E48: ='CB-17'!E48 -> 0.5 | F48: =SUM(G48:R48) -> 52.68 | G48: 4.39 | H48: 4.39 | I48: 4.39 | J48: 4.39 | K48: 4.39 | L48: 4.39 | M48: 4.39 | N48: 4.39 | O48: 4.39 | P48: 4.39 | Q48: 4.39 | R48: 4.39
B49: Cloud Academy | D49: =E49*F49 -> 499 | E49: ='CB-17'!E49 -> 1 | F49: =SUM(G49:R49) -> 499 | N49: 499
B50: Packt | D50: =E50*F50 -> 0 | E50: ='CB-17'!E50 -> 1 | F50: =SUM(G50:R50) -> 0
B51: Pluralsight | D51: =E51*F51 -> 95.79 | E51: ='CB-17'!E51 -> 1 | F51: =SUM(G51:R51) -> 95.79 | M51: 31.93 | N51: 31.93 | O51: 31.93
B52: Linux Academy | D52: =E52*F52 -> 0 | E52: ='CB-17'!E52 -> 1 | F52: =SUM(G52:R52) -> 0
B53: Adobe | D53: =E53*F53 -> 0 | E53: ='CB-17'!E53 -> 1 | F53: =SUM(G53:R53) -> 0
B54: O365 | D54: =E54*F54 -> 176.36 | E54: ='CB-17'!E54 -> 1 | F54: =SUM(G54:R54) -> 176.36 | G54: 5.51 | H54: 0 | I54: 0 | J54: 0 | K54: 0 | L54: 44.04 | M54: =5.69+44.04 -> 49.73 | N54: =11.01+44.04 -> 55.05 | O54: 11.01 | P54: 0 | Q54: 5.51 | R54: 5.51
B55: Microsoft Alumni | D55: =E55*F55 -> 0 | E55: ='CB-17'!E55 -> 1 | F55: =SUM(G55:R55) -> 0
B56: LinkedIn | D56: =E56*F56 -> 280.78 | E56: ='CB-17'!E56 -> 1 | F56: =SUM(G56:R56) -> 280.78 | G56: 16.52 | I56: =16.52+16.52 -> 33.04 | J56: =16.52+16.52 -> 33.04 | K56: 33.04 | L56: =16.52+16.52 -> 33.04 | M56: 66.05 | N56: 66.05
B57: DOODLY | D57: =E57*F57 -> 358 | E57: ='CB-17'!E57 -> 1 | F57: =SUM(G57:R57) -> 358 | K57: =67+97+97+97 -> 358
B58: Flooring | D58: =E58*F58 -> 0 | E58: ='CB-17'!E58 -> 1
B59: Paint | D59: =E59*F59 -> #VALUE! | E59: ='CB-17'!E59 -> Rate
B60: bathroom | D60: =E60*F60 -> 0 | E60: ='CB-17'!E60 -> 0.56
B61: Whizlabs | D61: =E61*F61 -> 0 | E61: ='CB-17'!E61 -> 0 | F61: =SUM(G61:R61) -> 99 | M61: 99
B62: AUTO MILEAGE | D62: Prorated | E62: Rate | F62: Annual
B63: 2021 IRS rate | D63: =E63*F63 -> 0 | E63: 0.56 | F63: =SUM(G63:R63) -> 0
B64: ='CB-17'!B61 -> SETUP EXPENSES | C64: ='CB-17'!C61 -> 0 | D64: ='CB-17'!D61 -> 0 | E64: ='CB-17'!E61 -> 0 | F64: ='CB-17'!F61 -> 0 | G64: ='CB-17'!G61 -> 0 | H64: ='CB-17'!H61 -> 0 | I64: ='CB-17'!I61 -> 0 | ... R64: ='CB-17'!R61 -> 0
B65: ='CB-17'!B62 -> WOODRIDGE OFFICE RENOVATION
B66: ='CB-17'!B63 -> Flooring | D66: =E66*F66 -> 0 | E66: ='CB-17'!E63 -> 1 | F66: =SUM(G66:R66) -> 0
B67: ='CB-17'!B64 -> Paint | D67: =E67*F67 -> 0 | E67: ='CB-17'!E64 -> 1 | F67: =SUM(G67:R67) -> 0
B68: ='CB-17'!B65 -> bathroom | D68: =E68*F68 -> 135.21 | E68: ='CB-17'!E65 -> 1 | F68: =SUM(G68:R68) -> 135.21 | M68: 79.03 | Q68: 20.89 | R68: 35.29
B69: ='CB-17'!B66 -> electrical work | D69: =E69*F69 -> 0 | E69: ='CB-17'!E66 -> 1 | F69: =SUM(G69:R69) -> 0
B70: ='CB-17'!B67 -> INDIA OFFICE RENOVATION
B71: ='CB-17'!B68 -> faucets | D71: =E71*F71 -> 0 | E71: ='CB-17'!E68 -> 1 | F71: =SUM(G71:R71) -> 0
B72: ='CB-17'!B69 -> furniture | D72: =E72*F72 -> 0 | E72: ='CB-17'!E69 -> 1 | F72: =SUM(G72:R72) -> 0
B73: ='CB-17'!B70 -> lights | D73: =E73*F73 -> 0 | E73: ='CB-17'!E70 -> 1 | F73: =SUM(G73:R73) -> 0
B74: ='CB-17'!B71 -> INDIA OFFICE EXPENSES
B75: ='CB-17'!B72 -> electricity | D75: =E75*F75 -> 0 | E75: ='CB-17'!E72 -> 1 | F75: =SUM(G75:R75) -> 0
B76: ='CB-17'!B73 -> taxes | D76: =E76*F76 -> 0 | E76: ='CB-17'!E73 -> 1 | F76: =SUM(G76:R76) -> 0
B77: ='CB-17'!B74 -> cleaning | D77: =E77*F77 -> 0 | E77: ='CB-17'!E74 -> 1 | F77: =SUM(G77:R77) -> 0
B78: ='CB-17'!B75 -> Staff | D78: =E78*F78 -> 0 | E78: ='CB-17'!E75 -> 1 | F78: =SUM(G78:R78) -> 0
B79: ='CB-17'!B76 -> PAYROLL

Sheet CB-20
A1: =Summary!J5 -> 2020 | B1: =Summary!J5 -> 2020 | G1: ="CLOUDBAUD CONSULTING "& Summary!J5 & " ONLY" -> CLOUDBAUD CONSULTING 2020 ONLY
A2: Sources | F2: TOTAL | G2: Jan | H2: Feb | I2: Mar | J2: Apr | K2: May | L2: Jun | M2: July | N2: Aug | O2: Sep | P2: Oct | Q2: Nov | R2: Dec
A3: Various | B3: ='CB-17'!B3 -> CONSULTING REVENUE | C3: =F3 -> 0 | F3: =SUM(G3:R3) -> 0 | G3: 0
F4: YTD | G4: =G3 -> 0 | H4: =G4+H3 -> 0 | I4: =H4+I3 -> 0 | J4: =I4+J3 -> 0 | K4: =J4+K3 -> 0 | L4: =K4+L3 -> 0 | M4: =L4+M3 -> 0 | N4: =M4+N3 -> 0 | O4: =N4+O3 -> 0 | ... R4: =Q4+R3 -> 0
B5: ='CB-17'!B5 -> TOTAL EXPENSES | C5: =C7+C20+C27+C76+C35+C59+C45+C62+C67+C71 -> 1569.8499 | F5: =SUM(G5:R5) -> 0
B6: ='CB-17'!B6 -> NET REVENUE | C6: =C3-C5 -> -1569.8499
B7: ='CB-17'!B7 -> UTILITIES | C7: =SUM(C8:C19) -> 809.1099 | D7: Prorated | E7: Rate | F7: Annual | G7: =SUM(H8:H14) -> 429.71 | H7: =SUM(I8:I14) -> 80.67 | I7: =SUM(J8:J14) -> 450.14 | J7: =SUM(K8:K32) -> 385.76 | K7: =SUM(L8:L14) -> 18.16 | L7: =SUM(M8:M14) -> 63.51 | M7: =SUM(N8:N14) -> 393.17 | N7: =SUM(O8:O14) -> 80.86 | O7: =SUM(P8:P14) -> 546.34 | P7: =SUM(Q8:Q14) -> 543.77 | Q7: =SUM(R8:R14) -> 81.38 | R7: =SUM(S8:S14) -> 0 | T7: 3048 | U7: 320.03 | V7: 45066
A8: PSE | B8: ='CB-17'!B8 -> Electricity | C8: =D8 -> 48.8206 | D8: =E8*F8 -> 48.8206 | E8: ='CB-17'!E8 -> 0.17 | F8: =SUM(G8:R8) -> 287.18 | P8: 123.52 | Q8: 163.66
A9: City | B9: ='CB-17'!B9 -> Waste & Recycle | C9: =D9 -> 55.1786 | D9: =E9*F9 -> 55.1786 | E9: ='CB-17'!E9 -> 0.17 | F9: =SUM(G9:R9) -> 324.58 | I9: 80.67 | L9: 18.16 | M9: 63.51 | O9: 80.86 | R9: 81.38
A10: City | B10: ='CB-17'!B10 -> Water & Sewer | C10: =D10 -> 418.4907 | D10: =E10*F10 -> 418.4907 | E10: ='CB-17'!E10 -> 0.17 | F10: =SUM(G10:R10) -> 2461.71 | H10: 429.71 | J10: 450.14 | K10: 385.76 | N10: 393.17 | P10: 422.82 | Q10: 380.11
A11: ADT | B11: ='CB-17'!B11 -> Security | C11: =D11 -> 0 | D11: =E11*F11 -> 0 | E11: ='CB-17'!E11 -> 0.17 | F11: =SUM(G11:R11) -> 0
A12: Personal | B12: ='CB-17'!B12 -> Landscaping | C12: =D12 -> 0 | D12: =E12*F12 -> 0 | E12: ='CB-17'!E12 -> 0.17 | F12: =SUM(G12:R12) -> 0
B13: ='CB-17'!B13 -> Home Owners Insurance | C13: =D13 -> 286.62 | D13: =E13*F13 -> 286.62 | E13: ='CB-17'!E13 -> 0.17 | F13: ='Home Insurance'!I13 -> 1686
A14: ='CB-17'!A14 -> CCMSEARS | B14: ='CB-17'!B14 -> Appliance Maintenance | C14: =D14 -> 0 | D14: =E14*F14 -> 0 | E14: ='CB-17'!E14 -> 0.5 | F14: ='Home Insurance'!I14 -> 0
B15: ='CB-17'!B15 -> Apple Warranty | C15: =D15 -> 0 | D15: =E15*F15 -> 0 | E15: ='CB-17'!E15 -> 0.5 | F15: ='Home Insurance'!I15 -> 0
B16: ='CB-17'!B16 -> Computers Warranty | C16: =D16 -> 0 | D16: =E16*F16 -> 0 | E16: ='CB-17'!E16 -> 0.5 | F16: ='Home Insurance'!I16 -> 0
A17: T-Mobile | B17: ='CB-17'!B17 -> Cellular Service | C17: =D17 -> 0 | D17: =E17*F17 -> 0 | E17: ='CB-17'!E17 -> 0.5 | F17: ='Home Insurance'!I17 -> 0
A18: Comcast | B18: ='CB-17'!B18 -> Broadband | C18: =D18 -> 0 | D18: =E18*F18 -> 0 | E18: ='CB-17'!E18 -> 0.5 | F18: ='Home Insurance'!I18 -> 0
B19: ='CB-17'!B19 -> TV Cable | C19: =D19 -> 0 | D19: =E19*F19 -> 0 | E19: ='CB-17'!E19 -> 0.5 | F19: ='Home Insurance'!I19 -> 0
B20: ='CB-17'!B20 -> DEPRECIABLE ASSETS | C20: =SUM(C21:C26) -> 0 | D20: Prorated | E20: Rate | F20: Annual | G20: =SUM(G21:G26) -> 0 | H20: =SUM(H21:H26) -> 0 | I20: =SUM(I21:I26) -> 0 | J20: =SUM(J21:J26) -> 0 | K20: =SUM(K21:K26) -> 0 | L20: =SUM(L21:L26) -> 0 | M20: =SUM(M21:M26) -> 0 | N20: =SUM(N21:N26) -> 0 | ... R20: =SUM(R21:R26) -> 0
B21: ='CB-17'!B21 -> ASUS Laptop | C21: =D21 -> 0 | D21: =E21*F21 -> 0 | E21: ='CB-17'!E21 -> 0.5 | F21: =SUM(G21:R21) -> 0
B22: ='CB-17'!B22 -> Mobile Device (samsung) | C22: =D22 -> 0 | D22: =E22*F22 -> 0 | E22: ='CB-17'!E22 -> 0.5 | F22: =SUM(G22:R22) -> 0
B23: ='CB-17'!B23 -> Cellphone Device | C23: =D23 -> 0 | D23: =E23*F23 -> 0 | E23: ='CB-17'!E23 -> 0.5 | F23: =SUM(G23:R23) -> 0
B24: ='CB-17'!B24 -> Supplies | C24: =D24 -> 0 | D24: =E24*F24 -> 0 | E24: ='CB-17'!E24 -> 1 | F24: =SUM(G24:R24) -> 0
B25: ='CB-17'!B25 -> Stationaries | C25: =D25 -> 0 | D25: =E25*F25 -> 0 | E25: ='CB-17'!E25 -> 1 | F25: =SUM(G25:R25) -> 0
B26: ='CB-17'!B26 -> Books | C26: =D26 -> 0 | D26: =E26*F26 -> 0 | E26: ='CB-17'!E26 -> 1 | F26: =SUM(G26:R26) -> 0
B27: ='CB-17'!B27 -> GOVERNMENT FEES | C27: =SUM(C28:C34) -> 197.22 | D27: Prorated | E27: Rate | F27: Annual
A28: Olympia + KC + City | B28: ='CB-17'!B28 -> Biz Registration | C28: =D28 -> 0 | D28: =E28*F28 -> 0 | E28: ='CB-17'!E28 -> 1 | F28: =SUM(G28:R28) -> 0
B29: ='CB-17'!B29 -> Licensing | C29: =D29 -> 157.22 | D29: =E29*F29 -> 157.22 | E29: ='CB-17'!E29 -> 1 | F29: =SUM(G29:R29) -> 157.22 | G29: 157.22
B30: ='CB-17'!B30 -> WA DOR Excise Tax | C30: =D30 -> 0 | D30: =E30*F30 -> 0 | E30: ='CB-17'!E30 -> 1 | F30: =SUM(G30:R30) -> 0
B31: ='CB-17'!B31 -> Garnishment Fee | C31: =D31 -> 0 | D31: =E31*F31 -> 0 | E31: ='CB-17'!E31 -> 1 | F31: =SUM(G31:R31) -> 0
B32: ='CB-17'!B32 -> LNI Insurance | C32: =D32 -> 40 | D32: =E32*F32 -> 40 | E32: ='CB-17'!E32 -> 1 | F32: =SUM(G32:R32) -> 40 | I32: 40
B33: ='CB-17'!B33 -> WA Employment Security | C33: =D33 -> 0 | D33: =E33*F33 -> 0 | E33: ='CB-17'!E33 -> 1 | F33: =SUM(G33:R33) -> 0
B34: ='CB-17'!B34 -> Commercial Insurance | C34: =D34 -> 0 | D34: =E34*F34 -> 0 | E34: ='CB-17'!E34 -> 1 | F34: =SUM(G34:R34) -> 0
B35: PROFESSIONAL SERVICES | C35: =SUM(C36:C44) -> 277 | D35: Prorated | E35: Rate | F35: Annual
B36: ='CB-17'!B36 -> Web Domains | C36: =D36 -> 0 | D36: =E36*F36 -> 0 | E36: ='CB-17'!E36 -> 1 | F36: =SUM(G36:R36) -> 0
B37: ='CB-17'!B37 -> Web Hosting | C37: =D37 -> 0 | D37: =E37*F37 -> 0 | E37: ='CB-17'!E37 -> 1 | F37: =SUM(G37:R37) -> 0
B38: ='CB-17'!B38 -> Digital Ads | C38: =D38 -> 0 | D38: =E38*F38 -> 0 | E38: ='CB-17'!E38 -> 1 | F38: =SUM(G38:R38) -> 0
B39: ='CB-17'!B39 -> Logo Services | C39: =D39 -> 0 | D39: =E39*F39 -> 0 | E39: ='CB-17'!E39 -> 1 | F39: =SUM(G39:R39) -> 0
B40: ='CB-17'!B40 -> Temp Services | C40: =D40 -> 0 | D40: =E40*F40 -> 0 | E40: ='CB-17'!E40 -> 1 | F40: =SUM(G40:R40) -> 0
B41: ='CB-17'!B41 -> Professional Services | C41: =D41 -> 0 | D41: =E41*F41 -> 0 | E41: ='CB-17'!E41 -> 1 | F41: =SUM(G41:R41) -> 0
B42: ='CB-17'!B42 -> Bank Fees | C42: =D42 -> 160 | D42: =E42*F42 -> 160 | E42: ='CB-17'!E42 -> 1 | F42: =SUM(G42:R42) -> 160 | G42: =35+125 -> 160
B43: ='CB-17'!B43 -> Legal Membership | C43: =D43 -> 117 | D43: =E43*F43 -> 117 | E43: ='CB-17'!E43 -> 1 | F43: =SUM(G43:R43) -> 117 | G43: =39+39 -> 78 | I43: 39
B44: ='CB-17'!B44 -> Business Insurance | C44: =D44 -> 0 | D44: =E44*F44 -> 0 | E44: ='CB-17'!E44 -> 1 | F44: =SUM(G44:R44) -> 0
B45: SUBSCRIPTIONS | C45: =SUM(C46:C58) -> 286.52 | D45: Prorated | E45: Rate | F45: Annual
B46: ='CB-17'!B46 -> Apple.com | C46: =D46 -> 0 | D46: =E46*F46 -> 0 | E46: ='CB-17'!E46 -> 0.5 | F46: =SUM(G46:R46) -> 0
B47: ='CB-17'!B47 -> Audible.com | C47: =D47 -> 0 | D47: =E47*F47 -> 0 | E47: ='CB-17'!E47 -> 1 | F47: =SUM(G47:R47) -> 0
B48: ='CB-17'!B48 -> Amazon | C48: =D48 -> 0 | D48: =E48*F48 -> 0 | E48: ='CB-17'!E48 -> 0.5 | F48: =SUM(G48:R48) -> 0
B49: ='CB-17'!B49 -> Cloud Academy | C49: =D49 -> 179 | D49: =E49*F49 -> 179 | E49: ='CB-17'!E49 -> 1 | F49: =SUM(G49:R49) -> 179 | G49: 179
B50: ='CB-17'!B50 -> Packt | C50: =D50 -> 0 | D50: =E50*F50 -> 0 | E50: ='CB-17'!E50 -> 1 | F50: =SUM(G50:R50) -> 0
B51: ='CB-17'!B51 -> Pluralsight | C51: =D51 -> 0 | D51: =E51*F51 -> 0 | E51: ='CB-17'!E51 -> 1 | F51: =SUM(G51:R51) -> 0
B52: ='CB-17'!B52 -> Linux Academy | C52: =D52 -> 0 | D52: =E52*F52 -> 0 | E52: ='CB-17'!E52 -> 1 | F52: =SUM(G52:R52) -> 0
B53: ='CB-17'!B53 -> Adobe | C53: =D53 -> 0 | D53: =E53*F53 -> 0 | E53: ='CB-17'!E53 -> 1 | F53: =SUM(G53:R53) -> 0
B54: ='CB-17'!B54 -> O365 | C54: =D54 -> 8.52 | D54: =E54*F54 -> 8.52 | E54: ='CB-17'!E54 -> 1 | F54: =SUM(G54:R54) -> 8.52 | G54: 3.01 | H54: 5.51
B55: ='CB-17'!B55 -> Microsoft Alumni | C55: =D55 -> 0 | D55: =E55*F55 -> 0 | E55: ='CB-17'!E55 -> 1 | F55: =SUM(G55:R55) -> 0
B56: ='CB-17'!B56 -> LinkedIn | C56: =D56 -> 0 | D56: =E56*F56 -> 0 | E56: ='CB-17'!E56 -> 1 | F56: =SUM(G56:R56) -> 0
B57: ='CB-17'!B57 -> DOODLY | C57: =D57 -> 0 | D57: =E57*F57 -> 0 | E57: ='CB-17'!E57 -> 1 | F57: =SUM(G57:R57) -> 0
B58: ='CB-17'!B58 -> Whizlabs | C58: =D58 -> 99 | D58: =E58*F58 -> 99 | E58: ='CB-17'!E58 -> 1 | F58: =SUM(G58:R58) -> 99 | M58: 99
B59: AUTO MILEAGE | D59: Prorated | E59: Rate | F59: Annual
B60: 2020 IRS rate | C60: =D60 -> 0 | D60: =E60*F60 -> 0 | E60: 0.545 | F60: =SUM(G60:R60) -> 0
B61: ='CB-17'!B61 -> SETUP EXPENSES
B62: ='CB-17'!B62 -> WOODRIDGE OFFICE RENOVATION | D62: Prorated | E62: Rate | F62: Annual
B63: ='CB-17'!B63 -> Flooring | C63: =D63 -> 0 | D63: =E63*F63 -> 0 | E63: 1 | F63: =SUM(G63:R63) -> 0
B64: ='CB-17'!B64 -> Paint | C64: =D64 -> 0 | D64: =E64*F64 -> 0 | E64: 1 | F64: =SUM(G64:R64) -> 0
B65: ='CB-17'!B65 -> bathroom | C65: =D65 -> 0 | D65: =E65*F65 -> 0 | E65: 1 | F65: =SUM(G65:R65) -> 0
B66: ='CB-17'!B66 -> electrical work | C66: =D66 -> 0 | D66: =E66*F66 -> 0 | E66: 1 | F66: =SUM(G66:R66) -> 0
B67: ='CB-17'!B67 -> INDIA OFFICE RENOVATION | D67: Prorated | E67: Rate | F67: Annual
B68: ='CB-17'!B68 -> faucets | C68: =D68 -> 0 | D68: =E68*F68 -> 0 | E68: 1 | F68: =SUM(G68:R68) -> 0
B69: ='CB-17'!B69 -> furniture | C69: =D69 -> 0 | D69: =E69*F69 -> 0 | E69: 1 | F69: =SUM(G69:R69) -> 0
B70: ='CB-17'!B70 -> lights | C70: =D70 -> 0 | D70: =E70*F70 -> 0 | E70: 1 | F70: =SUM(G70:R70) -> 0
B71: ='CB-17'!B71 -> INDIA OFFICE EXPENSES | C71: =SUM(C72:C74) -> 0 | D71: Prorated | E71: Rate | F71: Annual
B72: ='CB-17'!B72 -> electricity | C72: =D72 -> 0 | D72: =E72*F72 -> 0 | E72: 1 | F72: =SUM(G72:R72) -> 0
B73: ='CB-17'!B73 -> taxes | C73: =D73 -> 0 | D73: =E73*F73 -> 0 | E73: 1 | F73: =SUM(G73:R73) -> 0
B74: ='CB-17'!B74 -> cleaning | C74: =D74 -> 0 | D74: =E74*F74 -> 0 | E74: 1 | F74: =SUM(G74:R74) -> 0
B75: ='CB-17'!B75 -> Staff | C75: =D75 -> 0 | D75: =E75*F75 -> 0 | E75: 1 | F75: =SUM(G75:R75) -> 0
B76: PAYROLL | C76: =SUM(C77:C80) -> 0 | D76: Prorated | E76: Rate | F76: Annual
F77: =SUM(G77:R77) -> 0
F78: =SUM(G78:R78) -> 0
F79: =SUM(G79:R79) -> 0
F80: =SUM(G80:R80) -> 0

Sheet CB-19
B1: =Summary!K5 -> 2019 | C1: =Summary!K5 -> 2019 | H1: ="CLOUDBAUD CONSULTING "& Summary!K5 & " ONLY" -> CLOUDBAUD CONSULTING 2019 ONLY
B2: Sources | G2: TOTAL | H2: Jan | I2: Feb | J2: Mar | K2: Apr | L2: May | M2: Jun | N2: Jul | O2: Aug | P2: Sep | Q2: Oct | R2: Nov | S2: Dec | U2: Check# | V2: Amount | W2: Date | X2: Payee
B3: Various | C3: ='CB-17'!B3 -> CONSULTING REVENUE | D3: =G3 -> 130000 | G3: =SUM(H3:S3) -> 130000 | H3: =10000+10000 -> 20000 | I3: =10000+10000 -> 20000 | J3: =10000+10000 -> 20000 | K3: =10000+10000 -> 20000 | L3: =10000+10000 -> 20000 | M3: =10000+10000 -> 20000 | N3: 0 | O3: 10000 | P3: 0 | Q3: 0 | R3: 0 | S3: 0 | U3: 9923 | V3: 200 | W3: 44944
G4: YTD | H4: =H3 -> 20000 | I4: =H4+I3 -> 40000 | J4: =I4+J3 -> 60000 | K4: =J4+K3 -> 80000 | L4: =K4+L3 -> 100000 | M4: =L4+M3 -> 120000 | N4: =M4+N3 -> 120000 | O4: =N4+O3 -> 130000 | P4: =O4+P3 -> 130000 | ... S4: =R4+S3 -> 130000 | U4: 9924 | V4: 200 | W4: 44977
C5: ='CB-17'!B5 -> TOTAL EXPENSES | D5: =D7+D20+D27+D76+D35+D59+D45+D62+D67+D71 -> 50174.487 | U5: 9925 | V5: 200 | W5: 45004
C6: ='CB-17'!B6 -> NET REVENUE | D6: =D3-D5 -> 79825.513
C7: ='CB-17'!B7 -> UTILITIES | D7: =SUM(D8:D19) -> 1712.8666 | E7: Prorated | F7: Rate | G7: Annual | H7: =SUM(H8:H14) -> 445.12 | I7: =SUM(I8:I14) -> 1217.14 | J7: =SUM(J8:J14) -> 479.18 | K7: =SUM(K8:K34) -> 1736.62 | L7: =SUM(L8:L14) -> 365.36 | M7: =SUM(M8:M14) -> 706.03 | N7: =SUM(N8:N14) -> 332.83 | O7: =SUM(O8:O14) -> 600.07 | P7: =SUM(P8:P14) -> 190 | Q7: =SUM(Q8:Q14) -> 682.43 | R7: =SUM(R8:R14) -> 397.14 | S7: =SUM(S8:S14) -> 1115.94 | U7: 3048 | V7: 320.03 | W7: 45066
B8: =#REF! -> #REF! | C8: ='CB-17'!B8 -> Electricity | D8: =E8 -> 368.8048 | E8: =F8*G8 -> 368.8048 | F8: ='CB-17'!E8 -> 0.17 | G8: =SUM(H8:S8) -> 2169.44 | H8: 255.12 | I8: 272.7 | J8: 289.18 | K8: 249.83 | L8: 175.36 | M8: =12.64+130.19 -> 142.83 | N8: =12.64+130.19 -> 142.83 | O8: 67.14 | Q8: 119.23 | R8: 207.14 | S8: 248.08
B9: =#REF! -> #REF! | C9: ='CB-17'!B9 -> Waste & Recycle | D9: =E9 -> 22.1561 | E9: =F9*G9 -> 22.1561 | F9: ='CB-17'!E9 -> 0.17 | G9: =SUM(H9:S9) -> 130.33 | K9: 130.33
B10: =#REF! -> #REF! | C10: ='CB-17'!B10 -> Water & Sewer | D10: =E10 -> 499.3257 | E10: =F10*G10 -> 499.3257 | F10: ='CB-17'!E10 -> 0.17 | G10: =SUM(H10:S10) -> 2937.21 | I10: 754.44 | K10: 415.58 | M10: 373.2 | O10: 342.93 | Q10: 373.2 | S10: 677.86
B11: =#REF! -> #REF! | C11: ='CB-17'!B11 -> Security | D11: =E11 -> 102 | E11: =F11*G11 -> 102 | F11: ='CB-17'!E11 -> 0.17 | G11: =SUM(H11:S11) -> 600 | H11: 50 | I11: 50 | J11: 50 | K11: 50 | L11: 50 | M11: 50 | N11: 50 | O11: 50 | P11: 50 | Q11: 50 | R11: 50 | S11: 50
B12: =#REF! -> #REF! | C12: ='CB-17'!B12 -> Landscaping | D12: =E12 -> 285.6 | E12: =F12*G12 -> 285.6 | F12: ='CB-17'!E12 -> 0.17 | G12: =SUM(H12:S12) -> 1680 | H12: 140 | I12: 140 | J12: 140 | K12: 140 | L12: 140 | M12: 140 | N12: 140 | O12: 140 | P12: 140 | Q12: 140 | R12: 140 | S12: 140
C13: ='CB-17'!B13 -> Home Owners Insurance | D13: =E13 -> 0 | E13: =F13*G13 -> 0 | F13: ='CB-17'!E13 -> 0.17 | G13: =SUM(H13:S13) -> 0
C14: ='CB-17'!B14 -> Appliance Maintenance | D14: =E14 -> 0 | E14: =F14*G14 -> 0 | F14: ='CB-17'!E14 -> 0.5 | G14: =SUM(H14:S14) -> 0
C15: ='CB-17'!B15 -> Apple Warranty | D15: =E15 -> 164.5 | E15: =F15*G15 -> 164.5 | F15: ='CB-17'!E15 -> 0.5 | G15: =SUM(H15:S15) -> 329 | K15: 329
C16: ='CB-17'!B16 -> Computers Warranty | D16: =E16 -> 0 | E16: =F16*G16 -> 0 | F16: ='CB-17'!E16 -> 0.5 | G16: =SUM(H16:S16) -> 0
B17: T-Mobile | C17: ='CB-17'!B17 -> Cellular Service | D17: =E17 -> 270.48 | E17: =F17*G17 -> 270.48 | F17: ='CB-17'!E17 -> 0.5 | G17: =SUM(H17:S17) -> 540.96 | H17: 45.08 | J17: =45.08+45.08 -> 90.16 | L17: =45.08+45.08 -> 90.16 | N17: =45.08+45.08 -> 90.16 | O17: 45.08 | Q17: =45.08+45.08 -> 90.16 | S17: =45.08+45.08 -> 90.16
A18: xfiniti | B18: Comcast | C18: ='CB-17'!B18 -> Broadband | D18: =E18 -> 0 | E18: =F18*G18 -> 0 | F18: ='CB-17'!E18 -> 0.5 | G18: =SUM(H18:S18) -> 0
C19: ='CB-17'!B19 -> TV Cable | D19: =E19 -> 0 | E19: =F19*G19 -> 0 | F19: ='CB-17'!E19 -> 0.5 | G19: =SUM(H19:S19) -> 0
C20: ='CB-17'!B20 -> DEPRECIABLE ASSETS | D20: =SUM(D21:D26) -> 0 | E20: Prorated | F20: Rate | G20: Annual | H20: =SUM(H21:H26) -> 0 | I20: =SUM(I21:I26) -> 0 | J20: =SUM(J21:J26) -> 0 | K20: =SUM(K21:K26) -> 0 | L20: =SUM(L21:L26) -> 0 | M20: =SUM(M21:M26) -> 0 | N20: =SUM(N21:N26) -> 0 | O20: =SUM(O21:O26) -> 0 | ... S20: =SUM(S21:S26) -> 0
C21: ='CB-17'!B21 -> ASUS Laptop | D21: =E21 -> 0 | E21: =F21*G21 -> 0 | F21: ='CB-17'!E21 -> 0.5 | G21: =SUM(H21:S21) -> 0
C22: ='CB-17'!B22 -> Mobile Device (samsung) | D22: =E22 -> 0 | E22: =F22*G22 -> 0 | F22: ='CB-17'!E22 -> 0.5 | G22: =SUM(H22:S22) -> 0
C23: ='CB-17'!B23 -> Cellphone Device | D23: =E23 -> 0 | E23: =F23*G23 -> 0 | F23: ='CB-17'!E23 -> 0.5 | G23: =SUM(H23:S23) -> 0
C24: ='CB-17'!B24 -> Supplies | D24: =E24 -> 0 | E24: =F24*G24 -> 0 | F24: ='CB-17'!E24 -> 1 | G24: =SUM(H24:S24) -> 0
C25: ='CB-17'!B25 -> Stationaries | D25: =E25 -> 0 | E25: =F25*G25 -> 0 | F25: ='CB-17'!E25 -> 1 | G25: =SUM(H25:S25) -> 0
C26: ='CB-17'!B26 -> Books | D26: =E26 -> 0 | E26: =F26*G26 -> 0 | F26: ='CB-17'!E26 -> 1 | G26: =SUM(H26:S26) -> 0
C27: ='CB-17'!B27 -> GOVERNMENT FEES | D27: =SUM(D28:D34) -> 5015.77 | E27: Prorated | F27: Rate | G27: Annual
B28: =#REF! -> #REF! | C28: ='CB-17'!B28 -> Biz Registration | D28: =G28 -> 0 | E28: =F28*G28 -> 0 | F28: ='CB-17'!E28 -> 1 | G28: =SUM(H28:S28) -> 0
C29: ='CB-18'!B29 -> Licensing | D29: =G29 -> 0 | E29: =F29*G29 -> 0 | F29: ='CB-17'!E29 -> 1 | G29: =SUM(H29:S29) -> 0
C30: ='CB-17'!B30 -> WA DOR Excise Tax | D30: =G30 -> 3838.61 | E30: =F30*G30 -> 3838.61 | F30: ='CB-17'!E30 -> 1 | G30: =SUM(H30:S30) -> 3838.61 | H30: 911.59 | I30: 559.19 | J30: 542.87 | K30: 421.88 | L30: 326.25 | N30: =478.79+517.5 -> 996.29 | R30: 80.54
C31: ='CB-17'!B31 -> Garnishment Fee | D31: =G31 -> 250 | E31: =F31*G31 -> 250 | F31: ='CB-17'!E31 -> 1 | G31: =SUM(H31:S31) -> 250 | H31: 125 | P31: 125
C32: ='CB-17'!B32 -> LNI Insurance | D32: =G32 -> 207.45 | E32: =F32*G32 -> 207.45 | F32: ='CB-17'!E32 -> 1 | G32: =SUM(H32:S32) -> 207.45 | H32: 207.45
C33: ='CB-17'!B33 -> WA Employment Security | D33: =G33 -> 719.71 | E33: =F33*G33 -> 719.71 | F33: ='CB-17'!E33 -> 1 | G33: =SUM(H33:S33) -> 719.71 | P33: 719.71
C34: ='CB-17'!B34 -> Commercial Insurance | D34: =G34 -> 0 | E34: =F34*G34 -> 0 | F34: ='CB-17'!E34 -> 1 | G34: =SUM(H34:S34) -> 0
C35: ='CB-17'!B35 -> PROFESSIONAL SERVICES | D35: =SUM(D36:D44) -> 245.85 | E35: Prorated | F35: Rate | G35: Annual
C36: ='CB-17'!B36 -> Web Domains | D36: =G36 -> 0 | E36: =F36*G36 -> 0 | F36: ='CB-17'!E36 -> 1 | G36: =SUM(H36:S36) -> 0
C37: ='CB-17'!B37 -> Web Hosting | D37: =G37 -> 0 | E37: =F37*G37 -> 0 | F37: ='CB-17'!E37 -> 1 | G37: =SUM(H37:S37) -> 0
C38: ='CB-17'!B38 -> Digital Ads | D38: =G38 -> 0 | E38: =F38*G38 -> 0 | F38: ='CB-17'!E38 -> 1 | G38: =SUM(H38:S38) -> 0
C39: ='CB-17'!B39 -> Logo Services | D39: =G39 -> 0 | E39: =F39*G39 -> 0 | F39: ='CB-17'!E39 -> 1 | G39: =SUM(H39:S39) -> 0
C40: ='CB-17'!B40 -> Temp Services | D40: =G40 -> 0 | E40: =F40*G40 -> 0 | F40: ='CB-17'!E40 -> 1 | G40: =SUM(H40:S40) -> 0
C41: ='CB-17'!B41 -> Professional Services | D41: =G41 -> 0 | E41: =F41*G41 -> 0 | F41: ='CB-17'!E41 -> 1 | G41: =SUM(H41:S41) -> 0
C42: ='CB-17'!B42 -> Bank Fees | D42: =G42 -> 245.85 | E42: =F42*G42 -> 245.85 | F42: ='CB-17'!E42 -> 1 | G42: =SUM(H42:S42) -> 245.85 | H42: 1.25 | I42: =35+35+1.25 -> 71.25 | J42: =3.75+10 -> 13.75 | L42: 2.5 | M42: =2.5+2.93+1.25 -> 6.68 | N42: =2.5+2.5+2.5+2.5+2.92+2.9*3+2.99+3.45+3.63*2+2.5+2.99+3.45+2.5+2.5+6+3.46*2+2.5*2+2.99*2+3.45*2+2.5*2+2.99*2+3.44*2+2.5*2+2.98*2+3.64*2+5+5.8 -> 126.96 | O42: =2.5*3+2.91+3.55+1.25 -> 15.21 | P42: 8.25
C43: ='CB-17'!B43 -> Legal Membership | D43: =G43 -> 0 | E43: =F43*G43 -> 0 | F43: ='CB-17'!E43 -> 1 | G43: =SUM(H43:S43) -> 0
C44: ='CB-17'!B44 -> Business Insurance | D44: =G44 -> 0 | E44: =F44*G44 -> 0 | F44: ='CB-17'!E44 -> 1 | G44: =SUM(H44:S44) -> 0
C45: ='CB-17'!B45 -> SUBSCRIPTIONS | D45: =SUM(D46:D58) -> 0 | E45: Prorated | F45: Rate | G45: Annual
C46: ='CB-17'!B46 -> Apple.com | D46: =E46 -> 0 | E46: =F46*G46 -> 0 | F46: 0.5 | G46: =SUM(H46:S46) -> 0
C47: ='CB-17'!B47 -> Audible.com | D47: =E47 -> 0 | E47: =F47*G47 -> 0 | F47: 1 | G47: =SUM(H47:S47) -> 0
C48: ='CB-17'!B48 -> Amazon | D48: =E48 -> 0 | E48: =F48*G48 -> 0 | F48: 0.5 | G48: =SUM(H48:S48) -> 0
C49: ='CB-17'!B49 -> Cloud Academy | D49: =E49 -> 0 | E49: =F49*G49 -> 0 | F49: 1 | G49: =SUM(H49:S49) -> 0
C50: ='CB-17'!B50 -> Packt | D50: =E50 -> 0 | E50: =F50*G50 -> 0 | F50: 1 | G50: =SUM(H50:S50) -> 0
C51: ='CB-17'!B51 -> Pluralsight | D51: =E51 -> 0 | E51: =F51*G51 -> 0 | F51: 1 | G51: =SUM(H51:S51) -> 0
C52: ='CB-17'!B52 -> Linux Academy | D52: =E52 -> 0 | E52: =F52*G52 -> 0 | F52: 1 | G52: =SUM(H52:S52) -> 0
C53: ='CB-17'!B53 -> Adobe | D53: =E53 -> 0 | E53: =F53*G53 -> 0 | F53: 1 | G53: =SUM(H53:S53) -> 0
C54: ='CB-17'!B54 -> O365 | D54: =E54 -> 0 | E54: =F54*G54 -> 0 | F54: 1 | G54: =SUM(H54:S54) -> 0
C55: ='CB-17'!B55 -> Microsoft Alumni | D55: =E55 -> 0 | E55: =F55*G55 -> 0 | F55: 1 | G55: =SUM(H55:S55) -> 0
C56: ='CB-17'!B56 -> LinkedIn | D56: =E56 -> 0 | E56: =F56*G56 -> 0 | F56: 1 | G56: =SUM(H56:S56) -> 0
C57: ='CB-17'!B57 -> DOODLY | D57: =E57 -> 0 | E57: =F57*G57 -> 0 | F57: 1 | G57: =SUM(H57:S57) -> 0
C58: ='CB-17'!B58 -> Whizlabs | D58: =E58 -> 0 | E58: =F58*G58 -> 0 | F58: 1 | G58: =SUM(H58:S58) -> 0
C59: AUTO MILEAGE | D59: =D60 -> 0 | E59: Prorated | F59: Rate | G59: Annual
C60: =C1 & " IRS rate" -> 2019 IRS rate | D60: =E60 -> 0 | E60: =F60*G60 -> 0 | F60: 0.545 | G60: =SUM(H60:S60) -> 0
C61: ='CB-17'!B61 -> SETUP EXPENSES
C62: ='CB-17'!B62 -> WOODRIDGE OFFICE RENOVATION | D62: =SUM(D63:D66) -> 0 | E62: Prorated | F62: Rate | G62: Annual
C63: ='CB-17'!B63 -> Flooring | D63: =E63 -> 0 | E63: =F63*G63 -> 0 | F63: 1 | G63: =SUM(H63:S63) -> 0
C64: ='CB-17'!B64 -> Paint | D64: =E64 -> 0 | E64: =F64*G64 -> 0 | F64: 1 | G64: =SUM(H64:S64) -> 0
C65: ='CB-17'!B65 -> bathroom | D65: =E65 -> 0 | E65: =F65*G65 -> 0 | F65: 1 | G65: =SUM(H65:S65) -> 0
C66: ='CB-17'!B66 -> electrical work | D66: =E66 -> 0 | E66: =F66*G66 -> 0 | F66: 1 | G66: =SUM(H66:S66) -> 0
C67: ='CB-17'!B67 -> INDIA OFFICE RENOVATION | D67: =SUM(D68:D70) -> 0 | E67: Prorated | F67: Rate | G67: Annual
C68: ='CB-17'!B68 -> faucets | D68: =E68 -> 0 | E68: =F68*G68 -> 0 | F68: 1 | G68: =SUM(H68:S68) -> 0
C69: ='CB-17'!B69 -> furniture | D69: =E69 -> 0 | E69: =F69*G69 -> 0 | F69: 1 | G69: =SUM(H69:S69) -> 0
C70: ='CB-17'!B70 -> lights | D70: =E70 -> 0 | E70: =F70*G70 -> 0 | F70: 1 | G70: =SUM(H70:S70) -> 0
C71: ='CB-17'!B71 -> INDIA OFFICE EXPENSES | D71: =SUM(D72:D74) -> 0 | E71: Prorated | F71: Rate | G71: Annual
C72: ='CB-17'!B72 -> electricity | D72: =E72 -> 0 | E72: =F72*G72 -> 0 | F72: 1 | G72: =SUM(H72:S72) -> 0
C73: ='CB-17'!B73 -> taxes | D73: =E73 -> 0 | E73: =F73*G73 -> 0 | F73: 1 | G73: =SUM(H73:S73) -> 0
C74: ='CB-17'!B74 -> cleaning | D74: =E74 -> 0 | E74: =F74*G74 -> 0 | F74: 1 | G74: =SUM(H74:S74) -> 0
C75: ='CB-17'!B75 -> Staff | D75: =E75 -> 0 | E75: =F75*G75 -> 0 | F75: 1 | G75: =SUM(H75:S75) -> 0
C76: ='CB-17'!B76 -> PAYROLL | D76: =SUM(G77:G80) -> 43200 | F76: Rate
C77: W2 Ethan Rose | E77: =G77*F77 -> 0 | F77: 1
C78: Fed 76.44; FICA 62; Medicare 14.5 | E78: =G78*F78 -> 0 | F78: 1 | G78: =SUM(H78:S78) -> 0
C79: W2 Zach DeVita | D79: =E79 -> 0 | E79: =G79*F79 -> 0 | F79: 1 | G79: =SUM(H79:S79) -> 0
C80: 1099 Shirish Sharma | D80: =E80 -> 43200 | E80: =G80*F80 -> 43200 | F80: 1 | G80: =SUM(I80:S80) -> 43200 | I80: 7200 | K80: 14400 | N80: 7200 | O80: 7200 | P80: 7200
U82: 3044 | V82: 330 | W82: 44766 | X82: Edilberto
U83: 3583 | V83: 300 | W83: 44745 | X83: SEARS
U84: 9917 | V84: 200 | W84: 44760 | X84: BoA
U85: 3022 | V85: 570 | W85: 44779 | X85: Edilberto
U86: 3023 | V86: 350 | W86: 44779 | X86: Edilberto
U87: 3024 | V87: 151 | W87: 44794 | X87: Edilberto
U88: 3025 | V88: 180 | W88: 44794 | X88: Edilberto
U89: 3584 | V89: 300 | W89: 44776 | X89: SEARS
U90: 9918 | V90: 200 | W90: 44793 | X90: BoA
U91: 3045 | V91: 135 | W91: 44814 | X91: Edilberto
U92: 3046 | V92: 165 | W92: 44814 | X92: Edilberto
U93: 3583 | V93: 300 | W93: 44808 | X93: SEARS
... U100: 9921 | V100: 200 | W100: 44885 | X100: BoA
C101: IRA | U101: 103 | V101: 1230.57 | W101: 44898 | X101: zach devita
C102: SEP IRA | J102: 5000 | U102: 3047 | V102: 1449.68 | W102: 44913 | X102: zach devita
U103: 9922 | V103: 200 | W103: 44913 | X103: BoA
J105: 613
H108: 19602
C111: home depot | H111: 34 | J111: 810.55 | K111: 1727.17

Sheet CB-18
A1: =Summary!L5 -> 2018 | B1: =Summary!L5 -> 2018 | G1: ="CLOUDBAUD CONSULTING "& Summary!L5 & " ONLY" -> CLOUDBAUD CONSULTING 2018 ONLY | T1: Last Update | V1: =NOW() -> 45893.328
A2: Sources | C2: ='CB-17'!C2 -> 0 | D2: ='CB-17'!D2 -> 0 | F2: TOTAL | G2: Jan | H2: Feb | I2: Mar | J2: Apr | K2: May | L2: Jun | M2: Jul | N2: Aug | O2: Sep | P2: Oct | Q2: Nov | R2: Dec | T2: Check# | U2: Amount | V2: Date | W2: Payee
A3: Various | B3: ='CB-17'!B3 -> CONSULTING REVENUE | C3: =F3-D3 -> 485019.41 | F3: =SUM(G3:R3) -> 485019.41 | G3: =15630+15630 -> 31260 | H3: =18018.79+H4-G4-18018.79 -> 35898.79 | I3: =I4-H4 -> 33883.57 | J3: =J4-I4 -> 33702.5 | K3: =16735+16927.7 -> 33662.7 | L3: =L4-K4 -> 33682.7 | M3: =M4-L4 -> 48414.56 | N3: =N4-M4 -> 40082.7 | O3: =O4-N4 -> 51282.7 | P3: =P4-O4 -> 51282.7 | Q3: =Q4-P4 -> 44923.57 | R3: =23130+10000+13812.92 -> 46942.92 | T3: 3032 | U3: 19 | V3: jan | W3: DOR
F4: YTD | G4: =G3 -> 31260 | H4: =67158.79 -> 67158.79 | I4: 101042.36 | J4: =K4-K3 -> 134744.86 | K4: 168407.56 | L4: 202090.26 | M4: 250504.82 | N4: 290587.52 | O4: 341870.22 | P4: 393152.92 | Q4: 438076.49 | R4: =461206.49+23812.92 -> 485019.41 | T4: 3033 | U4: 500 | V4: jan | W4: Edilberto
B5: ='CB-17'!B5 -> TOTAL EXPENSES | C5: =C7+C20+C27+C76+C35+C59+C45+C62+C67+C71 -> #REF! | D5: =SUM(D8:D18) -> 3612.6345 | T5: 3034 | U5: 1269 | V5: jan | W5: Deepika
B6: ='CB-17'!B6 -> NET REVENUE | C6: =C3-C5 -> #REF! | T6: 3035 | U6: 1000 | V6: jan | W6: edilberto
A7: PSE | B7: ='CB-17'!B7 -> UTILITIES | C7: =SUM(C8:C19) -> 3612.6345 | D7: Prorated | E7: Rate | F7: Annual | G7: =SUM(G8:G14) -> 490 | H7: =SUM(H8:H14) -> 841.33 | I7: =SUM(I8:I14) -> 490 | J7: =SUM(J8:J14) -> 840.86 | K7: =SUM(K8:K14) -> 490 | L7: =SUM(L8:L14) -> 988.88 | M7: =SUM(M8:M14) -> 2269.83 | N7: =SUM(N8:N14) -> 992.06 | ... R7: =SUM(R8:R14) -> 1194.96 | T7: 3036 | U7: 500 | V7: jan | W7: edilberto
A8: City | B8: ='CB-17'!B8 -> Electricity | C8: =D8 -> 152.6991 | D8: =E8*F8 -> 152.6991 | E8: ='CB-17'!E8 -> 0.17 | F8: =SUM(G8:R8) -> 898.23 | G8: 0 | H8: 0 | I8: 0 | J8: 0 | K8: 0 | L8: =12.64+130.19 -> 142.83 | M8: =12.64+130.19 -> 142.83 | N8: =8.7+111.68 -> 120.38 | O8: 120.89 | P8: 0 | Q8: 61.65 | R8: =95.6+214.05 -> 309.65 | T8: 3577 | U8: 300 | V8: jan | W8: SEARS
A9: City | B9: ='CB-17'!B9 -> Waste & Recycle | C9: =D9 -> 0 | D9: =E9*F9 -> 0 | E9: ='CB-17'!E9 -> 0.17 | F9: =SUM(G9:R9) -> 0 | G9: 0 | H9: 0 | I9: 0 | J9: 0 | K9: 0 | L9: 0 | M9: 0 | N9: 0 | O9: 0 | P9: 0 | Q9: 0 | R9: 0 | T9: 9910 | U9: 135 | V9: jan | W9: BoA
A10: ADT | B10: ='CB-17'!B10 -> Water & Sewer | C10: =D10 -> 384.9854 | D10: =E10*F10 -> 384.9854 | E10: ='CB-17'!E10 -> 0.17 | F10: =SUM(G10:R10) -> 2264.62 | H10: 351.33 | I10: 0 | J10: 350.86 | K10: 0 | L10: 356.05 | M10: 0 | N10: 381.68 | O10: 0 | P10: 429.39 | Q10: 0 | R10: 395.31 | T10: 9911 | U10: 135 | V10: jan | W10: BoA
A11: Personal | B11: ='CB-17'!B11 -> Security | C11: =D11 -> 102 | D11: =E11*F11 -> 102 | E11: ='CB-17'!E11 -> 0.17 | F11: =SUM(G11:R11) -> 600 | G11: 50 | H11: 50 | I11: 50 | J11: 50 | K11: 50 | L11: 50 | M11: 50 | N11: 50 | O11: 50 | P11: 50 | Q11: 50 | R11: 50 | T11: 3011 | U11: 2000 | V11: feb
B12: ='CB-17'!B12 -> Landscaping | C12: =D12 -> 285.6 | D12: =E12*F12 -> 285.6 | E12: ='CB-17'!E12 -> 0.17 | F12: =SUM(G12:R12) -> 1680 | G12: 140 | H12: 140 | I12: 140 | J12: 140 | K12: 140 | L12: 140 | M12: 140 | N12: 140 | O12: 140 | P12: 140 | Q12: 140 | R12: 140 | T12: 3578 | U12: 300 | V12: feb | W12: SEARS
A13: CCMSEARS | B13: ='CB-17'!B13 -> Home Owners Insurance | C13: =D13 -> 278.29 | D13: =E13*F13 -> 278.29 | E13: ='CB-17'!E13 -> 0.17 | F13: =SUM(G13:R13) -> 1637 | G13: 0 | H13: 0 | I13: 0 | J13: 0 | K13: 0 | L13: 0 | M13: ='Home Insurance'!K13 -> 1637 | N13: 0 | O13: 0 | P13: 0 | Q13: 0 | R13: 0 | T13: 3012 | U13: 1848.58 | V13: 44646 | W13: Plumbing
B14: ='CB-17'!B14 -> Appliance Maintenance | C14: =D14 -> 1800 | D14: =E14*F14 -> 1800 | E14: ='CB-17'!E14 -> 0.5 | F14: =SUM(G14:R14) -> 3600 | G14: =U8 -> 300 | H14: =U12 -> 300 | I14: =U12 -> 300 | J14: =U22 -> 300 | K14: =U28 -> 300 | L14: 300 | M14: =U35 -> 300 | N14: =U41 -> 300 | O14: 300 | P14: 300 | Q14: 300 | R14: 300
B15: ='CB-17'!B15 -> Apple Warranty | C15: =D15 -> 0 | D15: =E15*F15 -> 0 | E15: ='CB-17'!E15 -> 0.5 | F15: =SUM(G15:R15) -> 0
B16: ='CB-17'!B16 -> Computers Warranty | C16: =D16 -> 0 | D16: =E16*F16 -> 0 | E16: ='CB-17'!E16 -> 0.5 | F16: =SUM(G16:R16) -> 0 | T16: 9912 | U16: 135 | V16: 44621 | W16: BoA
A17: Comcast | B17: ='CB-17'!B17 -> Cellular Service | C17: =D17 -> 609.06 | D17: =F17*E17 -> 609.06 | E17: ='CB-17'!E17 -> 0.5 | F17: =SUM(G17:R17) -> 1218.12 | H17: 305.35 | K17: 126.68 | L17: 172.08 | M17: 172.08 | N17: 117.72 | O17: 112.72 | P17: 112.17 | Q17: 77.43 | R17: 21.89 | T17: 9913 | U17: 135 | V17: 44643 | W17: BoA
B18: ='CB-17'!B18 -> Broadband | C18: =D18 -> 0 | D18: =E18*F18 -> 0 | E18: ='CB-17'!E18 -> 0.5 | F18: =SUM(G18:R18) -> 0 | T18: 3013 | U18: 694 | V18: 44654 | W18: Edilberto
B19: ='CB-17'!B19 -> TV Cable | C19: =D19 -> 0 | D19: =E19*F19 -> 0 | E19: ='CB-17'!E19 -> 0.5 | F19: =SUM(G19:R19) -> 0 | T19: 3014 | U19: 3100 | V19: 44669 | W19: concrete
B20: ='CB-17'!B20 -> DEPRECIABLE ASSETS | C20: =SUM(C21:C26) -> 0 | D20: Prorated | E20: Rate | F20: Annual | G20: =SUM(G21:G26) -> 0 | H20: =SUM(H21:H26) -> 0 | I20: =SUM(I21:I26) -> 0 | J20: =SUM(J21:J26) -> 0 | K20: =SUM(K21:K26) -> 0 | L20: =SUM(L21:L26) -> 0 | M20: =SUM(M21:M26) -> 0 | N20: =SUM(N21:N26) -> 0 | ... R20: =SUM(R21:R26) -> 0 | T20: 3037 | U20: 1000 | V20: 44656 | W20: bathroom
B21: ='CB-17'!B21 -> ASUS Laptop | C21: =F21 -> 0 | D21: =E21*F21 -> 0 | E21: ='CB-17'!E21 -> 0.5 | F21: =SUM(G21:R21) -> 0 | T21: 3038 | U21: 300 | V21: 44662 | W21: paint
A22: Olympia + KC + City | B22: ='CB-17'!B22 -> Mobile Device (samsung) | C22: =F22 -> 0 | D22: =E22*F22 -> 0 | E22: ='CB-17'!E22 -> 0.5 | F22: =SUM(G22:R22) -> 0 | T22: 3580 | U22: 300 | V22: 44654 | W22: SEARS
B23: ='CB-17'!B23 -> Cellphone Device | C23: =F23 -> 0 | D23: =E23*F23 -> 0 | E23: ='CB-17'!E23 -> 0.5 | F23: =SUM(G23:R23) -> 0 | T23: 9914 | U23: 200 | V23: 44669 | W23: BoA
B24: ='CB-17'!B24 -> Supplies | C24: =F24 -> 0 | D24: =E24*F24 -> 0 | E24: 1 | F24: =SUM(G24:R24) -> 0 | T24: 3015 | U24: 200 | V24: 44683
B25: Stationaries | C25: =F25 -> 0 | D25: =E25*F25 -> 0 | E25: 1 | F25: =SUM(G25:R25) -> 0 | T25: 3017 | U25: 900 | V25: 44688 | W25: hector hickman
B26: ='CB-17'!B26 -> Books | C26: =F26 -> 0 | D26: =E26*F26 -> 0 | E26: 1 | F26: =SUM(G26:R26) -> 0 | T26: 3018 | U26: 925 | V26: 44688 | W26: hector hickman
B27: ='CB-17'!B27 -> GOVERNMENT FEES | C27: =SUM(C28:C34) -> 11572.2 | D27: Prorated | E27: Rate | F27: Annual | G27: =SUM(G28:G34) -> 19 | H27: =SUM(H28:H34) -> 0 | I27: =SUM(I28:I34) -> 511.1 | J27: =SUM(J28:J34) -> 0 | K27: =SUM(K28:K34) -> 1746.69 | L27: =SUM(L28:L34) -> 4316.97 | M27: =SUM(M28:M34) -> 0 | N27: =SUM(N28:N34) -> 676.67 | ... R27: =SUM(R28:R34) -> 673.85 | T27: 3039 | U27: 108 | V27: 44712 | W27: Plumbing
B28: ='CB-17'!B28 -> Biz Registration | C28: =F28 -> 0 | D28: =E28*F28 -> 0 | E28: ='CB-17'!E28 -> 1 | F28: =SUM(G28:R28) -> 0 | T28: 3581 | U28: 300 | V28: 44684 | W28: SEARS
B29: ='CB-17'!B29 -> Licensing | C29: =F29 -> 0 | D29: =E29*F29 -> 0 | E29: ='CB-17'!E29 -> 1 | F29: =SUM(G29:R29) -> 0 | T29: 9915 | U29: 200 | V29: 44699 | W29: BoA
B30: ='CB-17'!B30 -> WA DOR Excise Tax | C30: =F30 -> 11572.2 | D30: =E30*F30 -> 11572.2 | E30: ='CB-17'!E30 -> 1 | F30: =SUM(G30:R30) -> 11572.2 | G30: =U3 -> 19 | I30: 511.1 | K30: =854.49+892.2 -> 1746.69 | L30: =538.48+550.38+551.04+604.82+U30 -> 4316.97 | N30: =125.97+550.7 -> 676.67 | Q30: =715.48+838.47+1264.37+769.24+40.36 -> 3627.92 | R30: =673.85 -> 673.85 | T30: 3019 | U30: 2072.25 | V30: 44733 | W30: king county treasury
B31: ='CB-17'!B31 -> Garnishment Fee | C31: =F31 -> 0 | D31: =E31*F31 -> 0 | E31: ='CB-17'!E31 -> 1 | F31: =SUM(G31:R31) -> 0 | T31: 3020 | U31: 206 | V31: 44732 | W31: Edilberto
B32: ='CB-17'!B32 -> LNI Insurance | C32: =F32 -> 0 | D32: =E32*F32 -> 0 | E32: ='CB-17'!E32 -> 1 | F32: =SUM(G32:R32) -> 0 | T32: 3040 | U32: 400 | V32: 44716 | W32: Edilberto
B33: ='CB-17'!B33 -> WA Employment Security | C33: =F33 -> 0 | D33: =E33*F33 -> 0 | E33: ='CB-17'!E33 -> 1 | F33: =SUM(G33:R33) -> 0 | T33: 3041 | U33: 433 | V33: 44718 | W33: Edilberto
B34: ='CB-17'!B34 -> Commercial Insurance | C34: =F34 -> 0 | D34: =E34*F34 -> 0 | E34: ='CB-17'!E34 -> 1 | F34: =SUM(G34:R34) -> 0 | T34: 3042 | U34: 300 | V34: 44723 | W34: Edilberto
B35: ='CB-17'!B35 -> PROFESSIONAL SERVICES | C35: =SUM(C36:C44) -> 875 | D35: Prorated | E35: ='CB-17'!E35 -> Rate | F35: Annual | G35: =SUM(G36:G44) -> 0 | H35: =SUM(H36:H44) -> 0 | I35: =SUM(I36:I44) -> 105 | J35: =SUM(J36:J44) -> 0 | K35: =SUM(K36:K44) -> 47.5 | L35: =SUM(L36:L44) -> 122.5 | M35: =SUM(M36:M44) -> 0 | N35: =SUM(N36:N44) -> 0 | ... R35: =SUM(R36:R44) -> 0 | T35: 3583 | U35: 300 | V35: 44745 | W35: SEARS
A36: GoDaddy | B36: ='CB-17'!B36 -> Web Domains | C36: =F36 -> 0 | D36: =E36*F36 -> 0 | E36: ='CB-17'!E36 -> 1 | F36: =SUM(G36:R36) -> 0 | T36: 9917 | U36: 200 | V36: 44760 | W36: BoA
A37: Comcast | B37: ='CB-17'!B37 -> Web Hosting | C37: =F37 -> 0 | D37: =E37*F37 -> 0 | E37: ='CB-17'!E37 -> 1 | F37: =SUM(G37:R37) -> 0 | T37: 3022 | U37: 570 | V37: 44779 | W37: Edilberto
B38: ='CB-17'!B38 -> Digital Ads | C38: =F38 -> 0 | D38: =E38*F38 -> 0 | E38: ='CB-17'!E38 -> 1 | F38: =SUM(G38:R38) -> 0 | T38: 3023 | U38: 350 | V38: 44779 | W38: Edilberto
B39: ='CB-17'!B39 -> Logo Services | C39: =F39 -> 0 | D39: =E39*F39 -> 0 | E39: ='CB-17'!E39 -> 1 | F39: =SUM(G39:R39) -> 0 | T39: 3024 | U39: 151 | V39: 44794 | W39: Edilberto
B40: ='CB-17'!B40 -> Temp Services | C40: =F40 -> 0 | D40: =E40*F40 -> 0 | E40: ='CB-17'!E40 -> 1 | F40: =SUM(G40:R40) -> 0 | T40: 3025 | U40: 180 | V40: 44794 | W40: Edilberto
B41: ='CB-17'!B41 -> Professional Services | C41: =F41 -> 600 | D41: =E41*F41 -> 600 | E41: ='CB-17'!E41 -> 1 | F41: =SUM(G41:R41) -> 600 | Q41: 600 | T41: 3584 | U41: 300 | V41: 44776 | W41: SEARS
B42: ='CB-17'!B42 -> Bank Fees | C42: =F42 -> 275 | D42: =E42*F42 -> 275 | E42: ='CB-17'!E42 -> 1 | F42: =SUM(G42:R42) -> 275 | I42: 105 | K42: 47.5 | L42: =105+17.5 -> 122.5 | T42: 9918 | U42: 200 | V42: 44793 | W42: BoA
B43: ='CB-17'!B43 -> Legal Membership | C43: =F43 -> 0 | D43: =E43*F43 -> 0 | E43: ='CB-17'!E43 -> 1 | F43: =SUM(G43:R43) -> 0 | T43: 3045 | U43: 135 | V43: 44814 | W43: Edilberto
B44: ='CB-17'!B44 -> Business Insurance | C44: =F44 -> 0 | D44: =E44*F44 -> 0 | E44: ='CB-17'!E44 -> 1 | F44: =SUM(G44:R44) -> 0 | T44: 3046 | U44: 165 | V44: 44814 | W44: Edilberto
B45: ='CB-17'!B45 -> SUBSCRIPTIONS | C45: =SUM(C46:C58) -> 139.72 | D45: Prorated | E45: ='CB-17'!E45 -> Rate | F45: Annual | G45: =SUM(G49:G58) -> 95.73 | H45: =SUM(H49:H58) -> 0 | I45: =SUM(I49:I58) -> 43.99 | J45: =SUM(J49:J58) -> 0 | K45: =SUM(K49:K58) -> 0 | L45: =SUM(L49:L58) -> 0 | M45: =SUM(M49:M58) -> 0 | N45: =SUM(N49:N58) -> 0 | ... R45: =SUM(R49:R58) -> 0 | T45: 3047 | U45: 1449.68 | V45: 44913 | W45: zach devita
B46: ='CB-17'!B46 -> Apple.com | C46: =E46*D46 -> 0 | D46: =E46*F46 -> 0 | E46: ='CB-17'!E46 -> 0.5 | F46: =SUM(G46:R46) -> 0 | T46: 9922 | U46: 200 | V46: 44913 | W46: BoA
B47: ='CB-17'!B47 -> Audible.com | C47: =E47*D47 -> 0 | D47: =E47*F47 -> 0 | E47: ='CB-17'!E47 -> 1 | F47: =SUM(G47:R47) -> 0
B48: ='CB-17'!B48 -> Amazon | C48: =E48*D48 -> 0 | D48: =E48*F48 -> 0 | E48: ='CB-17'!E48 -> 0.5 | F48: =SUM(G48:R48) -> 0
B49: ='CB-17'!B49 -> Cloud Academy | C49: =E49*D49 -> 0 | D49: =E49*F49 -> 0 | E49: 1 | F49: =SUM(G49:R49) -> 0
B50: ='CB-17'!B50 -> Packt | C50: =E50*D50 -> 0 | D50: =E50*F50 -> 0 | E50: 1 | F50: =SUM(G50:R50) -> 0
B51: ='CB-17'!B51 -> Pluralsight | C51: =E51*D51 -> 95.73 | D51: =E51*F51 -> 95.73 | E51: 1 | F51: =SUM(G51:R51) -> 95.73 | G51: =31.91*3 -> 95.73
B52: ='CB-17'!B52 -> Linux Academy | C52: =E52*D52 -> 0 | D52: =E52*F52 -> 0 | E52: 1 | F52: =SUM(G52:R52) -> 0
B53: ='CB-17'!B53 -> Adobe | C53: =E53*D53 -> 0 | D53: =E53*F53 -> 0 | E53: 1 | F53: =SUM(G53:R53) -> 0
B54: ='CB-17'!B54 -> O365 | C54: =E54*D54 -> 0 | D54: =E54*F54 -> 0 | E54: 1 | F54: =SUM(G54:R54) -> 0
B55: ='CB-17'!B55 -> Microsoft Alumni | C55: =E55*D55 -> 0 | D55: =E55*F55 -> 0 | E55: 1 | F55: =SUM(G55:R55) -> 0
B56: ='CB-17'!B56 -> LinkedIn | C56: =E56*D56 -> 0 | D56: =E56*F56 -> 0 | E56: 1 | F56: =SUM(G56:R56) -> 0
B57: ='CB-17'!B57 -> DOODLY | C57: =E57*D57 -> 0 | D57: =E57*F57 -> 0 | E57: ='CB-17'!E57 -> 1 | F57: =SUM(G57:R57) -> 0
B58: ='CB-17'!B58 -> Whizlabs | C58: =E58*D58 -> 43.99 | D58: =E58*F58 -> 43.99 | E58: 1 | F58: =SUM(G58:R58) -> 43.99 | I58: 43.99
B59: ='CB-17'!B59 -> AUTO MILEAGE | C59: =C60 -> 0 | F59: =SUM(G59:R59) -> 0
B60: 2018 IRS rate | C60: =D60 -> 0 | D60: =E60*F60 -> 0 | E60: 0.545 | F60: =SUM(G60:R60) -> 0
B61: ='CB-17'!B61 -> SETUP EXPENSES
B62: ='CB-17'!B62 -> WOODRIDGE OFFICE RENOVATION | C62: =SUM(C63:C66) -> 800 | D62: Prorated | E62: Rate | F62: Annual | G62: =SUM(G63:G66) -> 0 | H62: =SUM(H63:H66) -> 0 | I62: =SUM(I63:I66) -> 0 | J62: =SUM(J63:J66) -> 0 | K62: =SUM(K63:K66) -> 0 | L62: =SUM(L63:L66) -> 0 | M62: =SUM(M63:M66) -> 0 | N62: =SUM(N63:N66) -> 0 | ... R62: =SUM(R63:R66) -> 800
B63: Flooring | C63: =D63 -> 0 | D63: =E63*F63 -> 0 | E63: 1 | F63: =SUM(G63:R63) -> 0
B64: Paint | C64: =D64 -> 0 | D64: =E64*F64 -> 0 | E64: 1 | F64: =SUM(G64:R64) -> 0
B65: bathroom | C65: =D65 -> 0 | D65: =E65*F65 -> 0 | E65: 1 | F65: =SUM(G65:R65) -> 0
B66: ='CB-17'!B66 -> electrical work | C66: =D66 -> 800 | D66: =E66*F66 -> 800 | E66: 1 | F66: =SUM(G66:R66) -> 800 | R66: 800
B67: ='CB-17'!B67 -> INDIA OFFICE RENOVATION | C67: =SUM(C68:C70) -> 0 | D67: Prorated | E67: Rate | F67: Annual | G67: =SUM(G68:G70) -> 0 | H67: =SUM(H68:H70) -> 0 | I67: =SUM(I68:I70) -> 0 | J67: =SUM(J68:J70) -> 0 | K67: =SUM(K68:K70) -> 0 | L67: =SUM(L68:L70) -> 0 | M67: =SUM(M68:M70) -> 0 | N67: =SUM(N68:N70) -> 0 | ... R67: =SUM(R68:R70) -> 0
B68: faucets | C68: =D68 -> 0 | D68: =E68*F68 -> 0 | E68: 1 | F68: =SUM(G68:R68) -> 0
B69: furniture | C69: =D69 -> 0 | D69: =E69*F69 -> 0 | E69: 1 | F69: =SUM(G69:R69) -> 0
B70: lights | C70: =D70 -> 0 | D70: =E70*F70 -> 0 | E70: 1 | F70: =SUM(G70:R70) -> 0
B71: ='CB-17'!B71 -> INDIA OFFICE EXPENSES | C71: =SUM(C72:C74) -> 0 | D71: Prorated | E71: Rate | F71: Annual
B72: electricity | C72: =D72 -> 0 | D72: =E72*F72 -> 0 | E72: 1 | F72: =SUM(G72:R72) -> 0
B73: taxes | C73: =D73 -> 0 | D73: =E73*F73 -> 0 | E73: 1 | F73: =SUM(G73:R73) -> 0
B74: cleaning | C74: =D74 -> 0 | D74: =E74*F74 -> 0 | E74: 1 | F74: =SUM(G74:R74) -> 0
B75: Staff | C75: =D75 -> 0 | D75: =E75*F75 -> 0 | E75: 1 | F75: =SUM(G75:R75) -> 0
B76: PAYROLL | C76: =SUM(C77:C80) -> #REF! | E76: Rate
B77: W2 Ethan Rose | C77: =D77 -> 847.06 | D77: =F77*E77 -> 847.06 | E77: ='CB-17'!E77 -> 1 | F77: =SUM(G77:R77) -> 847.06 | H77: 847.06
B78: Fed 76.44; FICA 62; Medicare 14.5 | C78: =D78 -> 0 | D78: =F78*E78 -> 0 | E78: ='CB-17'!E78 -> 1 | F78: =SUM(G78:R78) -> 0
B79: W2 Zach DeVita | C79: =D79 -> #REF! | D79: =F79*E79 -> #REF! | E79: ='CB-17'!E79 -> 1 | F79: =SUM(G79:R79) -> #REF! | Q79: =#REF! -> #REF! | R79: =#REF!+U45 -> #REF!
B80: 1099 Shirish Sharma | C80: =D80 -> 88628.29 | D80: =F80*E80 -> 88628.29 | E80: ='CB-17'!E80 -> 1 | F80: =SUM(H80:R80) -> 88628.29 | G80: =3240+3960 -> 7200 | H80: =3600+4320 -> 7920 | I80: =3240+3960 -> 7200 | J80: =3960+3960 -> 7920 | K80: =3600+3960 -> 7560 | L80: =3960+3960 -> 7920 | M80: 0 | N80: =3960+608.79+3600 -> 8168.79 | O80: =827.9+3240+4320 -> 8387.9 | P80: =827.9+3960+4320+827.9+3240+827.9 -> 14003.7 | Q80: =3600+3960+827.9+3960 -> 12347.9 | R80: =7200 -> 7200
B83: Western Tile | O83: 2328
B84: idtech | Q84: 1198
B85: eco electric | Q85: 2692.25
B86: priceline
B87: homedepot | Q87: 4

Sheet CB-17
A1: =Summary!M5 -> 2017 | B1: =Summary!M5 -> 2017 | G1: ="CLOUDBAUD CONSULTING "& Summary!M5 & " ONLY" -> CLOUDBAUD CONSULTING 2017 ONLY
A2: Sources | F2: TOTAL | G2: Jan | H2: Feb | I2: Mar | J2: Apr | K2: May | L2: Jun | M2: July | N2: Aug | O2: Sep | P2: Oct | Q2: Nov | R2: Dec
A3: Various | B3: CONSULTING REVENUE | C3: =F3 -> 335686.39 | F3: =SUM(G3:R3) -> 335686.39 | G3: 0 | H3: 14642.86 | I3: 15000 | J3: 15000 | K3: 15000 | L3: 19276.36 | M3: 45348.54 | N3: 43020 | O3: 51406.16 | P3: 43020 | Q3: 42616.56 | R3: 31355.91
F4: YTD | G4: =G3 -> 0 | H4: =G4+H3 -> 14642.86 | I4: =H4+I3 -> 29642.86 | J4: =I4+J3 -> 44642.86 | K4: =J4+K3 -> 59642.86 | L4: =K4+L3 -> 78919.22 | M4: =L4+M3 -> 124267.76 | N4: =M4+N3 -> 167287.76 | O4: =N4+O3 -> 218693.92 | ... R4: =Q4+R3 -> 335686.39
B5: TOTAL EXPENSES | C5: =C7+C20+C27+C76+C35+C59+C45+C62+C67+C71 -> 1120.9717
B6: NET REVENUE | C6: =C3-C5 -> 334565.42
B7: UTILITIES | C7: =SUM(C8:C19) -> 448.9717 | D7: Prorated | E7: Rate | F7: Annual | G7: =SUM(G8:G19) -> 350.31 | H7: =SUM(H8:H19) -> 238.3 | I7: =SUM(I8:I19) -> 189.33 | J7: =SUM(J8:J19) -> 236.92 | K7: =SUM(K8:K19) -> 105.99 | L7: =SUM(L8:L19) -> 91.06 | M7: =SUM(M8:M19) -> 88.44 | N7: =SUM(N8:N19) -> 210.4 | ... R7: =SUM(R8:R19) -> 313.56
A8: PSE | B8: Electricity | C8: =D8 -> 380.358 | D8: =E8*F8 -> 380.358 | E8: 0.17 | F8: =SUM(G8:R8) -> 2237.4 | G8: 276.41 | H8: 238.3 | I8: 189.33 | J8: 144.27 | K8: 105.99 | L8: 91.06 | M8: 88.44 | N8: 109.39 | O8: 175.01 | P8: 230.13 | Q8: 275.51 | R8: 313.56
A9: City | B9: Waste & Recycle | C9: =D9 -> 68.6137 | D9: =E9*F9 -> 68.6137 | E9: 0.17 | F9: =SUM(G9:R9) -> 403.61 | G9: 73.9 | J9: 92.65 | N9: 101.01 | O9: 61.37 | P9: 74.68
A10: City | B10: Water & Sewer | C10: =D10 -> 0 | D10: =E10*F10 -> 0 | E10: 0.17 | F10: =SUM(G10:R10) -> 0
A11: ADT | B11: Security | C11: =D11 -> 0 | D11: =E11*F11 -> 0 | E11: 0.17 | F11: =SUM(G11:R11) -> 0
A12: Personal | B12: Landscaping | C12: =D12 -> 0 | D12: =E12*F12 -> 0 | E12: 0.17 | F12: =SUM(G12:R12) -> 0
B13: Home Owners Insurance | C13: =D13 -> 0 | D13: =E13*F13 -> 0 | E13: 0.17 | F13: =SUM(G13:R13) -> 0
A14: CCMSEARS | B14: Appliance Maintenance | C14: =D14 -> 0 | D14: =E14*F14 -> 0 | E14: 0.5 | F14: =SUM(G14:R14) -> 0
B15: Apple Warranty | C15: =D15 -> 0 | D15: =E15*F15 -> 0 | E15: 0.5 | F15: =SUM(G15:R15) -> 0
B16: Computers Warranty | C16: =D16 -> 0 | D16: =E16*F16 -> 0 | E16: 0.5 | F16: =SUM(G16:R16) -> 0
A17: T-Mobile | B17: Cellular Service | C17: =D17 -> 0 | D17: =E17*F17 -> 0 | E17: 0.5 | F17: =SUM(G17:R17) -> 0
A18: Comcast | B18: Broadband | C18: =D18 -> 0 | D18: =E18*F18 -> 0 | E18: 0.5 | F18: =SUM(G18:R18) -> 0
B19: TV Cable | C19: =D19 -> 0 | D19: =E19*F19 -> 0 | E19: 0.5 | F19: =SUM(G19:R19) -> 0
B20: DEPRECIABLE ASSETS | C20: =SUM(C21:C26) -> 0 | D20: Prorated | E20: Rate | F20: Annual | G20: =SUM(G21:G26) -> 0 | H20: =SUM(H21:H26) -> 0 | I20: =SUM(I21:I26) -> 0 | J20: =SUM(J21:J26) -> 0 | K20: =SUM(K21:K26) -> 0 | L20: =SUM(L21:L26) -> 0 | M20: =SUM(M21:M26) -> 0 | N20: =SUM(N21:N26) -> 0 | ... R20: =SUM(R21:R26) -> 0
B21: ASUS Laptop | C21: =D21 -> 0 | D21: =E21*F21 -> 0 | E21: 0.5 | F21: =SUM(G21:R21) -> 0
B22: Mobile Device (samsung) | C22: =D22 -> 0 | D22: =E22*F22 -> 0 | E22: 0.5 | F22: =SUM(G22:R22) -> 0
B23: Cellphone Device | C23: =D23 -> 0 | D23: =E23*F23 -> 0 | E23: 0.5 | F23: =SUM(G23:R23) -> 0
B24: Supplies | C24: =D24 -> 0 | D24: =E24*F24 -> 0 | E24: 1 | F24: =SUM(G24:R24) -> 0
B25: ='CB-18'!B25 -> Stationaries | C25: =D25 -> 0 | D25: =E25*F25 -> 0 | E25: 1 | F25: =SUM(G25:R25) -> 0
B26: Books | C26: =D26 -> 0 | D26: =E26*F26 -> 0 | E26: 1 | F26: =SUM(G26:R26) -> 0
B27: GOVERNMENT FEES | C27: =SUM(C28:C34) -> 0 | D27: Prorated | E27: Rate | F27: Annual | G27: =SUM(G28:G34) -> 0 | H27: =SUM(H28:H34) -> 0 | I27: =SUM(I28:I34) -> 0 | J27: =SUM(J28:J34) -> 0 | K27: =SUM(K28:K34) -> 0 | L27: =SUM(L28:L34) -> 0 | M27: =SUM(M28:M34) -> 0 | N27: =SUM(N28:N34) -> 0 | ... T27: =SUM(T28:T34) -> 0
A28: Olympia + KC + City | B28: Biz Registration | C28: =D28 -> 0 | D28: =E28*F28 -> 0 | E28: 1 | F28: =SUM(G28:R28) -> 0
A29: DOL | B29: Licensing | C29: =D29 -> 0 | D29: =E29*F29 -> 0 | E29: 1 | F29: =SUM(G29:R29) -> 0
B30: WA DOR Excise Tax | C30: =D30 -> 0 | D30: =E30*F30 -> 0 | E30: 1 | F30: =SUM(G30:R30) -> 0
B31: Garnishment Fee | C31: =D31 -> 0 | D31: =E31*F31 -> 0 | E31: 1 | F31: =SUM(G31:R31) -> 0
B32: LNI Insurance | C32: =D32 -> 0 | D32: =E32*F32 -> 0 | E32: 1 | F32: =SUM(G32:R32) -> 0
B33: WA Employment Security | C33: =D33 -> 0 | D33: =E33*F33 -> 0 | E33: 1 | F33: =SUM(G33:R33) -> 0
B34: Commercial Insurance | C34: =D34 -> 0 | D34: =E34*F34 -> 0 | E34: 1 | F34: =SUM(G34:R34) -> 0
B35: PROFESSIONAL SERVICES | C35: =SUM(C36:C44) -> 0 | D35: Prorated | E35: Rate | F35: Annual | G35: =SUM(G36:G44) -> 0 | H35: =SUM(H36:H44) -> 0 | I35: =SUM(I36:I44) -> 0 | J35: =SUM(J36:J44) -> 0 | K35: =SUM(K36:K44) -> 0 | L35: =SUM(L36:L44) -> 0 | M35: =SUM(M36:M44) -> 0 | N35: =SUM(N36:N44) -> 0 | ... R35: =SUM(R36:R44) -> 0
B36: Web Domains | C36: =D36 -> 0 | D36: =E36*F36 -> 0 | E36: 1 | F36: =SUM(G36:R36) -> 0
A37: GoDaddy | B37: Web Hosting | C37: =D37 -> 0 | D37: =E37*F37 -> 0 | E37: 1 | F37: =SUM(G37:R37) -> 0
B38: Digital Ads | C38: =D38 -> 0 | D38: =E38*F38 -> 0 | E38: 1 | F38: =SUM(G38:R38) -> 0
B39: Logo Services | C39: =D39 -> 0 | D39: =E39*F39 -> 0 | E39: 1 | F39: =SUM(G39:R39) -> 0
B40: Temp Services | C40: =D40 -> 0 | D40: =E40*F40 -> 0 | E40: 1 | F40: =SUM(G40:R40) -> 0
B41: Professional Services | C41: =D41 -> 0 | D41: =E41*F41 -> 0 | E41: 1 | F41: =SUM(G41:R41) -> 0
B42: Bank Fees | C42: =D42 -> 0 | D42: =E42*F42 -> 0 | E42: 1 | F42: =SUM(G42:R42) -> 0
B43: Legal Membership | C43: =D43 -> 0 | D43: =E43*F43 -> 0 | E43: 1 | F43: =SUM(G43:R43) -> 0
B44: Business Insurance | C44: =D44 -> 0 | D44: =E44*F44 -> 0 | E44: 1 | F44: =SUM(G44:R44) -> 0
B45: SUBSCRIPTIONS | C45: =SUM(C46:C58) -> 0 | D45: Prorated | E45: Rate | F45: Annual | G45: =SUM(G46:G58) -> 0 | H45: =SUM(H46:H58) -> 0 | I45: =SUM(I46:I58) -> 0 | J45: =SUM(J46:J58) -> 0 | K45: =SUM(K46:K58) -> 0 | L45: =SUM(L46:L58) -> 0 | M45: =SUM(M46:M58) -> 0 | N45: =SUM(N46:N58) -> 0 | ... R45: =SUM(R46:R58) -> 0
B46: Apple.com | C46: =D46 -> 0 | D46: =E46*F46 -> 0 | E46: 0.5 | F46: =SUM(G46:R46) -> 0
B47: Audible.com | C47: =D47 -> 0 | D47: =E47*F47 -> 0 | E47: 1 | F47: =SUM(G47:R47) -> 0
B48: Amazon | C48: =D48 -> 0 | D48: =E48*F48 -> 0 | E48: 0.5 | F48: =SUM(G48:R48) -> 0
B49: Cloud Academy | C49: =D49 -> 0 | D49: =E49*F49 -> 0 | E49: 1 | F49: =SUM(G49:R49) -> 0
B50: Packt | C50: =D50 -> 0 | D50: =E50*F50 -> 0 | E50: 1 | F50: =SUM(G50:R50) -> 0
B51: Pluralsight | C51: =D51 -> 0 | D51: =E51*F51 -> 0 | E51: 1 | F51: =SUM(G51:R51) -> 0
B52: Linux Academy | C52: =D52 -> 0 | D52: =E52*F52 -> 0 | E52: 1 | F52: =SUM(G52:R52) -> 0
B53: Adobe | C53: =D53 -> 0 | D53: =E53*F53 -> 0 | E53: 1 | F53: =SUM(G53:R53) -> 0
B54: O365 | C54: =D54 -> 0 | D54: =E54*F54 -> 0 | E54: 1 | F54: =SUM(G54:R54) -> 0
B55: Microsoft Alumni | C55: =D55 -> 0 | D55: =E55*F55 -> 0 | E55: 1 | F55: =SUM(G55:R55) -> 0
B56: LinkedIn | C56: =D56 -> 0 | D56: =E56*F56 -> 0 | E56: 1 | F56: =SUM(G56:R56) -> 0
B57: DOODLY | C57: =D57 -> 0 | D57: =E57*F57 -> 0 | E57: 1 | F57: =SUM(G57:R57) -> 0
B58: Whizlabs | C58: =D58 -> 0 | D58: =E58*F58 -> 0 | E58: 1 | F58: =SUM(G58:R58) -> 0
B59: AUTO MILEAGE | C59: =C60 -> 672 | D59: Prorated | E59: Rate | F59: Annual
B60: =B1&" IRS rate:" -> 2017 IRS rate: | C60: =D60 -> 672 | D60: =E60*F60 -> 672 | E60: 0.56 | F60: =SUM(G60:R60) -> 1200 | G60: 100 | H60: 100 | I60: 100 | J60: 100 | K60: 100 | L60: 100 | M60: 100 | N60: 100 | O60: 100 | P60: 100 | Q60: 100 | R60: 100
B61: SETUP EXPENSES
B62: WOODRIDGE OFFICE RENOVATION | C62: =SUM(C63:C66) -> 0 | D62: Prorated | E62: Rate | F62: Annual | G62: =SUM(G63:G66) -> 0 | H62: =SUM(H63:H66) -> 0 | I62: =SUM(I63:I66) -> 0 | J62: =SUM(J63:J66) -> 0 | K62: =SUM(K63:K66) -> 0 | L62: =SUM(L63:L66) -> 0 | M62: =SUM(M63:M66) -> 0 | N62: =SUM(N63:N66) -> 0 | ... R62: =SUM(R63:R66) -> 0
B63: Flooring | C63: =D63 -> 0 | D63: =E63*F63 -> 0 | E63: 1 | F63: =SUM(G63:R63) -> 0
B64: Paint | C64: =D64 -> 0 | D64: =E64*F64 -> 0 | E64: 1 | F64: =SUM(G64:R64) -> 0
B65: bathroom | C65: =D65 -> 0 | D65: =E65*F65 -> 0 | E65: 1 | F65: =SUM(G65:R65) -> 0
B66: electrical work | C66: =D66 -> 0 | D66: =E66*F66 -> 0 | E66: 1 | F66: =SUM(G66:R66) -> 0
B67: INDIA OFFICE RENOVATION | C67: =SUM(C68:C70) -> 0 | D67: Prorated | E67: Rate | F67: Annual | G67: =SUM(G68:G70) -> 0 | H67: =SUM(H68:H70) -> 0 | I67: =SUM(I68:I70) -> 0 | J67: =SUM(J68:J70) -> 0 | K67: =SUM(K68:K70) -> 0 | L67: =SUM(L68:L70) -> 0 | M67: =SUM(M68:M70) -> 0 | N67: =SUM(N68:N70) -> 0 | ... R67: =SUM(R68:R70) -> 0
B68: faucets | C68: =D68 -> 0 | D68: =E68*F68 -> 0 | E68: 1 | F68: =SUM(G68:R68) -> 0
B69: furniture | C69: =D69 -> 0 | D69: =E69*F69 -> 0 | E69: 1 | F69: =SUM(G69:R69) -> 0
B70: lights | C70: =D70 -> 0 | D70: =E70*F70 -> 0 | E70: 1 | F70: =SUM(G70:R70) -> 0
B71: INDIA OFFICE EXPENSES | C71: =SUM(C72:C75) -> 0 | D71: Prorated | E71: Rate | F71: Annual | G71: =SUM(G72:G75) -> 0 | H71: =SUM(H72:H75) -> 0 | I71: =SUM(I72:I75) -> 0 | J71: =SUM(J72:J75) -> 0 | K71: =SUM(K72:K75) -> 0 | L71: =SUM(L72:L75) -> 0 | M71: =SUM(M72:M75) -> 0 | N71: =SUM(N72:N75) -> 0 | ... R71: =SUM(R72:R75) -> 0
B72: electricity | C72: =D72 -> 0 | D72: =E72*F72 -> 0 | E72: 1 | F72: =SUM(G72:R72) -> 0
B73: taxes | C73: =D73 -> 0 | D73: =E73*F73 -> 0 | E73: 1 | F73: =SUM(G73:R73) -> 0
B74: cleaning | C74: =D74 -> 0 | D74: =E74*F74 -> 0 | E74: 1 | F74: =SUM(G74:R74) -> 0
B75: Staff | C75: =D75 -> 0 | D75: =E75*F75 -> 0 | E75: 1 | F75: =SUM(G75:R75) -> 0
B76: PAYROLL | C76: =SUM(C77:C80) -> 0 | D76: Prorated | E76: Rate | F76: Annual | G76: =SUM(G77:G80) -> 0 | H76: =SUM(H77:H80) -> 0 | I76: =SUM(I77:I80) -> 0 | J76: =SUM(J77:J80) -> 0 | K76: =SUM(K77:K80) -> 0 | L76: =SUM(L77:L80) -> 0 | M76: =SUM(M77:M80) -> 0 | N76: =SUM(N77:N80) -> 0 | ... R76: =SUM(R77:R80) -> 0
B77: W2 Ethan Rose | C77: =D77 -> 0 | D77: =E77*F77 -> 0 | E77: 1 | F77: =SUM(G77:R77) -> 0
B78: Fed 76.44; FICA 62; Medicare 14.5 | C78: =D78 -> 0 | D78: =E78*F78 -> 0 | E78: 1 | F78: =SUM(G78:R78) -> 0
B79: Zach DeVita | C79: =D79 -> 0 | D79: =E79*F79 -> 0 | E79: 1 | F79: =SUM(G79:R79) -> 0
B80: 1099 Shirish Sharma | C80: =D80 -> 0 | D80: =E80*F80 -> 0 | E80: 1 | F80: =SUM(G80:R80) -> 0

Sheet CC-24
C1: =Summary!G5 -> 2023 | G1: ="CHERRY CREST RENTAL " & C1 &" ONLY" -> CHERRY CREST RENTAL 2023 ONLY
F2: TOTAL | G2: Jan | H2: Feb | I2: Mar | J2: Apr | K2: May | L2: Jun | M2: July | N2: Aug | O2: Sep | P2: Oct | Q2: Nov | R2: Dec
C3: 1099 Revenue | F3: 26760 | G3: =$F$3/12 -> 2230 | H3: =$F$3/12 -> 2230 | I3: =$F$3/12 -> 2230 | J3: =$F$3/12 -> 2230 | K3: =$F$3/12 -> 2230 | L3: =$F$3/12 -> 2230 | M3: =$F$3/12 -> 2230 | N3: =$F$3/12 -> 2230 | ... R3: =$F$3/12 -> 2230
C5: Total Expenses | F5: =SUM(G5:R5) -> 5012.04 | G5: =SUM(G6:G22) -> 417.67 | H5: =SUM(H6:H22) -> 417.67 | I5: =SUM(I6:I22) -> 417.67 | J5: =SUM(J6:J22) -> 417.67 | K5: =SUM(K6:K22) -> 417.67 | L5: =SUM(L6:L22) -> 417.67 | M5: =SUM(M6:M22) -> 417.67 | N5: =SUM(N6:N22) -> 417.67 | ... R5: =SUM(R6:R22) -> 417.67
C6: Mortgage Interest | F6: =SUM(G6:R6) -> 0 | G6: 0 | H6: 0 | I6: 0 | J6: 0 | K6: 0 | L6: 0 | M6: 0 | N6: 0 | O6: 0 | P6: 0 | Q6: 0 | R6: 0
C7: Real-estate Taxes | F7: =SUM(G7:R7) -> 0
C8: Home Owners Insurance | F8: =SUM(G8:R8) -> 0
C9: HOA | F9: =SUM(G9:R9) -> 5012.04 | G9: 417.67 | H9: 417.67 | I9: 417.67 | J9: 417.67 | K9: 417.67 | L9: 417.67 | M9: 417.67 | N9: 417.67 | O9: 417.67 | P9: 417.67 | Q9: 417.67 | R9: 417.67
C10: Appliance Maintenance | F10: =SUM(G10:R10) -> 0
C11: Property Management | F11: =SUM(G11:R11) -> 0
C13: ELECTRICITY | F13: =SUM(G13:R13) -> 0
C14: WASTE | F14: =SUM(G14:R14) -> 0
C15: Water & Sewer | F15: =SUM(G15:R15) -> 0
C16: Security | F16: =SUM(G16:R16) -> 0
B17: xfiniti | C17: BROADBAND | F17: =SUM(G17:R17) -> 0
C19: Landscaping | F19: =SUM(G19:R19) -> 0
C20: Supplies | F20: =SUM(G20:R20) -> 0
B21: misc. | C21: Temp Services | F21: =SUM(G21:R21) -> 0
C22: Bank Fees | F22: =SUM(G22:R22) -> 0
C24: Flooring
C25: Paint
C26: bathroom
C27: electrical work | F27: =SUM(G27:R27) -> 0
C30: Gross Income | F30: =F3-F5 -> 21747.96

Sheet CC-23
C1: =Summary!G5 -> 2023 | G1: ="CHERRY CREST RENTAL " & C1 &" ONLY" -> CHERRY CREST RENTAL 2023 ONLY
F2: TOTAL | G2: Jan | H2: Feb | I2: Mar | J2: Apr | K2: May | L2: Jun | M2: July | N2: Aug | O2: Sep | P2: Oct | Q2: Nov | R2: Dec
C3: 1099 Revenue | F3: 26760 | G3: =$F$3/12 -> 2230 | H3: =$F$3/12 -> 2230 | I3: =$F$3/12 -> 2230 | J3: =$F$3/12 -> 2230 | K3: =$F$3/12 -> 2230 | L3: =$F$3/12 -> 2230 | M3: =$F$3/12 -> 2230 | N3: =$F$3/12 -> 2230 | ... R3: =$F$3/12 -> 2230
C5: Total Expenses | F5: =SUM(G5:R5) -> 5012.04 | G5: =SUM(G6:G22) -> 417.67 | H5: =SUM(H6:H22) -> 417.67 | I5: =SUM(I6:I22) -> 417.67 | J5: =SUM(J6:J22) -> 417.67 | K5: =SUM(K6:K22) -> 417.67 | L5: =SUM(L6:L22) -> 417.67 | M5: =SUM(M6:M22) -> 417.67 | N5: =SUM(N6:N22) -> 417.67 | ... R5: =SUM(R6:R22) -> 417.67
C6: Mortgage Interest | F6: =SUM(G6:R6) -> 0 | G6: 0 | H6: 0 | I6: 0 | J6: 0 | K6: 0 | L6: 0 | M6: 0 | N6: 0 | O6: 0 | P6: 0 | Q6: 0 | R6: 0
C7: Real-estate Taxes | F7: =SUM(G7:R7) -> 0
C8: Home Owners Insurance | F8: =SUM(G8:R8) -> 0
C9: HOA | F9: =SUM(G9:R9) -> 5012.04 | G9: 417.67 | H9: 417.67 | I9: 417.67 | J9: 417.67 | K9: 417.67 | L9: 417.67 | M9: 417.67 | N9: 417.67 | O9: 417.67 | P9: 417.67 | Q9: 417.67 | R9: 417.67
C10: Appliance Maintenance | F10: =SUM(G10:R10) -> 0
C11: Property Management | F11: =SUM(G11:R11) -> 0
C13: ELECTRICITY | F13: =SUM(G13:R13) -> 0
C14: WASTE | F14: =SUM(G14:R14) -> 0
C15: Water & Sewer | F15: =SUM(G15:R15) -> 0
C16: Security | F16: =SUM(G16:R16) -> 0
B17: xfiniti | C17: BROADBAND | F17: =SUM(G17:R17) -> 0
C19: Landscaping | F19: =SUM(G19:R19) -> 0
C20: Supplies | F20: =SUM(G20:R20) -> 0
B21: misc. | C21: Temp Services | F21: =SUM(G21:R21) -> 0
C22: Bank Fees | F22: =SUM(G22:R22) -> 0
C24: Flooring
C25: Paint
C26: bathroom
C27: electrical work | F27: =SUM(G27:R27) -> 0
C30: Gross Income | F30: =F3-F5 -> 21747.96

Sheet CC-22
C1: =Summary!H5 -> 2022 | G1: ="CHERRY CREST RENTAL " & C1 &" ONLY" -> CHERRY CREST RENTAL 2022 ONLY
F2: TOTAL | G2: Jan | H2: Feb | I2: Mar | J2: Apr | K2: May | L2: Jun | M2: July | N2: Aug | O2: Sep | P2: Oct | Q2: Nov | R2: Dec
C3: 1099 Revenue | F3: 26760 | G3: =$F$3/12 -> 2230 | H3: =$F$3/12 -> 2230 | I3: =$F$3/12 -> 2230 | J3: =$F$3/12 -> 2230 | K3: =$F$3/12 -> 2230 | L3: =$F$3/12 -> 2230 | M3: =$F$3/12 -> 2230 | N3: =$F$3/12 -> 2230 | ... R3: =$F$3/12 -> 2230
C5: Total Expenses | F5: =SUM(G5:R5) -> 5012.04 | G5: =SUM(G6:G22) -> 417.67 | H5: =SUM(H6:H22) -> 417.67 | I5: =SUM(I6:I22) -> 417.67 | J5: =SUM(J6:J22) -> 417.67 | K5: =SUM(K6:K22) -> 417.67 | L5: =SUM(L6:L22) -> 417.67 | M5: =SUM(M6:M22) -> 417.67 | N5: =SUM(N6:N22) -> 417.67 | ... R5: =SUM(R6:R22) -> 417.67
C6: Mortgage Interest | F6: =SUM(G6:R6) -> 0 | G6: 0 | H6: 0 | I6: 0 | J6: 0 | K6: 0 | L6: 0 | M6: 0 | N6: 0 | O6: 0 | P6: 0 | Q6: 0 | R6: 0
C7: Real-estate Taxes | F7: =SUM(G7:R7) -> 0
C8: Home Owners Insurance | F8: =SUM(G8:R8) -> 0
C9: HOA | F9: =SUM(G9:R9) -> 5012.04 | G9: 417.67 | H9: 417.67 | I9: 417.67 | J9: 417.67 | K9: 417.67 | L9: 417.67 | M9: 417.67 | N9: 417.67 | O9: 417.67 | P9: 417.67 | Q9: 417.67 | R9: 417.67
C10: Appliance Maintenance | F10: =SUM(G10:R10) -> 0
C11: Property Management | F11: =SUM(G11:R11) -> 0
C13: ELECTRICITY | F13: =SUM(G13:R13) -> 0
C14: WASTE | F14: =SUM(G14:R14) -> 0
C15: Water & Sewer | F15: =SUM(G15:R15) -> 0
C16: Security | F16: =SUM(G16:R16) -> 0
B17: xfiniti | C17: BROADBAND | F17: =SUM(G17:R17) -> 0
C19: Landscaping | F19: =SUM(G19:R19) -> 0
C20: Supplies | F20: =SUM(G20:R20) -> 0
B21: misc. | C21: Temp Services | F21: =SUM(G21:R21) -> 0
C22: Bank Fees | F22: =SUM(G22:R22) -> 0
C24: Flooring
C25: Paint
C26: bathroom
C27: electrical work | F27: =SUM(G27:R27) -> 0
C30: Gross Income | F30: =F3-F5 -> 21747.96

Sheet CC-21
B1: =Summary!I5 -> 2021 | F1: ="CHERRY CREST RENTAL " & B1 &" ONLY" -> CHERRY CREST RENTAL 2021 ONLY
E2: TOTAL | F2: Jan | G2: Feb | H2: Mar | I2: Apr | J2: May | K2: Jun | L2: July | M2: Aug | N2: Sep | O2: Oct | P2: Nov | Q2: Dec
B3: 1099 Revenue | E3: 26760 | F3: =$E$3/12 -> 2230 | G3: =$E$3/12 -> 2230 | H3: =$E$3/12 -> 2230 | I3: =$E$3/12 -> 2230 | J3: =$E$3/12 -> 2230 | K3: =$E$3/12 -> 2230 | L3: =$E$3/12 -> 2230 | M3: =$E$3/12 -> 2230 | ... Q3: =$E$3/12 -> 2230
B5: Total Expenses | E5: =SUM(F5:Q5) -> 5012.04 | F5: =SUM(F6:F22) -> 417.67 | G5: =SUM(G6:G22) -> 417.67 | H5: =SUM(H6:H22) -> 417.67 | I5: =SUM(I6:I22) -> 417.67 | J5: =SUM(J6:J22) -> 417.67 | K5: =SUM(K6:K22) -> 417.67 | L5: =SUM(L6:L22) -> 417.67 | M5: =SUM(M6:M22) -> 417.67 | ... Q5: =SUM(Q6:Q22) -> 417.67
B6: Mortgage Interest | E6: =SUM(F6:Q6) -> 0 | F6: 0 | G6: 0 | H6: 0 | I6: 0 | J6: 0 | K6: 0 | L6: 0 | M6: 0 | N6: 0 | O6: 0 | P6: 0 | Q6: 0
B7: Real-estate Taxes | E7: =SUM(F7:Q7) -> 0
B8: Home Owners Insurance | E8: =SUM(F8:Q8) -> 0
B9: HOA | E9: =SUM(F9:Q9) -> 5012.04 | F9: 417.67 | G9: 417.67 | H9: 417.67 | I9: 417.67 | J9: 417.67 | K9: 417.67 | L9: 417.67 | M9: 417.67 | N9: 417.67 | O9: 417.67 | P9: 417.67 | Q9: 417.67
B10: Appliance Maintenance | E10: =SUM(F10:Q10) -> 0
B11: Property Management | E11: =SUM(F11:Q11) -> 0
B13: ELECTRICITY | E13: =SUM(F13:Q13) -> 0
B14: WASTE | E14: =SUM(F14:Q14) -> 0
B15: Water & Sewer | E15: =SUM(F15:Q15) -> 0
B16: Security | E16: =SUM(F16:Q16) -> 0
A17: xfiniti | B17: BROADBAND | E17: =SUM(F17:Q17) -> 0
B19: Landscaping | E19: =SUM(F19:Q19) -> 0
B20: Supplies | E20: =SUM(F20:Q20) -> 0
A21: misc. | B21: Temp Services | E21: =SUM(F21:Q21) -> 0
B22: Bank Fees | E22: =SUM(F22:Q22) -> 0
B24: Flooring
B25: Paint
B26: bathroom
B27: electrical work | E27: =SUM(F27:Q27) -> 0
B30: Gross Income | E30: =E3-E5 -> 21747.96

Sheet CC-20
B1: =Summary!J5 -> 2020 | G1: ="CHERRY CREST RENTAL " & B1 &" ONLY" -> CHERRY CREST RENTAL 2020 ONLY
F2: TOTAL | G2: Jan | H2: Feb | I2: Mar | J2: Apr | K2: May | L2: Jun | M2: July | N2: Aug | O2: Sep | P2: Oct | Q2: Nov | R2: Dec
B3: Rental Revenue | F3: =SUM(G3:R3) -> 0
F4: YTD | G4: =G3 -> 0
B5: Total Expenses | F5: =SUM(G5:R5) -> 0
B6: Ratio of Home Use | C6: 0.17
B7: Mortgage Interest | F7: =SUM(G7:R7) -> 0
B8: ELECTRICITY | F8: =SUM(G8:R8) -> 0
B9: WASTE | F9: =SUM(G9:R9) -> 0
B10: Water | F10: =SUM(G10:R10) -> 0
B11: Security | F11: =SUM(G11:R11) -> 0
B12: Landscaping | F12: =SUM(G12:R12) -> 0
B13: Home Owners Insurance | F13: =SUM(G13:R13) -> 0
B15: Real-estate Taxes | F15: =2072.25+2794.1+2860.9+3286.48 -> 11013.73
B17: Supplies | F17: =SUM(G17:R17) -> 0
B18: STATIONARIES | F18: =SUM(G18:R18) -> 0
A19: misc. | B19: Temp Services | F19: =SUM(G19:R19) -> 0
B20: Professional Services | F20: =SUM(G20:R20) -> 0
F21: =SUM(G21:R21) -> 0
B22: Flooring | F22: =SUM(G22:R22) -> 0
B23: Paint | F23: =SUM(G23:R23) -> 0
B24: bathroom | F24: =SUM(G24:R24) -> 0
B25: electrical work | F25: 800
B27: Auto Mileage (client visits)
B28: =B1&" IRS rate" -> 2020 IRS rate | C28: 0.545 | F28: =SUM(G28:R28) -> 0
F29: =SUM(G29:R29) -> 0

Sheet CC-19
B1: 2019 | F1: ="CHERRY CREST RENTAL " & B1 &" ONLY" -> CHERRY CREST RENTAL 2019 ONLY
E2: TOTAL | F2: Jan | G2: Feb | H2: Mar | I2: Apr | J2: May | K2: Jun | L2: July | M2: Aug | N2: Sep | O2: Oct | P2: Nov | Q2: Dec | S2: Check# | T2: Amount | U2: Date | V2: Payee
B3: Rental Revenue | E3: =SUM(F3:Q3) -> 0 | F3: 0 | G3: 0 | H3: 0 | I3: 0 | J3: 0 | K3: 0 | L3: 0 | M3: 0 | N3: 0 | O3: 0 | P3: 0 | Q3: 0 | S3: 3032 | T3: 19 | U3: jan | V3: DOR
E4: YTD | F4: =F3 -> 0 | S4: 3033 | T4: 500 | U4: jan | V4: Edilberto
B5: Total Expenses | E5: =SUM(F5:Q5) -> 35434.59 | F5: =SUM(F8:F30) -> 5092.1 | G5: =SUM(G8:G30) -> 417.67 | H5: =SUM(H8:H30) -> 2266.25 | I5: =SUM(I8:I30) -> 5511.67 | J5: =SUM(J8:J30) -> 2350.67 | K5: =SUM(K8:K30) -> 5233.73 | L5: =SUM(L8:L30) -> 1981.67 | M5: =SUM(M8:M30) -> 1668.67 | ... Q5: =SUM(Q8:Q30) -> 9359.15 | S5: 3034 | T5: 1269 | U5: jan | V5: Deepika
B6: Ratio of Home Use | C6: 0.17 | S6: 3035 | T6: 1000 | U6: jan | V6: edilberto
B7: Mortgage Interest | E7: =SUM(F7:Q7) -> 0 | S7: 3036 | U7: jan | V7: edilberto
B8: ELECTRICITY | E8: =SUM(F8:Q8) -> 0 | F8: 0 | G8: 0 | H8: 0 | I8: 0 | J8: 0 | K8: 0 | L8: 0 | M8: 0 | N8: 0 | O8: 0 | P8: 0 | Q8: 0 | S8: 3036 | T8: 500 | U8: jan | V8: edilberto
B9: WASTE | E9: =SUM(F9:Q9) -> 0 | F9: 0 | G9: 0 | H9: 0 | I9: 0 | J9: 0 | K9: 0 | L9: 0 | M9: 0 | N9: 0 | O9: 0 | P9: 0 | Q9: 0 | S9: 3577 | T9: 300 | U9: jan | V9: SEARS
B10: Water | E10: =SUM(F10:Q10) -> 0 | F10: 0 | G10: 0 | H10: 0 | I10: 0 | J10: 0 | K10: 0 | L10: 0 | M10: 0 | N10: 0 | O10: 0 | P10: 0 | Q10: 0 | S10: 9910 | T10: 135 | U10: jan | V10: BoA
B11: Security | E11: =SUM(F11:Q11) -> 0 | S11: 9911 | T11: 135 | U11: jan | V11: BoA
B12: Landscaping | E12: =SUM(F12:Q12) -> 0 | S12: 3011 | T12: 2000 | U12: feb
B13: Home Owners Insurance | E13: =SUM(F13:Q13) -> 0 | S13: 3578 | T13: 300 | U13: feb
B14: HoA Dues | E14: =SUM(F14:Q14) -> 5012.04 | F14: 417.67 | G14: 417.67 | H14: 417.67 | I14: 417.67 | J14: 417.67 | K14: 417.67 | L14: 417.67 | M14: 417.67 | N14: 417.67 | O14: 417.67 | P14: 417.67 | Q14: 417.67 | S14: 3012 | T14: 1848.58 | U14: 44646 | V14: Plumbing
B15: Real-estate Taxes | E15: =SUM(F15:Q15) -> 11013.73 | K15: 2072.25 | Q15: =2794.1+2860.9+3286.48 -> 8941.48 | S15: 3579 | T15: 300 | U15: 44625 | V15: SEARS
S16: 9912 | T16: 135 | U16: 44621 | V16: BoA
B17: Supplies | E17: =SUM(F17:Q17) -> 0 | S17: 9913 | T17: 135 | U17: 44643 | V17: BoA
B18: STATIONARIES | E18: =SUM(F18:Q18) -> 0 | S18: 3013 | T18: 694 | U18: 44654 | V18: Edilberto
A19: misc. | B19: Temp Services | E19: =SUM(F19:Q19) -> 7148 | F19: =T4+T6+T8 -> 2000 | I19: =T18 -> 694 | K19: =T31+T32+T33+T34 -> 1339 | L19: =T37+T38+T39 -> 1564 | M19: =T42+T43+T44+T45 -> 1251 | N19: =T48+T49 -> 300 | S19: 3014 | T19: 3100 | U19: 44669 | V19: concrete
B20: Professional Services | E20: =SUM(F20:Q20) -> 0 | S20: 3037 | T20: 1000 | U20: 44656 | V20: bathroom
E21: =SUM(F21:Q21) -> 0 | S21: 3038 | T21: 300 | U21: 44662 | V21: paint
B22: Flooring | E22: =SUM(F22:Q22) -> 5604.81 | F22: 1100 | I22: =T19 -> 3100 | K22: 1404.81 | S22: 3580 | T22: 300 | U22: 44654 | V22: SEARS
B23: Paint | E23: =SUM(F23:Q23) -> 300 | I23: =T21 -> 300 | S23: 9914 | T23: 200 | U23: 44669 | V23: BoA
B24: bathroom | E24: =SUM(F24:Q24) -> 2574.43 | F24: 1574.43 | I24: =T20 -> 1000 | S24: 3015 | T24: 200 | U24: 44683
B25: electrical work | E25: =SUM(F25:Q25) -> 1825 | J25: =Table13[[#This Row],[Amount]]+T26 -> 1825 | S25: 3017 | T25: 900 | U25: 44688 | V25: hector hickman
B26: Plumbing | H26: =T14 -> 1848.58 | J26: =T27 -> 108 | S26: 3018 | T26: 925 | U26: 44688 | V26: hector hickman
B27: Auto Mileage (client visits) | S27: 3039 | T27: 108 | U27: 44712 | V27: Plumbing
B28: 2019 IRS rate | C28: 0.545 | E28: =SUM(F28:Q28) -> 0 | S28: 3581 | T28: 300 | U28: 44684 | V28: SEARS
E29: =SUM(F29:Q29) -> 0 | S29: 9915 | T29: 200 | U29: 44699 | V29: BoA
S30: 3019 | T30: 2072.25 | U30: 44733 | V30: king county treasury
S31: 3020 | T31: 206 | U31: 44732 | V31: Edilberto
S32: 3040 | T32: 400 | U32: 44716 | V32: Edilberto
S33: 3041 | T33: 433 | U33: 44718 | V33: Edilberto
S34: 3042 | T34: 300 | U34: 44723 | V34: Edilberto
S35: 3582 | T35: 300 | U35: 44716 | V35: SEARS
S36: 9916 | T36: 200 | U36: 44731 | V36: BoA
S37: 3021 | T37: 435 | U37: 44761 | V37: Edilberto
S38: 3043 | T38: 799 | U38: 44745 | V38: Edilberto
S39: 3044 | T39: 330 | U39: 44766 | V39: Edilberto
S40: 3583 | T40: 300 | U40: 44745 | V40: SEARS
S41: 9917 | T41: 200 | U41: 44760 | V41: BoA
... S60: 9922 | T60: 200 | U60: 44913 | V60: BoA

Sheet CC-18
B1: =Summary!L5 -> 2018 | F1: ="CHERRY CREST RENTAL " & B1 &" ONLY" -> CHERRY CREST RENTAL 2018 ONLY
E2: TOTAL | F2: Jan | G2: Feb | H2: Mar | I2: Apr | J2: May | K2: Jun | L2: July | M2: Aug | N2: Sep | O2: Oct | P2: Nov | Q2: Dec | S2: Check# | T2: Amount | U2: Date | V2: Payee
B3: Rental Revenue | E3: =SUM(F3:Q3) -> 0 | F3: 0 | G3: 0 | H3: 0 | I3: 0 | J3: 0 | K3: 0 | L3: 0 | M3: 0 | N3: 0 | O3: 0 | P3: 0 | Q3: 0 | S3: 3032 | T3: 19 | U3: jan | V3: DOR
E4: YTD | F4: =F3 -> 0 | S4: 3033 | T4: 500 | U4: jan | V4: Edilberto
B5: Total Expenses | E5: =SUM(F5:Q5) -> 35434.59 | F5: =SUM(F8:F30) -> 5092.1 | G5: =SUM(G8:G30) -> 417.67 | H5: =SUM(H8:H30) -> 2266.25 | I5: =SUM(I8:I30) -> 5511.67 | J5: =SUM(J8:J30) -> 2350.67 | K5: =SUM(K8:K30) -> 5233.73 | L5: =SUM(L8:L30) -> 1981.67 | M5: =SUM(M8:M30) -> 1668.67 | ... Q5: =SUM(Q8:Q30) -> 9359.15 | S5: 3034 | T5: 1269 | U5: jan | V5: Deepika
B6: Ratio of Home Use | C6: 0.17 | S6: 3035 | T6: 1000 | U6: jan | V6: edilberto
B7: Mortgage Interest | E7: =SUM(F7:Q7) -> 0 | S7: 3036 | U7: jan | V7: edilberto
B8: ELECTRICITY | E8: =SUM(F8:Q8) -> 0 | F8: 0 | G8: 0 | H8: 0 | I8: 0 | J8: 0 | K8: 0 | L8: 0 | M8: 0 | N8: 0 | O8: 0 | P8: 0 | Q8: 0 | S8: 3036 | T8: 500 | U8: jan | V8: edilberto
B9: WASTE | E9: =SUM(F9:Q9) -> 0 | F9: 0 | G9: 0 | H9: 0 | I9: 0 | J9: 0 | K9: 0 | L9: 0 | M9: 0 | N9: 0 | O9: 0 | P9: 0 | Q9: 0 | S9: 3577 | T9: 300 | U9: jan | V9: SEARS
B10: Water | E10: =SUM(F10:Q10) -> 0 | F10: 0 | G10: 0 | H10: 0 | I10: 0 | J10: 0 | K10: 0 | L10: 0 | M10: 0 | N10: 0 | O10: 0 | P10: 0 | Q10: 0 | S10: 9910 | T10: 135 | U10: jan | V10: BoA
B11: Security | E11: =SUM(F11:Q11) -> 0 | S11: 9911 | T11: 135 | U11: jan | V11: BoA
B12: Landscaping | E12: =SUM(F12:Q12) -> 0 | S12: 3011 | T12: 2000 | U12: feb
B13: Home Owners Insurance | E13: =SUM(F13:Q13) -> 0 | S13: 3578 | T13: 300 | U13: feb
B14: HoA Dues | E14: =SUM(F14:Q14) -> 5012.04 | F14: 417.67 | G14: 417.67 | H14: 417.67 | I14: 417.67 | J14: 417.67 | K14: 417.67 | L14: 417.67 | M14: 417.67 | N14: 417.67 | O14: 417.67 | P14: 417.67 | Q14: 417.67 | S14: 3012 | T14: 1848.58 | U14: 44646 | V14: Plumbing
B15: Real-estate Taxes | E15: =SUM(F15:Q15) -> 11013.73 | K15: 2072.25 | Q15: =2794.1+2860.9+3286.48 -> 8941.48 | S15: 3579 | T15: 300 | U15: 44625 | V15: SEARS
S16: 9912 | T16: 135 | U16: 44621 | V16: BoA
B17: Supplies | E17: =SUM(F17:Q17) -> 0 | S17: 9913 | T17: 135 | U17: 44643 | V17: BoA
B18: STATIONARIES | E18: =SUM(F18:Q18) -> 0 | S18: 3013 | T18: 694 | U18: 44654 | V18: Edilberto
A19: misc. | B19: Temp Services | E19: =SUM(F19:Q19) -> 7148 | F19: =T4+T6+T8 -> 2000 | I19: =T18 -> 694 | K19: =T31+T32+T33+T34 -> 1339 | L19: =T37+T38+T39 -> 1564 | M19: =T42+T43+T44+T45 -> 1251 | N19: =T48+T49 -> 300 | S19: 3014 | T19: 3100 | U19: 44669 | V19: concrete
B20: Professional Services | E20: =SUM(F20:Q20) -> 0 | S20: 3037 | T20: 1000 | U20: 44656 | V20: bathroom
E21: =SUM(F21:Q21) -> 0 | S21: 3038 | T21: 300 | U21: 44662 | V21: paint
B22: Flooring | E22: =SUM(F22:Q22) -> 5604.81 | F22: 1100 | I22: =T19 -> 3100 | K22: 1404.81 | S22: 3580 | T22: 300 | U22: 44654 | V22: SEARS
B23: Paint | E23: =SUM(F23:Q23) -> 300 | I23: =T21 -> 300 | S23: 9914 | T23: 200 | U23: 44669 | V23: BoA
B24: bathroom | E24: =SUM(F24:Q24) -> 2574.43 | F24: 1574.43 | I24: =T20 -> 1000 | S24: 3015 | T24: 200 | U24: 44683
B25: electrical work | E25: =SUM(F25:Q25) -> 1825 | J25: =Table1[[#This Row],[Amount]]+T26 -> 1825 | S25: 3017 | T25: 900 | U25: 44688 | V25: hector hickman
B26: Plumbing | H26: =T14 -> 1848.58 | J26: =T27 -> 108 | S26: 3018 | T26: 925 | U26: 44688 | V26: hector hickman
B27: Auto Mileage (client visits) | S27: 3039 | T27: 108 | U27: 44712 | V27: Plumbing
B28: 2018 IRS rate | C28: 0.545 | E28: =SUM(F28:Q28) -> 0 | S28: 3581 | T28: 300 | U28: 44684 | V28: SEARS
E29: =SUM(F29:Q29) -> 0 | S29: 9915 | T29: 200 | U29: 44699 | V29: BoA
S30: 3019 | T30: 2072.25 | U30: 44733 | V30: king county treasury
S31: 3020 | T31: 206 | U31: 44732 | V31: Edilberto
S32: 3040 | T32: 400 | U32: 44716 | V32: Edilberto
S33: 3041 | T33: 433 | U33: 44718 | V33: Edilberto
S34: 3042 | T34: 300 | U34: 44723 | V34: Edilberto
S35: 3582 | T35: 300 | U35: 44716 | V35: SEARS
S36: 9916 | T36: 200 | U36: 44731 | V36: BoA
S37: 3021 | T37: 435 | U37: 44761 | V37: Edilberto
S38: 3043 | T38: 799 | U38: 44745 | V38: Edilberto
S39: 3044 | T39: 330 | U39: 44766 | V39: Edilberto
S40: 3583 | T40: 300 | U40: 44745 | V40: SEARS
S41: 9917 | T41: 200 | U41: 44760 | V41: BoA
... S60: 9922 | T60: 200 | U60: 44913 | V60: BoA

Sheet OC-23
D1: =Summary!G5 -> 2023 | I1: ="Olympic Court Condo "&D1&" ONLY" -> Olympic Court Condo 2023 ONLY
H2: TOTAL | I2: Jan | J2: Feb | K2: Mar | L2: Apr | M2: May | N2: Jun | O2: July | P2: Aug | Q2: Sep | R2: Oct | S2: Nov | T2: Dec
D3: Rental Revenue (CAD) | H3: =SUM(I3:T3) -> 10220 | I3: 0 | J3: 0 | K3: 0 | L3: 0 | M3: 0 | N3: 1460 | O3: 1460 | P3: 1460 | Q3: 1460 | R3: 1460 | S3: 1460 | T3: 1460
D5: Total Expenses | H5: =SUM(I5:T5) -> 7200.64 | I5: =SUM(I6:I33) -> 1381.72 | J5: =SUM(J6:J33) -> 181.72 | K5: =SUM(K6:K33) -> 181.72 | L5: =SUM(L6:L33) -> 181.72 | M5: =SUM(M6:M33) -> 181.72 | N5: =SUM(N6:N33) -> 3041.72 | O5: =SUM(O6:O33) -> 341.72 | P5: =SUM(P6:P33) -> 341.72 | ... T5: =SUM(T6:T33) -> 341.72
D6: Mortgage Interest | H6: =SUM(I6:T6) -> 0
D7: Home Owners Insurance | H7: =SUM(I7:T7) -> 1200 | I7: 1200
D8: HoA | H8: =SUM(I8:T8) -> 2180.64 | I8: 181.72 | J8: 181.72 | K8: 181.72 | L8: 181.72 | M8: 181.72 | N8: 181.72 | O8: 181.72 | P8: 181.72 | Q8: 181.72 | R8: 181.72 | S8: 181.72 | T8: 181.72
D9: Supplies | H9: =SUM(I9:T9) -> 0
D10: PAYROLL | H10: =SUM(I10:T10) -> 0
D11: W2 Ethan Rose | H11: =SUM(I11:T11) -> 0
D12: Fed 76.44; FICA 62; Medicare 14.5 | H12: =SUM(I12:T12) -> 0
D13: Zach DeVita | H13: =SUM(I13:T13) -> 0
D14: 1099 Shirish Sharma | H14: =SUM(I14:T14) -> 0
B16: misc. | D16: Temp Services | H16: =SUM(I16:T16) -> 700 | N16: 700
D17: Professional Services | H17: =SUM(I17:T17) -> 1120 | I17: 0 | J17: 0 | K17: 0 | L17: 0 | M17: 0 | N17: 160 | O17: 160 | P17: 160 | Q17: 160 | R17: 160 | S17: 160 | T17: 160
D18: Bank Fees | H18: =SUM(I18:T18) -> 0
D19: Business Insurance | H19: =SUM(I19:T19) -> 0
D20: Auto Mileage (condo visits) | H20: =SUM(I20:T20) -> 0
D21: =D1&" IRS rate" -> 2023 IRS rate | E21: 0.56 | H21: =SUM(I21:T21) -> 0
H22: =SUM(I22:T22) -> 0
D23: Flooring | H23: =SUM(I23:T23) -> 0
D24: Paint | H24: =SUM(I24:T24) -> 0
D25: bathroom | H25: =SUM(I25:T25) -> 0
D26: electrical work | H26: =SUM(I26:T26) -> 0
D27: Paint & Repairs | H27: =SUM(I27:T27) -> 2000 | N27: 2000
H28: =SUM(I28:T28) -> 0
H29: =SUM(I29:T29) -> 0
H30: =SUM(I30:T30) -> 0
H31: =SUM(I31:T31) -> 0

Sheet OC-22
D1: =Summary!H5 -> 2022 | I1: ="Olympic Court Condo "&D1&" ONLY" -> Olympic Court Condo 2022 ONLY
H2: TOTAL | I2: Jan | J2: Feb | K2: Mar | L2: Apr | M2: May | N2: Jun | O2: July | P2: Aug | Q2: Sep | R2: Oct | S2: Nov | T2: Dec
D3: Rental Revenue (CAD) | H3: =SUM(I3:T3) -> 10220 | I3: 0 | J3: 0 | K3: 0 | L3: 0 | M3: 0 | N3: 1460 | O3: 1460 | P3: 1460 | Q3: 1460 | R3: 1460 | S3: 1460 | T3: 1460
D5: Total Expenses | H5: =SUM(I5:T5) -> 7200.64 | I5: =SUM(I6:I33) -> 1381.72 | J5: =SUM(J6:J33) -> 181.72 | K5: =SUM(K6:K33) -> 181.72 | L5: =SUM(L6:L33) -> 181.72 | M5: =SUM(M6:M33) -> 181.72 | N5: =SUM(N6:N33) -> 3041.72 | O5: =SUM(O6:O33) -> 341.72 | P5: =SUM(P6:P33) -> 341.72 | ... T5: =SUM(T6:T33) -> 341.72
D6: Mortgage Interest | H6: =SUM(I6:T6) -> 0
D7: Home Owners Insurance | H7: =SUM(I7:T7) -> 1200 | I7: 1200
D8: HoA | H8: =SUM(I8:T8) -> 2180.64 | I8: 181.72 | J8: 181.72 | K8: 181.72 | L8: 181.72 | M8: 181.72 | N8: 181.72 | O8: 181.72 | P8: 181.72 | Q8: 181.72 | R8: 181.72 | S8: 181.72 | T8: 181.72
D9: Supplies | H9: =SUM(I9:T9) -> 0
D10: PAYROLL | H10: =SUM(I10:T10) -> 0
D11: W2 Ethan Rose | H11: =SUM(I11:T11) -> 0
D12: Fed 76.44; FICA 62; Medicare 14.5 | H12: =SUM(I12:T12) -> 0
D13: Zach DeVita | H13: =SUM(I13:T13) -> 0
D14: 1099 Shirish Sharma | H14: =SUM(I14:T14) -> 0
B16: misc. | D16: Temp Services | H16: =SUM(I16:T16) -> 700 | N16: 700
D17: Professional Services | H17: =SUM(I17:T17) -> 1120 | I17: 0 | J17: 0 | K17: 0 | L17: 0 | M17: 0 | N17: 160 | O17: 160 | P17: 160 | Q17: 160 | R17: 160 | S17: 160 | T17: 160
D18: Bank Fees | H18: =SUM(I18:T18) -> 0
D19: Business Insurance | H19: =SUM(I19:T19) -> 0
D20: Auto Mileage (condo visits) | H20: =SUM(I20:T20) -> 0
D21: =D1&" IRS rate" -> 2022 IRS rate | E21: 0.56 | H21: =SUM(I21:T21) -> 0
H22: =SUM(I22:T22) -> 0
D23: Flooring | H23: =SUM(I23:T23) -> 0
D24: Paint | H24: =SUM(I24:T24) -> 0
D25: bathroom | H25: =SUM(I25:T25) -> 0
D26: electrical work | H26: =SUM(I26:T26) -> 0
D27: Paint & Repairs | H27: =SUM(I27:T27) -> 2000 | N27: 2000
H28: =SUM(I28:T28) -> 0
H29: =SUM(I29:T29) -> 0
H30: =SUM(I30:T30) -> 0
H31: =SUM(I31:T31) -> 0

Sheet OC-21
D1: =Summary!I5 -> 2021 | I1: ="Olympic Court Condo "&D1&" ONLY" -> Olympic Court Condo 2021 ONLY
H2: TOTAL | I2: Jan | J2: Feb | K2: Mar | L2: Apr | M2: May | N2: Jun | O2: July | P2: Aug | Q2: Sep | R2: Oct | S2: Nov | T2: Dec
D3: Rental Revenue (CAD) | H3: =SUM(I3:T3) -> 10220 | I3: 0 | J3: 0 | K3: 0 | L3: 0 | M3: 0 | N3: 1460 | O3: 1460 | P3: 1460 | Q3: 1460 | R3: 1460 | S3: 1460 | T3: 1460
D5: Total Expenses | H5: =SUM(I5:T5) -> 7200.64 | I5: =SUM(I6:I33) -> 1381.72 | J5: =SUM(J6:J33) -> 181.72 | K5: =SUM(K6:K33) -> 181.72 | L5: =SUM(L6:L33) -> 181.72 | M5: =SUM(M6:M33) -> 181.72 | N5: =SUM(N6:N33) -> 3041.72 | O5: =SUM(O6:O33) -> 341.72 | P5: =SUM(P6:P33) -> 341.72 | ... T5: =SUM(T6:T33) -> 341.72
D6: Mortgage Interest | H6: =SUM(I6:T6) -> 0
D7: Home Owners Insurance | H7: =SUM(I7:T7) -> 1200 | I7: 1200
D8: HoA | H8: =SUM(I8:T8) -> 2180.64 | I8: 181.72 | J8: 181.72 | K8: 181.72 | L8: 181.72 | M8: 181.72 | N8: 181.72 | O8: 181.72 | P8: 181.72 | Q8: 181.72 | R8: 181.72 | S8: 181.72 | T8: 181.72
D9: Supplies | H9: =SUM(I9:T9) -> 0
D10: PAYROLL | H10: =SUM(I10:T10) -> 0
D11: W2 Ethan Rose | H11: =SUM(I11:T11) -> 0
D12: Fed 76.44; FICA 62; Medicare 14.5 | H12: =SUM(I12:T12) -> 0
D13: Zach DeVita | H13: =SUM(I13:T13) -> 0
D14: 1099 Shirish Sharma | H14: =SUM(I14:T14) -> 0
B16: misc. | D16: Temp Services | H16: =SUM(I16:T16) -> 700 | N16: 700
D17: Professional Services | H17: =SUM(I17:T17) -> 1120 | I17: 0 | J17: 0 | K17: 0 | L17: 0 | M17: 0 | N17: 160 | O17: 160 | P17: 160 | Q17: 160 | R17: 160 | S17: 160 | T17: 160
D18: Bank Fees | H18: =SUM(I18:T18) -> 0
D19: Business Insurance | H19: =SUM(I19:T19) -> 0
D20: Auto Mileage (condo visits) | H20: =SUM(I20:T20) -> 0
D21: =D1&" IRS rate" -> 2021 IRS rate | E21: 0.56 | H21: =SUM(I21:T21) -> 0
H22: =SUM(I22:T22) -> 0
D23: Flooring | H23: =SUM(I23:T23) -> 0
D24: Paint | H24: =SUM(I24:T24) -> 0
D25: bathroom | H25: =SUM(I25:T25) -> 0
D26: electrical work | H26: =SUM(I26:T26) -> 0
D27: Paint & Repairs | H27: =SUM(I27:T27) -> 2000 | N27: 2000
H28: =SUM(I28:T28) -> 0
H29: =SUM(I29:T29) -> 0
H30: =SUM(I30:T30) -> 0
H31: =SUM(I31:T31) -> 0

Sheet OC-20
D1: =Summary!J5 -> 2020 | I1: ="Olympic Court Condo "&D1&" ONLY" -> Olympic Court Condo 2020 ONLY
H2: TOTAL | I2: Jan | J2: Feb | K2: Mar | L2: Apr | M2: May | N2: Jun | O2: July | P2: Aug | Q2: Sep | R2: Oct | S2: Nov | T2: Dec
D3: Rental Revenue (CAD) | H3: =SUM(I3:T3) -> 10220 | I3: 0 | J3: 0 | K3: 0 | L3: 0 | M3: 0 | N3: 1460 | O3: 1460 | P3: 1460 | Q3: 1460 | R3: 1460 | S3: 1460 | T3: 1460
D5: Total Expenses | H5: =SUM(I5:T5) -> 7200.64 | I5: =SUM(I6:I33) -> 1381.72 | J5: =SUM(J6:J33) -> 181.72 | K5: =SUM(K6:K33) -> 181.72 | L5: =SUM(L6:L33) -> 181.72 | M5: =SUM(M6:M33) -> 181.72 | N5: =SUM(N6:N33) -> 3041.72 | O5: =SUM(O6:O33) -> 341.72 | P5: =SUM(P6:P33) -> 341.72 | ... T5: =SUM(T6:T33) -> 341.72
D6: Mortgage Interest | H6: =SUM(I6:T6) -> 0
D7: Home Owners Insurance | H7: =SUM(I7:T7) -> 1200 | I7: 1200
D8: HoA | H8: =SUM(I8:T8) -> 2180.64 | I8: 181.72 | J8: 181.72 | K8: 181.72 | L8: 181.72 | M8: 181.72 | N8: 181.72 | O8: 181.72 | P8: 181.72 | Q8: 181.72 | R8: 181.72 | S8: 181.72 | T8: 181.72
D9: Supplies | H9: =SUM(I9:T9) -> 0
D10: PAYROLL | H10: =SUM(I10:T10) -> 0
D11: W2 Ethan Rose | H11: =SUM(I11:T11) -> 0
D12: Fed 76.44; FICA 62; Medicare 14.5 | H12: =SUM(I12:T12) -> 0
D13: Zach DeVita | H13: =SUM(I13:T13) -> 0
D14: 1099 Shirish Sharma | H14: =SUM(I14:T14) -> 0
H15: =SUM(I15:T15) -> 0
B16: misc. | D16: Temp Services | H16: =SUM(I16:T16) -> 700 | N16: 700
D17: Professional Services | H17: =SUM(I17:T17) -> 1120 | I17: 0 | J17: 0 | K17: 0 | L17: 0 | M17: 0 | N17: 160 | O17: 160 | P17: 160 | Q17: 160 | R17: 160 | S17: 160 | T17: 160
D18: Bank Fees | H18: =SUM(I18:T18) -> 0
D19: Business Insurance | H19: =SUM(I19:T19) -> 0
D20: Auto Mileage (condo visits) | H20: =SUM(I20:T20) -> 0
D21: =D1&" IRS rate" -> 2020 IRS rate | E21: 0.56 | H21: =SUM(I21:T21) -> 0
H22: =SUM(I22:T22) -> 0
D23: Flooring | H23: =SUM(I23:T23) -> 0
D24: Paint | H24: =SUM(I24:T24) -> 0
D25: bathroom | H25: =SUM(I25:T25) -> 0
D26: electrical work | H26: =SUM(I26:T26) -> 0
D27: Paint & Repairs | H27: =SUM(I27:T27) -> 2000 | N27: 2000
H28: =SUM(I28:T28) -> 0
H29: =SUM(I29:T29) -> 0
H30: =SUM(I30:T30) -> 0
H31: =SUM(I31:T31) -> 0

Sheet OC-19
B1: =Summary!K5 -> 2019 | C1: 1 CAD= | D1: =1/1.3268 -> 0.7536931 | E1: USD (average rate in 2019) | G1: ="Olympic Court Condo "&B1&" ONLY" -> Olympic Court Condo 2019 ONLY
C2: GRAND TOTAL (USD) | D2: USD | F2: TOTAL | G2: Jan | H2: Feb | I2: Mar | J2: Apr | K2: May | L2: Jun | M2: July | N2: Aug | O2: Sep | P2: Oct | Q2: Nov | R2: Dec
B3: Rental Revenue (CAD) | C3: =D3 -> 13513.305 | D3: =F3/1.2965 -> 13513.305 | F3: =SUM(G3:R3) -> 17520 | G3: 1460 | H3: 1460 | I3: 1460 | J3: 1460 | K3: 1460 | L3: 1460 | M3: 1460 | N3: 1460 | O3: 1460 | P3: 1460 | Q3: 1460 | R3: 1460
B5: Total Expenses | C5: =D5+D19 -> 9015.7021 | D5: =E5/1.2965 -> 8083.0621 | E5: =SUM(E6:E27) -> 10479.69 | F5: =SUM(G5:R5) -> 9279.69 | G5: =SUM(G6:G27) -> 1636.72 | H5: =SUM(H6:H29) -> 436.72 | I5: =SUM(I6:I29) -> 436.72 | J5: =SUM(J6:J29) -> 436.72 | K5: =SUM(K6:K29) -> 436.72 | L5: =SUM(L6:L29) -> 436.72 | M5: =SUM(M6:M29) -> 436.72 | N5: =SUM(N6:N29) -> 436.72 | O5: =SUM(O6:O29) -> 436.72 | ... R5: =SUM(R6:R29) -> 3275.77
B6: Mortgage Interest - 2019 | E6: =F6 -> 2839.05 | F6: =SUM(G6:R6) -> 2839.05 | R6: 2839.05
B7: Home Insurance -2019 | E7: =F7 -> 1200 | F7: =SUM(G7:R7) -> 1200 | G7: 1200
B8: HoA - 2019 | E8: =F8 -> 2180.64 | F8: =SUM(G8:R8) -> 2180.64 | G8: 181.72 | H8: 181.72 | I8: 181.72 | J8: 181.72 | K8: 181.72 | L8: 181.72 | M8: 181.72 | N8: 181.72 | O8: 181.72 | P8: 181.72 | Q8: 181.72 | R8: 181.72
B9: Property Taxes - 2019 | E9: =F9 -> 1140 | F9: =SUM(G9:R9) -> 1140 | G9: 95 | H9: 95 | I9: 95 | J9: 95 | K9: 95 | L9: 95 | M9: 95 | N9: 95 | O9: 95 | P9: 95 | Q9: 95 | R9: 95
B10: PAYROLL | F10: =SUM(G10:R10) -> 0
B11: W2 Ethan Rose | F11: =SUM(G11:R11) -> 0
B12: Fed 76.44; FICA 62; Medicare 14.5 | F12: =SUM(G12:R12) -> 0
B13: Zach DeVita | F13: =SUM(G13:R13) -> 0
B14: 1099 Shirish Sharma | F14: =SUM(G14:R14) -> 0
B16: Temp Services | E16: =F16 -> 0 | F16: =SUM(G16:R16) -> 0
B17: Property Management - 2019 only | E17: =F17 -> 1920 | F17: =SUM(G17:R17) -> 1920 | G17: 160 | H17: 160 | I17: 160 | J17: 160 | K17: 160 | L17: 160 | M17: 160 | N17: 160 | O17: 160 | P17: 160 | Q17: 160 | R17: 160
B18: Bank Fees | F18: =SUM(G18:R18) -> 0
B19: Auto Mileage (condo visits in 2019) | C19: $0.58 per mile | D19: 932.64 | F19: =SUM(G19:R19) -> 0
F20: =SUM(G20:R20) -> 0
B21: Appliances | F21: =SUM(G21:R21) -> 0
B22: Flooring | F22: =SUM(G22:R22) -> 0
B23: Paint | F23: =SUM(G23:R23) -> 0
B24: bathroom | F24: =SUM(G24:R24) -> 0
B25: electrical work | F25: =SUM(G25:R25) -> 0
B26: Paint & Repairs | E26: 1200 | F26: =SUM(G26:R26) -> 0
F27: =SUM(G27:R27) -> 0

Sheet OC-18
B1: =Summary!L5 -> 2018 | C1: 1 CAD= | D1: =1/1.2965 -> 0.77130737 | E1: USD (average rate in 2018) | G1: ="Olympic Court Condo "&B1&" since 2012" -> Olympic Court Condo 2018 since 2012
C2: GRAND TOTAL (USD) | D2: USD | F2: TOTAL | G2: Jan | H2: Feb | I2: Mar | J2: Apr | K2: May | L2: Jun | M2: July | N2: Aug | O2: Sep | P2: Oct | Q2: Nov | R2: Dec
B3: Total Rental Revenue | C3: =D3 -> 7882.7613 | D3: =F3*D1 -> 7882.7613 | F3: =SUM(G3:R3) -> 10220 | G3: 0 | H3: 0 | I3: 0 | J3: 0 | K3: 0 | L3: 1460 | M3: 1460 | N3: 1460 | O3: 1460 | P3: 1460 | Q3: 1460 | R3: 1460
B5: Total Rental Expenses | C5: =D5+D45 -> 52623.603 | D5: =E5*D1 -> 43946.433 | E5: =SUM(E13:E53) -> 56976.55 | F5: =SUM(G5:R5) -> 44845.45 | G5: =SUM(G13:G55) -> 10882.2 | H5: =SUM(H13:H55) -> 2482.2 | I5: =SUM(I13:I55) -> 2482.2 | J5: =SUM(J13:J55) -> 2482.2 | K5: =SUM(K13:K55) -> 2482.2 | L5: =SUM(L13:L55) -> 5342.2 | M5: =SUM(M13:M55) -> 2642.2 | N5: =SUM(N13:N55) -> 2642.2 | ... R5: =SUM(R13:R55) -> 5481.25
B6: Mortgage Interest - 2012 | F6: =SUM(G6:R6) -> 2839.05 | R6: 2839.05
B7: Mortgage Interest - 2013 | F7: =SUM(G7:R7) -> 2839.05 | R7: 2839.05
B8: Mortgage Interest - 2014 | F8: =SUM(G8:R8) -> 2839.05 | R8: 2839.05
B9: Mortgage Interest - 2015 | F9: =SUM(G9:R9) -> 2839.05 | R9: 2839.05
B10: Mortgage Interest - 2016 | F10: =SUM(G10:R10) -> 2839.05 | R10: 2839.05
B11: Mortgage Interest - 2017 | F11: =SUM(G11:R11) -> 2839.05 | R11: 2839.05
B12: Mortgage Interest - 2018 | F12: =SUM(G12:R12) -> 2839.05 | R12: 2839.05
B13: Mortgage Interest Subtotal | E13: =SUM(F6:F12) -> 19873.35 | R13: 2839.05
B14: Home Insurance - 2012 | F14: =SUM(G14:R14) -> 1200 | G14: 1200
B15: Home Insurance - 2013 | F15: =SUM(G15:R15) -> 1200 | G15: 1200
B16: Home Insurance - 2014 | F16: =SUM(G16:R16) -> 1200 | G16: 1200
B17: Home Insurance - 2015 | F17: =SUM(G17:R17) -> 1200 | G17: 1200
B18: Home Insurance - 2016 | F18: =SUM(G18:R18) -> 1200 | G18: 1200
B19: Home Insurance - 2017 | F19: =SUM(G19:R19) -> 1200 | G19: 1200
B20: Home Insurance - 2018 | F20: =SUM(G20:R20) -> 1200 | G20: 1200
B21: Home Insurance Subtotal | E21: =F21 -> 8400 | F21: =SUM(F14:F20) -> 8400
B22: HoA - 2014 | F22: =SUM(G22:R22) -> 2180.64 | G22: 181.72 | H22: 181.72 | I22: 181.72 | J22: 181.72 | K22: 181.72 | L22: 181.72 | M22: 181.72 | N22: 181.72 | O22: 181.72 | P22: 181.72 | Q22: 181.72 | R22: 181.72
B23: HoA - 2015 | F23: =SUM(G23:R23) -> 2180.64 | G23: 181.72 | H23: 181.72 | I23: 181.72 | J23: 181.72 | K23: 181.72 | L23: 181.72 | M23: 181.72 | N23: 181.72 | O23: 181.72 | P23: 181.72 | Q23: 181.72 | R23: 181.72
B24: HoA - 2016 | F24: =SUM(G24:R24) -> 2180.64 | G24: 181.72 | H24: 181.72 | I24: 181.72 | J24: 181.72 | K24: 181.72 | L24: 181.72 | M24: 181.72 | N24: 181.72 | O24: 181.72 | P24: 181.72 | Q24: 181.72 | R24: 181.72
B25: HoA - 2017 | F25: =SUM(G25:R25) -> 2180.64 | G25: 181.72 | H25: 181.72 | I25: 181.72 | J25: 181.72 | K25: 181.72 | L25: 181.72 | M25: 181.72 | N25: 181.72 | O25: 181.72 | P25: 181.72 | Q25: 181.72 | R25: 181.72
B26: HoA - 2018 | F26: =SUM(G26:R26) -> 2180.64 | G26: 181.72 | H26: 181.72 | I26: 181.72 | J26: 181.72 | K26: 181.72 | L26: 181.72 | M26: 181.72 | N26: 181.72 | O26: 181.72 | P26: 181.72 | Q26: 181.72 | R26: 181.72
B27: HoA Fee Subtotal | E27: =F27 -> 10903.2 | F27: =SUM(F22:F26) -> 10903.2 | G27: =SUM(G22:G26) -> 908.6 | H27: =SUM(H22:H26) -> 908.6 | I27: =SUM(I22:I26) -> 908.6 | J27: =SUM(J22:J26) -> 908.6 | K27: =SUM(K22:K26) -> 908.6 | L27: =SUM(L22:L26) -> 908.6 | M27: =SUM(M22:M26) -> 908.6 | ... R27: =SUM(R22:R26) -> 908.6
B28: Property Taxes - 2012 | F28: =SUM(G28:R28) -> 1140 | G28: 95 | H28: 95 | I28: 95 | J28: 95 | K28: 95 | L28: 95 | M28: 95 | N28: 95 | O28: 95 | P28: 95 | Q28: 95 | R28: 95
B29: Property Taxes - 2013 | F29: =SUM(G29:R29) -> 1140 | G29: 95 | H29: 95 | I29: 95 | J29: 95 | K29: 95 | L29: 95 | M29: 95 | N29: 95 | O29: 95 | P29: 95 | Q29: 95 | R29: 95
B30: Property Taxes - 2014 | F30: =SUM(G30:R30) -> 1140 | G30: 95 | H30: 95 | I30: 95 | J30: 95 | K30: 95 | L30: 95 | M30: 95 | N30: 95 | O30: 95 | P30: 95 | Q30: 95 | R30: 95
B31: Property Taxes - 2015 | F31: =SUM(G31:R31) -> 1140 | G31: 95 | H31: 95 | I31: 95 | J31: 95 | K31: 95 | L31: 95 | M31: 95 | N31: 95 | O31: 95 | P31: 95 | Q31: 95 | R31: 95
B32: Property Taxes - 2016 | F32: =SUM(G32:R32) -> 1140 | G32: 95 | H32: 95 | I32: 95 | J32: 95 | K32: 95 | L32: 95 | M32: 95 | N32: 95 | O32: 95 | P32: 95 | Q32: 95 | R32: 95
B33: Property Taxes - 2017 | F33: =SUM(G33:R33) -> 1140 | G33: 95 | H33: 95 | I33: 95 | J33: 95 | K33: 95 | L33: 95 | M33: 95 | N33: 95 | O33: 95 | P33: 95 | Q33: 95 | R33: 95
B34: Property Taxes - 2018 | F34: =SUM(G34:R34) -> 1140 | G34: 95 | H34: 95 | I34: 95 | J34: 95 | K34: 95 | L34: 95 | M34: 95 | N34: 95 | O34: 95 | P34: 95 | Q34: 95 | R34: 95
B35: Property Tax Subtotal | E35: =SUM(F28:F34) -> 7980
B36: PAYROLL | F36: =SUM(G36:R36) -> 0
B37: W2 Ethan Rose | F37: =SUM(G37:R37) -> 0
B38: Fed 76.44; FICA 62; Medicare 14.5 | F38: =SUM(G38:R38) -> 0
B39: Zach DeVita | F39: =SUM(G39:R39) -> 0
B40: 1099 Shirish Sharma | F40: =SUM(G40:R40) -> 0
F41: =SUM(G41:R41) -> 0
B42: Temp Services | E42: =F42 -> 700 | F42: =SUM(G42:R42) -> 700 | L42: 700
B43: Property Management - 2018 only | E43: =F43 -> 1120 | F43: =SUM(G43:R43) -> 1120 | G43: 0 | H43: 0 | I43: 0 | J43: 0 | K43: 0 | L43: 160 | M43: 160 | N43: 160 | O43: 160 | P43: 160 | Q43: 160 | R43: 160
B44: Bank Fees | F44: =SUM(G44:R44) -> 0
B45: Auto Mileage (condo visits since 2012) | D45: 8677.17 | F45: =SUM(G45:R45) -> 0
F46: =SUM(G46:R46) -> 0
B47: Appliances | E47: 6000 | F47: =SUM(G47:R47) -> 0
B48: Flooring | F48: =SUM(G48:R48) -> 0
B49: Paint | F49: =SUM(G49:R49) -> 0
B50: bathroom | F50: =SUM(G50:R50) -> 0
B51: electrical work | F51: =SUM(G51:R51) -> 0
B52: Paint & Repairs | E52: =F52 -> 2000 | F52: =SUM(G52:R52) -> 2000 | L52: 2000
F53: =SUM(G53:R53) -> 0

Sheet Home Insurance
F3: 2023 | G3: 2022 | H3: 2021 | I3: 2020 | J3: 2019 | K3: 2018 | L3: 2017
C4: Mortgage
C13: Insurance | E13: Woodridge | G13: 1779 | H13: 1667 | I13: 1686 | J13: 1750 | K13: 1637 | L13: 1402
E14: Cherry | G14: 1519
E15: Olympic
C19: Real estate Taxes

Sheet Robertos
E1: 2018 only
E2: Jan | F2: Feb | G2: Mar | H2: Apr | I2: May | J2: Jun | K2: July | L2: Aug | M2: Sep | N2: Oct | O2: Nov | P2: Dec
C3: Total Revenue | D3: 26381.74
C4: Total Expenses | D4: =SUM(D6:D54) -> 70963.66
C6: RENT | D6: 7800
C7: ELECTRICITY | D7: =1084.17 -> 1084.17
C8: WASTE | D8: $-
C9: EQUIPMENT LEASING | D9: =SUM(E9:I9)+225+930.91 -> 1155.91
C10: Mobile Device (moto) | D10: 900
C11: Appliance Maintenance | D11: =SUM(E11:H11) -> 0
C12: Business Insurance | D12: =476.95 -> 476.95
C13: Coca Cola Machine | D13: 422.58
C15: WA DOR | D15: 9325.49
C16: 2017 Excise | D16: 3056.02
C17: Garnishment Fee | D17: 625
C19: Food Inventory | D19: =SUM(E19:H19)+418+239.94+102.16 -> 760.1
C20: Supplies | D20: 115.38
C21: STATIONARIES | D21: =21.9 -> 21.9
C22: PAYROLL
C23: Wages | D23: =912.6+M23 -> 912.6
C24: SS withheld by ADP | D24: 56.59
C25: Medicare Tax Withheld by ADP | D25: 13.23
C26: Fed Tax Withheld | D26: 1.98
C27: TEMP SERVICES | D27: 7131
C28: ADP Fees | D28: 464.27
C29: Bank Fees | D29: 1408.5
C30: Unclaimed Contract Labor | D30: =74.48+488.4+97.88+366.67+332.46+573.33+40+659.98+500 -> 3133.2
C31: LAUNDRY | D31: =SUM(E31:H31) -> 0
C32: Professional Fees | D32: =645 -> 645
C34: WEB HOSTING | D34: 360
C35: Comcast Business BROADBAND | D35: 884.19
C36: PHONE | D36: 420
B37: 0.5 | C37: CELLULAR | D37: 64.07
C38: Digital Ads | D38: $-
D39: $-
C42: Asbestos | D42: 750
C43: Flooring Cement | D43: =1000+775 -> 1775
C44: Paint | D44: =154.34+1600+1592 -> 3346.34
C45: Ceiling Speakers | D45: 306.45
C46: low voltage wiring | D46: 213
C47: iPads Two | D47: 2000
C48: iPad Stand | D48: 1000
C49: Cash Drawer | D49: 210.99
C50: Bathroom Holder | D50: 23.75
C52: Furniture Fraud | D52: 2600
C53: Remodeling Fraud | D53: 17500

Sheet Office Equipments
E1: Date Aquired | F1: Price Paid
C2: Office Furnitures
C3: Hutch & Desk
C4: Chair
C5: Bookshelf
C6: Corner Table
C7: Leather Pad
C8: Web cam
C9: overhead lamps and lights
C10: monitor
D11: LG Extra-wide
D12: LG Wide
D13: LG
D14: Samsung
D15: ACER
D16: ACER
C17: Laptop
C18: iPad
C19: iPad 2
C20: iPhones
C21: Android
C22: Samsung Tablet
C23: Stationaries
C24: Printer
C25: Cartridge
C26: wifi Setup
C27: Mouse
C28: Keyboard
... C33: Graphics Cards

Sheet Real Estates
D2: LAKE HILLS | E2: WOODRIDGE | F2: CHERRY CREST | G2: OLYMPIC COURT | H2: RUDINS LOUNGE | I2: EVOLVE | J2: USHAKAMAL | K2: GREEN HOME
C3: Cost basis
C5: Mortgage Interest
C7: Taxes
C9: Expenses

Sheet PB_CACHE_JS
